Workbook

Sheet Read me
A1: Auction Retest indicator on FxPro MT5 GOLD, 4 Jan 2021 - 2 Oct 2026 (your 1-minute data): profitable settings per goal, accuracy, TP1-TP4, streaks, recovery rules
A3: HOW TO USE THIS FILE:
A4: 1. Strategy guide: pick your goal (most profit, shortest losing streak, longest winning streak, highest win rate, most trades, every year positive, smoothest, simplest,
A5: one session only) and your timeframe. Click the strategy to jump to its column.
A6: 2. <TF> strategies (M1, M5, M15, H1): one column per strategy. Every indicator input is listed with its exact name; yellow = change it to that value, grey = keep the default.
A7: Below the settings: what to expect - trades, win %, TP1-TP4 reached, R per trade in each half and each year, longest winning and losing streaks, deepest fall, $ results.
A8: 3. All profitable settings: every setting that passed the profit rule, with a filter on each column (e.g. longest losing streak <= 6).
A9: 4. Recovery rules, Rule C split test and Crooks A and B test: money management (loss recovery). The rest of the sheets are the research detail.
A11: DATA: 2,037,975 one-minute bars from your MT5 export; 441 fake 00:00 "daily summary" bars removed. M5 / M15 / H1 were built from M1 on the broker clock (EET, UTC+2 / UTC+3 in summer).
A12: ENGINE: the same signal engine as the TradingView indicator / strategy and the MT5 EA (Python twin, checked trade-for-trade against the EA). VWAP and sessions reset at broker midnight; VWAP weights = tick volume.
A13: COSTS: the spread recorded in the MT5 data at each fill bar, as a share of the stop distance ("after spread"). On M1 / M5 the stop is small, so the spread eats a large part of every trade.
A14: DEFINITIONS: R = result in units of the stop distance. TPk hit = price reached that target after the fill bar and before the stop. Win = closed at the final target.
... A31: best = strategy S1 "Most profit", low-streak = the "Shortest losing streak" strategy) | TP1-TP4 | Settings sweep | Combinations | Exits | Robustness | Hours | Streak math

Sheet Strategy guide
A1: Strategy guide: which settings to use for which goal (FxPro MT5 gold, 2021-2026, after the spread)
A2: Part 1: for each goal and timeframe, the strategy to use (click it for the exact settings on the timeframe sheet). Part 2: every strategy with its key numbers. Every strategy is profitable after spread in 2021-23 and 2024-26 and positive in at least 4 of 6 years. "-" = no profitable setting for that goal.
A4: PART 1 - pick by goal
A5: Goal | B5: M1 | C5: M5 | D5: M15 | E5: H1
A6: Most profit | B6: M1-S1: W/L streak 8/14, +0.057 R, 1.32/day | C6: M5-S1: W/L streak 7/21, +0.087 R, 0.99/day | D6: M15-S1: W/L streak 8/17, +0.134 R, 0.93/day | E6: H1-S1: W/L streak 8/8, +0.337 R, 0.13/day
A7: Shortest losing streak | B7: M1-S2: W/L streak 7/12, +0.052 R, 1.21/day | C7: M5-S2: W/L streak 11/9, +0.045 R, 1.14/day | D7: M15-S2: W/L streak 18/5, +0.066 R, 0.77/day | E7: H1-S2: W/L streak 12/3, +0.176 R, 0.13/day
A8: Shortest losing streak - indicator only | B8: M1-S2: W/L streak 7/12, +0.052 R, 1.21/day | C8: M5-S2: W/L streak 11/9, +0.045 R, 1.14/day | D8: M15-S3: W/L streak 6/8, +0.132 R, 0.76/day | E8: H1-S3: W/L streak 7/6, +0.232 R, 0.15/day
A9: Longest winning streak | B9: M1-S1: W/L streak 8/14, +0.057 R, 1.32/day | C9: M5-S2: W/L streak 11/9, +0.045 R, 1.14/day | D9: M15-S4: W/L streak 22/6, +0.070 R, 0.81/day | E9: H1-S4: W/L streak 18/6, +0.108 R, 0.18/day
A10: Highest win rate | B10: M1-S1: W/L streak 8/14, +0.057 R, 1.32/day | C10: M5-S2: W/L streak 11/9, +0.045 R, 1.14/day | D10: M15-S5: W/L streak 21/5, +0.055 R, 0.93/day | E10: H1-S5: W/L streak 13/4, +0.174 R, 0.13/day
A11: Most trades a day | B11: M1-S3: W/L streak 7/14, +0.044 R, 1.42/day | C11: M5-S3: W/L streak 6/13, +0.072 R, 1.22/day | D11: M15-S6: W/L streak 10/11, +0.062 R, 1.20/day | E11: H1-S6: W/L streak 4/16, +0.119 R, 0.36/day
A12: Every year positive | B12: - | C12: M5-S2: W/L streak 11/9, +0.045 R, 1.14/day | D12: M15-S7: W/L streak 8/17, +0.146 R, 0.93/day | E12: H1-S1: W/L streak 8/8, +0.337 R, 0.13/day
A13: Smoothest | B13: M1-S1: W/L streak 8/14, +0.057 R, 1.32/day | C13: M5-S1: W/L streak 7/21, +0.087 R, 0.99/day | D13: M15-S3: W/L streak 6/8, +0.132 R, 0.76/day | E13: H1-S7: W/L streak 10/7, +0.309 R, 0.14/day
A14: Simplest | B14: M1-S4: W/L streak 8/14, +0.041 R, 1.35/day | C14: M5-S4: W/L streak 8/20, +0.058 R, 1.00/day | D14: M15-S8: W/L streak 6/18, +0.084 R, 0.79/day | E14: H1-S8: W/L streak 5/12, +0.105 R, 0.34/day
A15: Asia session only | B15: - | C15: - | D15: M15-S9: W/L streak 6/21, +0.051 R, 0.48/day | E15: -
A16: London session only | B16: - | C16: - | D16: - | E16: -
... A18: London close session only | B18: M1-S1: W/L streak 8/14, +0.057 R, 1.32/day | C18: - | D18: - | E18: -
A20: PART 2 - every strategy
A21: Strategy | B21: Timeframe | C21: Goal(s) | D21: Works in | E21: Trades per day | F21: Profitable trades % | G21: TP1 reached % | H21: R per trade 2021-23 | I21: R per trade 2024-26 | J21: R per trade 2021-2026 | K21: Years positive | L21: Longest winning streak | M21: Longest losing streak | N21: Deepest fall (R) | O21: Fixed $50: net ($) | P21: Rule C split 3, $500 cap, Start again: net ($) | Q21: ... its deepest fall % | R21: Crooks A, $500 cap, Start again: net ($) | S21: ... its deepest fall % | T21: Settings to change (indicator names)
A22: M1-S1 | B22: M1 | C22: Most profit + Longest winning streak + Highest win rate + Smoothest + London close session only | D22: Indicator, strategy and EA | E22: 1.319 | F22: 0.3662 | G22: 0.6297 | H22: 0.0545 | I22: 0.0601 | J22: 0.0573 | K22: 4 | L22: 8 | M22: 14 | N22: 30.01 | O22: 5441.57 | P22: 17859.4 | Q22: 0.4614 | R22: 15765.65 | S22: 0.1767 | T22: Stop Distance (x ATR) = 4 | Cooldown After Exit (bars) = 8 | Anchor = Month | Trade Only In Kill Zones (Indian time) = On: London Close 19:30-21:30
A23: M1-S2 | B23: M1 | C23: Shortest losing streak + Shortest losing streak - indicator only | D23: Indicator, strategy and EA | E23: 1.213 | F23: 0.3646 | G23: 0.626 | H23: 0.0286 | I23: 0.075 | J23: 0.0516 | K23: 4 | L23: 7 | M23: 12 | N23: 30.73 | O23: 4561.27 | P23: 29940.03 | Q23: 0.4104 | R23: 965.26 | S23: 0.3664 | T23: Stop Distance (x ATR) = 4 | Cooldown After Exit (bars) = 30 | Anchor = Month | Trade Only In Kill Zones (Indian time) = On: London Close 19:30-21:30
A24: M1-S3 | B24: M1 | C24: Most trades a day | D24: Indicator, strategy and EA | E24: 1.422 | F24: 0.3614 | G24: 0.6239 | H24: 0.0632 | I24: 0.0249 | J24: 0.0439 | K24: 4 | L24: 7 | M24: 14 | N24: 34.45 | O24: 4470.32 | P24: 25623.29 | Q24: 0.3857 | R24: 8960.71 | S24: 0.2492 | T24: Min Displacement Range (x ATR) = 0.4 | Stop Distance (x ATR) = 4 | Anchor = Month | Trade Only In Kill Zones (Indian time) = On: London Close 19:30-21:30
A25: M1-S4 | B25: M1 | C25: Simplest | D25: Indicator, strategy and EA | E25: 1.351 | F25: 0.3609 | G25: 0.6261 | H25: 0.0489 | I25: 0.0341 | J25: 0.0415 | K25: 4 | L25: 8 | M25: 14 | N25: 37.97 | O25: 4040.42 | P25: 25252.4 | Q25: 0.4438 | R25: 10595.14 | S25: 0.1987 | T25: Stop Distance (x ATR) = 4 | Anchor = Month | Trade Only In Kill Zones (Indian time) = On: London Close 19:30-21:30
A27: M5-S1 | B27: M5 | C27: Most profit + Smoothest + New York session only | D27: Indicator, strategy and EA | E27: 0.991 | F27: 0.3207 | G27: 0.6291 | H27: 0.0969 | I27: 0.0776 | J27: 0.0872 | K27: 4 | L27: 7 | M27: 21 | N27: 37.22 | O27: 6136.32 | P27: 51480.28 | Q27: 0.3588 | R27: 9244.49 | S27: 0.3077 | T27: Stop Distance (x ATR) = 2.4 | TP4 (R) = 2.5 | Anchor = Month | Entry Price = Market (next bar open) | Skip Choppy Sessions: Max VWAP Crosses Per 100 Bars = On, 8 | Trade Only Between (Time Zone = Asia/Kolkata) = On, 1830-2230
A28: M5-S2 | B28: M5 | C28: Shortest losing streak + Shortest losing streak - indicator only + Longest winning streak + Highest win rate + Every year positive | D28: Indicator, strategy and EA | E28: 1.139 | F28: 0.5236 | G28: 0.6277 | H28: 0.0465 | I28: 0.0434 | J28: 0.045 | K28: 6 | L28: 11 | M28: 9 | N28: 25.77 | O28: 3667.19 | P28: 24417.33 | Q28: 0.341 | R28: 2116.38 | S28: 0.1925 | T28: Stop Distance (x ATR) = 2.4 | Anchor = Month | Entry Price = Market (next bar open) | When TP2 Hits, Move Stop To (R) = On, 0.6 R | Skip Choppy Sessions: Max VWAP Crosses Per 100 Bars = On, 8 | Trade Only Between (Time Zone = Asia/Kolkata) = On, 1830-2230
A29: M5-S3 | B29: M5 | C29: Most trades a day | D29: Indicator, strategy and EA | E29: 1.215 | F29: 0.369 | G29: 0.6299 | H29: 0.066 | I29: 0.0786 | J29: 0.0723 | K29: 4 | L29: 6 | M29: 13 | N29: 37.95 | O29: 6275.5 | P29: 38465.04 | Q29: 0.4522 | R29: 14021.94 | S29: 0.1534 | T29: Momentum Lookback (bars) = 5 | Stop Distance (x ATR) = 2.4 | Anchor = Month | Entry Price = Market (next bar open) | Skip Choppy Sessions: Max VWAP Crosses Per 100 Bars = On, 8 | Trade Only Between (Time Zone = Asia/Kolkata) = On, 1830-2230
A30: M5-S4 | B30: M5 | C30: Simplest | D30: Indicator, strategy and EA | E30: 1.002 | F30: 0.3683 | G30: 0.6263 | H30: 0.0696 | I30: 0.045 | J30: 0.0578 | K30: 4 | L30: 8 | M30: 20 | N30: 44.7 | O30: 4134.19 | P30: 5171.53 | Q30: 0.4951 | R30: 5156.73 | S30: 0.2282 | T30: Anchor = Month | Entry Price = Market (next bar open) | Skip Choppy Sessions: Max VWAP Crosses Per 100 Bars = On, 8 | Skip When The 1h EMA20 Moved More Than ... ATR In 3 Hours = On, 1.4 | Trade Only Between (Time Zone = Asia/Kolkata) = On, 1830-2230
A32: M15-S1 | B32: M15 | C32: Most profit | D32: Indicator, strategy and EA | E32: 0.935 | F32: 0.4539 | G32: 0.6628 | H32: 0.1353 | I32: 0.1324 | J32: 0.1338 | K32: 6 | L32: 8 | M32: 17 | N32: 23.23 | O32: 9076.9 | P32: 67852.71 | Q32: 0.3608 | R32: 12348.06 | S32: 0.1619 | T32: Stop Distance (x ATR) = 4 | Half Stop (x ATR) = 1.2 | When TP3 Hits, Move Stop To (R) = On, 1 R
A33: M15-S2 | B33: M15 | C33: Shortest losing streak | D33: Strategy and EA only (partial close) | E33: 0.766 | F33: 0.6614 | G33: 0.6614 | H33: 0.0648 | I33: 0.0682 | J33: 0.0664 | K33: 6 | L33: 18 | M33: 5 | N33: 22.61 | O33: 3704.09 | P33: 15152.96 | Q33: 0.3727 | R33: 3169.3 | S33: 0.1444 | T33: Min CMO (clean move) = 30 | Stop Distance (x ATR) = 4 | Half Stop (x ATR) = 1.2 | When TP3 Hits, Move Stop To (R) = On, 1 R | Skip When The 1h EMA20 Moved More Than ... ATR In 3 Hours = On, 1.2 | Close % At TP1 = 70
A34: M15-S3 | B34: M15 | C34: Shortest losing streak - indicator only + Smoothest | D34: Indicator, strategy and EA | E34: 0.76 | F34: 0.4517 | G34: 0.6537 | H34: 0.1343 | I34: 0.1294 | J34: 0.1319 | K34: 6 | L34: 6 | M34: 8 | N34: 14.36 | O34: 7274.17 | P34: 47681.14 | Q34: 0.2564 | R34: 11592.75 | S34: 0.0624 | T34: Stop Distance (x ATR) = 4 | Half Stop (x ATR) = 1.2 | VWAP Slope Bars = 0 | When TP3 Hits, Move Stop To (R) = On, 1 R | Skip When The 1h EMA20 Moved More Than ... ATR In 3 Hours = On, 1.2
A35: M15-S4 | B35: M15 | C35: Longest winning streak | D35: Strategy and EA only (partial close) | E35: 0.813 | F35: 0.6628 | G35: 0.6628 | H35: 0.0765 | I35: 0.0639 | J35: 0.0702 | K35: 6 | L35: 22 | M35: 6 | N35: 24.32 | O35: 4150.61 | P35: 25426.18 | Q35: 0.3976 | R35: 4529.84 | S35: 0.1008 | T35: Stop Distance (x ATR) = 4 | Half Stop (x ATR) = 1.2 | When TP3 Hits, Move Stop To (R) = On, 1 R | Skip Choppy Sessions: Max VWAP Crosses Per 100 Bars = On, 16 | Close % At TP1 = 70
... A49: H1-S8 | B49: H1 | C49: Simplest | D49: Indicator, strategy and EA | E49: 0.335 | F49: 0.3755 | G49: 0.6104 | H49: 0.097 | I49: 0.1129 | J49: 0.1051 | K49: 4 | L49: 5 | M49: 12 | N49: 23.94 | O49: 2557.3 | P49: 1289.09 | Q49: 0.2886 | R49: 3966.05 | S49: 0.1544 | T49: Anchor = Month | Don't Chase: Skip Signals Beyond ... sigma From VWAP = On, 2.2

Sheet M1 strategies
A1: M1: profitable settings for each scenario - what to set in the indicator and what to expect
A2: Pick the column for your goal and read down. Yellow cells = change this input to the value shown; grey = leave the default. All results are 2021-2026 on FxPro gold after the spread, and every setting here was profitable in both 2021-23 and 2024-26 with at least 4 of 6 years positive. Expect live results to be weaker.
A4: Group | B4: Input (exactly as in the indicator) | C4: MT5 EA input | D4: Default | E4: M1-S1 | F4: M1-S2 | G4: M1-S3 | H4: M1-S4
A5: WHEN TO USE IT
B6: Scenario | E6: Most profit + Longest winning streak + Highest win rate + Smoothest + London close session only | F6: Shortest losing streak + Shortest losing streak - indicator only | G6: Most trades a day | H6: Simplest
B7: Use it when | E7: Best R per trade after spread in both halves (ranked by the weaker half); the main recommendation. The most wins in a row. The largest share of profitable trades. The best profit for the deepest fall from a peak (total R / max drawdown in R), among the 25 strongest settings. Trades only in the London close session (Indian time); for traders who can only watch that session. | F7: The fewest losses in a row, keeping a fair profit. May use a partial close (strategy / EA only). As above, without a partial close, so the indicator shows the same trades and results. | G7: The most trades while still profitable in both halves. | H7: The fewest settings to change.
B8: Works in | E8: Indicator, strategy and EA | F8: Indicator, strategy and EA | G8: Indicator, strategy and EA | H8: Indicator, strategy and EA
A9: SETTINGS - change the yellow cells, leave the rest at the default
A10: SIGNAL MODEL | B10: Structure Lookback (bars) | C10: InpStructLen | D10: 10 | E10: 10 | F10: 10 | G10: 10 | H10: 10
B11: Signal Break Lookback (bars) | C11: InpBrkLen | D11: 6 | E11: 6 | F11: 6 | G11: 6 | H11: 6
B12: Entry Level Lookback (bars) | C12: InpEntryLen | D12: 6 | E12: 6 | F12: 6 | G12: 6 | H12: 6
B13: Retest Window (bars) | C13: InpRetestBars | D13: 5 | E13: 5 | F13: 5 | G13: 5 | H13: 5
B14: Min Displacement Range (x ATR) | C14: InpDispAtr | D14: 0.8 | E14: 0.8 | F14: 0.8 | G14: 0.4 | H14: 0.8
B15: Min Displacement Body (% of range) | C15: InpBodyPct | D15: 55 | E15: 55 | F15: 55 | G15: 55 | H15: 55
B16: Max Close Distance From Extreme (% of range) | C16: InpClosePct | D16: 25 | E16: 25 | F16: 25 | G16: 25 | H16: 25
B17: Momentum Lookback (bars) | C17: InpMomLen | D17: 10 | E17: 10 | F17: 10 | G17: 10 | H17: 10
B18: Min (x ATR) [same line as Momentum Lookback] | C18: InpMomAtr | D18: 0.85 | E18: 0.85 | F18: 0.85 | G18: 0.85 | H18: 0.85
B19: Min CMO (clean move) | C19: InpCmoMin | D19: 20 | E19: 20 | F19: 20 | G19: 20 | H19: 20
B20: Same-Direction Re-arm | C20: InpRearm | D20: Keep first | E20: Keep first | F20: Keep first | G20: Keep first | H20: Keep first
B21: Stop Mode | C21: InpStopMode | D21: ATR Model | E21: ATR Model | F21: ATR Model | G21: ATR Model | H21: ATR Model
B22: Stop Distance (x ATR) | C22: InpStopAtr | D22: 1.8 | E22: 4 | F22: 4 | G22: 4 | H22: 4
... B46: Shorts | C46: InpAllowShort | D46: On | E46: On | F46: On | G46: On | H46: On
A47: VWAP | B47: Anchor | C47: InpVwapAnchor | D47: Session | E47: Month | F47: Month | G47: Month | H47: Month
B48: Source | C48: InpVwapSrc | D48: hlc3 | E48: hlc3 | F48: hlc3 | G48: hlc3 | H48: hlc3
A49: ENTRY PRICE | B49: Entry Price | C49: InpEntryMode | D49: Model (body mid or 6-bar level) | E49: Model (body mid or 6-bar level) | F49: Model (body mid or 6-bar level) | G49: Model (body mid or 6-bar level) | H49: Model (body mid or 6-bar level)
B50: Custom % (0 = close, 50 = mid, 100 = low/high) | C50: InpEntryPct | D50: 50 | E50: 50 | F50: 50 | G50: 50 | H50: 50
A51: TARGETS, EXIT AND STOP MOVES | B51: TP1 | C51: InpTp1R | D51: 0.6 | E51: 0.6 | F51: 0.6 | G51: 0.6 | H51: 0.6
B52: TP2 | C52: InpTp2R | D52: 1 | E52: 1 | F52: 1 | G52: 1 | H52: 1
B53: TP3 | C53: InpTp3R | D53: 1.5 | E53: 1.5 | F53: 1.5 | G53: 1.5 | H53: 1.5
B54: TP4 | C54: InpTp4R | D54: 2 | E54: 2 | F54: 2 | G54: 2 | H54: 2
B55: Final Exit At | C55: InpExitAt | D55: TP4 | E55: TP4 | F55: TP4 | G55: TP4 | H55: TP4
B56: When TP1 Hits, Move Stop To (R) [tick box] | C56: InpMv1On | D56: Off | E56: Off | F56: Off | G56: Off | H56: Off
B57: ... value (R) [same line] | C57: InpMv1R | D57: 0 | E57: 0 | F57: 0 | G57: 0 | H57: 0
B58: When TP2 Hits, Move Stop To (R) [tick box] | C58: InpMv2On | D58: Off | E58: Off | F58: Off | G58: Off | H58: Off
B59: ... value (R) [same line] | C59: InpMv2R | D59: 0.6 | E59: 0.6 | F59: 0.6 | G59: 0.6 | H59: 0.6
B60: When TP3 Hits, Move Stop To (R) [tick box] | C60: InpMv3On | D60: Off | E60: Off | F60: Off | G60: Off | H60: Off
B61: ... value (R) [same line] | C61: InpMv3R | D61: 1 | E61: 1 | F61: 1 | G61: 1 | H61: 1
A62: ACCURACY FILTERS | B62: Don't Chase: Skip Signals Beyond [tick box] | C62: InpNoChase | D62: Off | E62: Off | F62: Off | G62: Off | H62: Off
B63: σ From VWAP [same line] | C63: InpNoChaseSig | D63: 2.4 | E63: 2.4 | F63: 2.4 | G63: 2.4 | H63: 2.4
B64: After A Loss, No Same-Direction Trade Until A Win | C64: InpLossBlock | D64: Off | E64: Off | F64: Off | G64: Off | H64: Off
B65: Skip Signals Too Close To VWAP: Min Distance [tick box] | C65: InpMinVwOn | D65: Off | E65: Off | F65: Off | G65: Off | H65: Off
B66: x ATR [same line] | C66: InpMinVwAtr | D66: 1 | E66: 1 | F66: 1 | G66: 1 | H66: 1
B67: Skip Choppy Sessions: Max VWAP Crosses [tick box] | C67: InpChopOn | D67: Off | E67: Off | F67: Off | G67: Off | H67: Off
B68: Per 100 Bars [same line] | C68: InpChopMax | D68: 12 | E68: 12 | F68: 12 | G68: 12 | H68: 12
B69: Skip When The 1h EMA20 Moved More Than [tick box] | C69: InpEmaOn | D69: Off | E69: Off | F69: Off | G69: Off | H69: Off
B70: ATR In 3 Hours [same line] | C70: InpEmaMax | D70: 1.65 | E70: 1.65 | F70: 1.65 | G70: 1.65 | H70: 1.65
A71: DAYS AND HOURS | B71: Time Zone | C71: InpUserGMT = 5.5 | D71: Asia/Kolkata | E71: Asia/Kolkata | F71: Asia/Kolkata | G71: Asia/Kolkata | H71: Asia/Kolkata
B72: Trade Only On The Ticked Days | C72: InpDayOn | D72: Off | E72: Off | F72: Off | G72: Off | H72: Off
B73: Mon Tue Wed Thu Fri Sat Sun [ticks] | C73: InpMon ... InpSun | D73: all ticked | E73: all ticked | F73: all ticked | G73: all ticked | H73: all ticked
B74: Trade Only Between [tick box] | C74: InpHoursOn | D74: Off | E74: Off | F74: Off | G74: Off | H74: Off
B75: session, Indian time [same line] | C75: InpStartH:M - InpEndH:M | D75: 0600-2300 | E75: 0600-2300 | F75: 0600-2300 | G75: 0600-2300 | H75: 0600-2300
B76: Trade Only In Kill Zones (Indian time) | C76: InpKzOn | D76: Off | E76: On | F76: On | G76: On | H76: On
B77: Asia 05:30-09:30 | C77: InpKzAsia | D77: On | E77: Off | F77: Off | G77: Off | H77: Off
B78: London 11:30-14:30 | C78: InpKzLon | D78: On | E78: Off | F78: Off | G78: Off | H78: Off
B79: New York 16:30-19:30 | C79: InpKzNy | D79: On | E79: Off | F79: Off | G79: Off | H79: Off
B80: London Close 19:30-21:30 | C80: InpKzLc | D80: On | E80: On | F80: On | G80: On | H80: On
B81: Shift All Kill Zones (hours) | C81: InpKzShift | D81: 0 | E81: 0 | F81: 0 | G81: 0 | H81: 0
A82: PARTIAL PROFITS (strategy / EA only) | B82: Close % At TP1 | C82: InpP1 | D82: 0 | E82: 0 | F82: 0 | G82: 0 | H82: 0
B83: Close % At TP2 | C83: InpP2 | D83: 0 | E83: 0 | F83: 0 | G83: 0 | H83: 0
B84: Close % At TP3 | C84: InpP3 | D84: 0 | E84: 0 | F84: 0 | G84: 0 | H84: 0
A85: WHAT TO EXPECT - 2021-2026, FxPro gold, after the spread (blue = backtest result, black = formula)
B86: Trades | E86: 1958 | F86: 1802 | G86: 2111 | H86: 2006
B87: Trades per day | E87: =E86/1485 -> 1.3185185 | F87: =F86/1485 -> 1.213468 | G87: =G86/1485 -> 1.4215488 | H87: =H86/1485 -> 1.3508418
B88: Wins (closed at the final target) | E88: 717 | F88: 657 | G88: 763 | H88: 724
B89: Win % (closed at the final target) | E89: =IF(E86=0,"",E88/E86) -> 0.36618999 | F89: =IF(F86=0,"",F88/F86) -> 0.36459489 | G89: =IF(G86=0,"",G88/G86) -> 0.36144008 | H89: =IF(H86=0,"",H88/H86) -> 0.36091725
B90: Profitable trades | E90: 717 | F90: 657 | G90: 763 | H90: 724
B91: Profitable trades % | E91: =IF(E86=0,"",E90/E86) -> 0.36618999 | F91: =IF(F86=0,"",F90/F86) -> 0.36459489 | G91: =IF(G86=0,"",G90/G86) -> 0.36144008 | H91: =IF(H86=0,"",H90/H86) -> 0.36091725
B92: TP1 reached (count) | E92: 1233 | F92: 1128 | G92: 1317 | H92: 1256
B93: TP1 reached % (TP1 = R shown in TARGETS) | E93: =IF(E86=0,"",E92/E86) -> 0.62972421 | F93: =IF(F86=0,"",F92/F86) -> 0.62597114 | G93: =IF(G86=0,"",G92/G86) -> 0.62387494 | H93: =IF(H86=0,"",H92/H86) -> 0.62612164
B94: TP2 reached (count) | E94: 1020 | F94: 933 | G94: 1084 | H94: 1040
B95: TP2 reached % (TP2 = R shown in TARGETS) | E95: =IF(E86=0,"",E94/E86) -> 0.52093973 | F95: =IF(F86=0,"",F94/F86) -> 0.51775805 | G95: =IF(G86=0,"",G94/G86) -> 0.51350071 | H95: =IF(H86=0,"",H94/H86) -> 0.51844467
B96: TP3 reached (count) | E96: 834 | F96: 764 | G96: 893 | H96: 848
B97: TP3 reached % (TP3 = R shown in TARGETS) | E97: =IF(E86=0,"",E96/E86) -> 0.42594484 | F97: =IF(F86=0,"",F96/F86) -> 0.42397336 | G97: =IF(G86=0,"",G96/G86) -> 0.42302226 | H97: =IF(H86=0,"",H96/H86) -> 0.4227318
B98: TP4 reached (count) | E98: 717 | F98: 657 | G98: 763 | H98: 724
B99: TP4 reached % (TP4 = R shown in TARGETS) | E99: =IF(E86=0,"",E98/E86) -> 0.36618999 | F99: =IF(F86=0,"",F98/F86) -> 0.36459489 | G99: =IF(G86=0,"",G98/G86) -> 0.36144008 | H99: =IF(H86=0,"",H98/H86) -> 0.36091725
B100: Breakeven exits (stop moved to entry) | E100: 0 | F100: 0 | G100: 0 | H100: 0
B101: Total R after spread | E101: 112.153 | F101: 93.003 | G101: 92.736 | H101: 83.214
B102: R per trade after spread, 2021-2026 | E102: =IF(E86=0,"",E101/E86) -> 0.057279367 | F102: =IF(F86=0,"",F101/F86) -> 0.051610988 | G102: =IF(G86=0,"",G101/G86) -> 0.043929891 | H102: =IF(H86=0,"",H101/H86) -> 0.041482552
B103: 2021-23 trades | E103: 980 | F103: 909 | G103: 1048 | H103: 1001
B104: 2021-23 total R after spread | E104: 53.406 | F104: 26.001 | G104: 66.229 | H104: 48.942
B105: R per trade, 2021-23 | E105: =IF(E103=0,"",E104/E103) -> 0.054495918 | F105: =IF(F103=0,"",F104/F103) -> 0.02860396 | G105: =IF(G103=0,"",G104/G103) -> 0.063195611 | H105: =IF(H103=0,"",H104/H103) -> 0.048893107
B106: 2024-26 trades | E106: 978 | F106: 893 | G106: 1063 | H106: 1005
B107: 2024-26 total R after spread | E107: 58.747 | F107: 67.002 | G107: 26.507 | H107: 34.271
B108: R per trade, 2024-26 | E108: =IF(E106=0,"",E107/E106) -> 0.060068507 | F108: =IF(F106=0,"",F107/F106) -> 0.075030235 | G108: =IF(G106=0,"",G107/G106) -> 0.02493603 | H108: =IF(H106=0,"",H107/H106) -> 0.034100498
B109: R per trade if live costs are 0.05 R higher | E109: =IF(E102="","",E102-0.05) -> 0.0072793667 | F109: =IF(F102="","",F102-0.05) -> 0.0016109878 | G109: =IF(G102="","",G102-0.05) -> -0.006070109 | H109: =IF(H102="","",H102-0.05) -> -0.0085174477
B110: 2021: total R after spread | E110: -2.26 | F110: -7.72 | G110: -8.12 | H110: -9.68
B111: 2022: total R after spread | E111: 13.54 | F111: 16.51 | G111: 16.25 | H111: 11.04
B112: 2023: total R after spread | E112: 42.13 | F112: 17.21 | G112: 58.11 | H112: 47.58
B113: 2024: total R after spread | E113: -0.81 | F113: -0.2 | G113: -9.47 | H113: -16.03
B114: 2025: total R after spread | E114: 35.35 | F114: 49.8 | G114: 11.93 | H114: 24.17
B115: 2026: total R after spread | E115: 24.21 | F115: 17.4 | G115: 24.05 | H115: 26.14
B116: Years positive (of 6) | E116: =COUNTIF(E110:E115,">0") -> 4 | F116: =COUNTIF(F110:F115,">0") -> 4 | G116: =COUNTIF(G110:G115,">0") -> 4 | H116: =COUNTIF(H110:H115,">0") -> 4
B117: Longest winning streak | E117: 8 | F117: 7 | G117: 7 | H117: 8
B118: Longest losing streak | E118: 14 | F118: 12 | G118: 14 | H118: 14
B119: Winning streaks of 5 or more (how often) | E119: 4 | F119: 7 | G119: 4 | H119: 4
B120: Losing streaks of 5 or more (how often) | E120: 72 | F120: 69 | G120: 86 | H120: 76
B121: Deepest fall from a peak (R, fixed risk) | E121: 30.01 | F121: 30.73 | G121: 34.45 | H121: 37.97
A122: MONEY - $10,000 start, $50 risk per trade (strategy / EA sizing: a stop-out loses $50 including the spread)
B123: Fixed $50 risk (Loss Recovery = Off): net profit ($) | E123: 5441.57 | F123: 4561.27 | G123: 4470.32 | H123: 4040.42
B124: deepest fall from a peak ($) | E124: 1480.81 | F124: 1467.44 | G124: 1644.27 | H124: 1822.11
...

Sheet M5 strategies
A1: M5: profitable settings for each scenario - what to set in the indicator and what to expect
A2: Pick the column for your goal and read down. Yellow cells = change this input to the value shown; grey = leave the default. All results are 2021-2026 on FxPro gold after the spread, and every setting here was profitable in both 2021-23 and 2024-26 with at least 4 of 6 years positive. Expect live results to be weaker.
A4: Group | B4: Input (exactly as in the indicator) | C4: MT5 EA input | D4: Default | E4: M5-S1 | F4: M5-S2 | G4: M5-S3 | H4: M5-S4
A5: WHEN TO USE IT
B6: Scenario | E6: Most profit + Smoothest + New York session only | F6: Shortest losing streak + Shortest losing streak - indicator only + Longest winning streak + Highest win rate + Every year positive | G6: Most trades a day | H6: Simplest
B7: Use it when | E7: Best R per trade after spread in both halves (ranked by the weaker half); the main recommendation. The best profit for the deepest fall from a peak (total R / max drawdown in R), among the 25 strongest settings. Trades only in the New York session (Indian time); for traders who can only watch that session. | F7: The fewest losses in a row, keeping a fair profit. May use a partial close (strategy / EA only). As above, without a partial close, so the indicator shows the same trades and results. The most wins in a row. The largest share of profitable trades. Profitable in all 6 years (2021-2026), best score. | G7: The most trades while still profitable in both halves. | H7: The fewest settings to change.
B8: Works in | E8: Indicator, strategy and EA | F8: Indicator, strategy and EA | G8: Indicator, strategy and EA | H8: Indicator, strategy and EA
A9: SETTINGS - change the yellow cells, leave the rest at the default
A10: SIGNAL MODEL | B10: Structure Lookback (bars) | C10: InpStructLen | D10: 10 | E10: 10 | F10: 10 | G10: 10 | H10: 10
B11: Signal Break Lookback (bars) | C11: InpBrkLen | D11: 6 | E11: 6 | F11: 6 | G11: 6 | H11: 6
B12: Entry Level Lookback (bars) | C12: InpEntryLen | D12: 6 | E12: 6 | F12: 6 | G12: 6 | H12: 6
B13: Retest Window (bars) | C13: InpRetestBars | D13: 5 | E13: 5 | F13: 5 | G13: 5 | H13: 5
B14: Min Displacement Range (x ATR) | C14: InpDispAtr | D14: 0.8 | E14: 0.8 | F14: 0.8 | G14: 0.8 | H14: 0.8
B15: Min Displacement Body (% of range) | C15: InpBodyPct | D15: 55 | E15: 55 | F15: 55 | G15: 55 | H15: 55
B16: Max Close Distance From Extreme (% of range) | C16: InpClosePct | D16: 25 | E16: 25 | F16: 25 | G16: 25 | H16: 25
B17: Momentum Lookback (bars) | C17: InpMomLen | D17: 10 | E17: 10 | F17: 10 | G17: 5 | H17: 10
B18: Min (x ATR) [same line as Momentum Lookback] | C18: InpMomAtr | D18: 0.85 | E18: 0.85 | F18: 0.85 | G18: 0.85 | H18: 0.85
B19: Min CMO (clean move) | C19: InpCmoMin | D19: 20 | E19: 20 | F19: 20 | G19: 20 | H19: 20
B20: Same-Direction Re-arm | C20: InpRearm | D20: Keep first | E20: Keep first | F20: Keep first | G20: Keep first | H20: Keep first
B21: Stop Mode | C21: InpStopMode | D21: ATR Model | E21: ATR Model | F21: ATR Model | G21: ATR Model | H21: ATR Model
B22: Stop Distance (x ATR) | C22: InpStopAtr | D22: 1.8 | E22: 2.4 | F22: 2.4 | G22: 2.4 | H22: 1.8
... B46: Shorts | C46: InpAllowShort | D46: On | E46: On | F46: On | G46: On | H46: On
A47: VWAP | B47: Anchor | C47: InpVwapAnchor | D47: Session | E47: Month | F47: Month | G47: Month | H47: Month
B48: Source | C48: InpVwapSrc | D48: hlc3 | E48: hlc3 | F48: hlc3 | G48: hlc3 | H48: hlc3
A49: ENTRY PRICE | B49: Entry Price | C49: InpEntryMode | D49: Model (body mid or 6-bar level) | E49: Market (next bar open) | F49: Market (next bar open) | G49: Market (next bar open) | H49: Market (next bar open)
B50: Custom % (0 = close, 50 = mid, 100 = low/high) | C50: InpEntryPct | D50: 50 | E50: 50 | F50: 50 | G50: 50 | H50: 50
A51: TARGETS, EXIT AND STOP MOVES | B51: TP1 | C51: InpTp1R | D51: 0.6 | E51: 0.6 | F51: 0.6 | G51: 0.6 | H51: 0.6
B52: TP2 | C52: InpTp2R | D52: 1 | E52: 1 | F52: 1 | G52: 1 | H52: 1
B53: TP3 | C53: InpTp3R | D53: 1.5 | E53: 1.5 | F53: 1.5 | G53: 1.5 | H53: 1.5
B54: TP4 | C54: InpTp4R | D54: 2 | E54: 2.5 | F54: 2 | G54: 2 | H54: 2
B55: Final Exit At | C55: InpExitAt | D55: TP4 | E55: TP4 | F55: TP4 | G55: TP4 | H55: TP4
B56: When TP1 Hits, Move Stop To (R) [tick box] | C56: InpMv1On | D56: Off | E56: Off | F56: Off | G56: Off | H56: Off
B57: ... value (R) [same line] | C57: InpMv1R | D57: 0 | E57: 0 | F57: 0 | G57: 0 | H57: 0
B58: When TP2 Hits, Move Stop To (R) [tick box] | C58: InpMv2On | D58: Off | E58: Off | F58: On | G58: Off | H58: Off
B59: ... value (R) [same line] | C59: InpMv2R | D59: 0.6 | E59: 0.6 | F59: 0.6 | G59: 0.6 | H59: 0.6
B60: When TP3 Hits, Move Stop To (R) [tick box] | C60: InpMv3On | D60: Off | E60: Off | F60: Off | G60: Off | H60: Off
B61: ... value (R) [same line] | C61: InpMv3R | D61: 1 | E61: 1 | F61: 1 | G61: 1 | H61: 1
A62: ACCURACY FILTERS | B62: Don't Chase: Skip Signals Beyond [tick box] | C62: InpNoChase | D62: Off | E62: Off | F62: Off | G62: Off | H62: Off
B63: σ From VWAP [same line] | C63: InpNoChaseSig | D63: 2.4 | E63: 2.4 | F63: 2.4 | G63: 2.4 | H63: 2.4
B64: After A Loss, No Same-Direction Trade Until A Win | C64: InpLossBlock | D64: Off | E64: Off | F64: Off | G64: Off | H64: Off
B65: Skip Signals Too Close To VWAP: Min Distance [tick box] | C65: InpMinVwOn | D65: Off | E65: Off | F65: Off | G65: Off | H65: Off
B66: x ATR [same line] | C66: InpMinVwAtr | D66: 1 | E66: 1 | F66: 1 | G66: 1 | H66: 1
B67: Skip Choppy Sessions: Max VWAP Crosses [tick box] | C67: InpChopOn | D67: Off | E67: On | F67: On | G67: On | H67: On
B68: Per 100 Bars [same line] | C68: InpChopMax | D68: 12 | E68: 8 | F68: 8 | G68: 8 | H68: 8
B69: Skip When The 1h EMA20 Moved More Than [tick box] | C69: InpEmaOn | D69: Off | E69: Off | F69: Off | G69: Off | H69: On
B70: ATR In 3 Hours [same line] | C70: InpEmaMax | D70: 1.65 | E70: 1.65 | F70: 1.65 | G70: 1.65 | H70: 1.4
A71: DAYS AND HOURS | B71: Time Zone | C71: InpUserGMT = 5.5 | D71: Asia/Kolkata | E71: Asia/Kolkata | F71: Asia/Kolkata | G71: Asia/Kolkata | H71: Asia/Kolkata
B72: Trade Only On The Ticked Days | C72: InpDayOn | D72: Off | E72: Off | F72: Off | G72: Off | H72: Off
B73: Mon Tue Wed Thu Fri Sat Sun [ticks] | C73: InpMon ... InpSun | D73: all ticked | E73: all ticked | F73: all ticked | G73: all ticked | H73: all ticked
B74: Trade Only Between [tick box] | C74: InpHoursOn | D74: Off | E74: On | F74: On | G74: On | H74: On
B75: session, Indian time [same line] | C75: InpStartH:M - InpEndH:M | D75: 0600-2300 | E75: 1830-2230 | F75: 1830-2230 | G75: 1830-2230 | H75: 1830-2230
B76: Trade Only In Kill Zones (Indian time) | C76: InpKzOn | D76: Off | E76: Off | F76: Off | G76: Off | H76: Off
B77: Asia 05:30-09:30 | C77: InpKzAsia | D77: On | E77: On | F77: On | G77: On | H77: On
B78: London 11:30-14:30 | C78: InpKzLon | D78: On | E78: On | F78: On | G78: On | H78: On
B79: New York 16:30-19:30 | C79: InpKzNy | D79: On | E79: On | F79: On | G79: On | H79: On
B80: London Close 19:30-21:30 | C80: InpKzLc | D80: On | E80: On | F80: On | G80: On | H80: On
B81: Shift All Kill Zones (hours) | C81: InpKzShift | D81: 0 | E81: 0 | F81: 0 | G81: 0 | H81: 0
A82: PARTIAL PROFITS (strategy / EA only) | B82: Close % At TP1 | C82: InpP1 | D82: 0 | E82: 0 | F82: 0 | G82: 0 | H82: 0
B83: Close % At TP2 | C83: InpP2 | D83: 0 | E83: 0 | F83: 0 | G83: 0 | H83: 0
B84: Close % At TP3 | C84: InpP3 | D84: 0 | E84: 0 | F84: 0 | G84: 0 | H84: 0
A85: WHAT TO EXPECT - 2021-2026, FxPro gold, after the spread (blue = backtest result, black = formula)
B86: Trades | E86: 1472 | F86: 1692 | G86: 1805 | H86: 1488
B87: Trades per day | E87: =E86/1485 -> 0.99124579 | F87: =F86/1485 -> 1.1393939 | G87: =G86/1485 -> 1.2154882 | H87: =H86/1485 -> 1.0020202
B88: Wins (closed at the final target) | E88: 472 | F88: 293 | G88: 666 | H88: 548
B89: Win % (closed at the final target) | E89: =IF(E86=0,"",E88/E86) -> 0.32065217 | F89: =IF(F86=0,"",F88/F86) -> 0.17316785 | G89: =IF(G86=0,"",G88/G86) -> 0.36897507 | H89: =IF(H86=0,"",H88/H86) -> 0.36827957
B90: Profitable trades | E90: 472 | F90: 886 | G90: 666 | H90: 548
B91: Profitable trades % | E91: =IF(E86=0,"",E90/E86) -> 0.32065217 | F91: =IF(F86=0,"",F90/F86) -> 0.52364066 | G91: =IF(G86=0,"",G90/G86) -> 0.36897507 | H91: =IF(H86=0,"",H90/H86) -> 0.36827957
B92: TP1 reached (count) | E92: 926 | F92: 1062 | G92: 1137 | H92: 932
B93: TP1 reached % (TP1 = R shown in TARGETS) | E93: =IF(E86=0,"",E92/E86) -> 0.62907609 | F93: =IF(F86=0,"",F92/F86) -> 0.62765957 | G93: =IF(G86=0,"",G92/G86) -> 0.6299169 | H93: =IF(H86=0,"",H92/H86) -> 0.62634409
B94: TP2 reached (count) | E94: 769 | F94: 886 | G94: 943 | H94: 777
B95: TP2 reached % (TP2 = R shown in TARGETS) | E95: =IF(E86=0,"",E94/E86) -> 0.52241848 | F95: =IF(F86=0,"",F94/F86) -> 0.52364066 | G95: =IF(G86=0,"",G94/G86) -> 0.52243767 | H95: =IF(H86=0,"",H94/H86) -> 0.52217742
B96: TP3 reached (count) | E96: 630 | F96: 444 | G96: 774 | H96: 644
B97: TP3 reached % (TP3 = R shown in TARGETS) | E97: =IF(E86=0,"",E96/E86) -> 0.42798913 | F97: =IF(F86=0,"",F96/F86) -> 0.26241135 | G97: =IF(G86=0,"",G96/G86) -> 0.42880886 | H97: =IF(H86=0,"",H96/H86) -> 0.4327957
B98: TP4 reached (count) | E98: 472 | F98: 293 | G98: 666 | H98: 548
B99: TP4 reached % (TP4 = R shown in TARGETS) | E99: =IF(E86=0,"",E98/E86) -> 0.32065217 | F99: =IF(F86=0,"",F98/F86) -> 0.17316785 | G99: =IF(G86=0,"",G98/G86) -> 0.36897507 | H99: =IF(H86=0,"",H98/H86) -> 0.36827957
B100: Breakeven exits (stop moved to entry) | E100: 0 | F100: 0 | G100: 0 | H100: 0
B101: Total R after spread | E101: 128.379 | F101: 76.087 | G101: 130.464 | H101: 85.983
B102: R per trade after spread, 2021-2026 | E102: =IF(E86=0,"",E101/E86) -> 0.087213995 | F102: =IF(F86=0,"",F101/F86) -> 0.044968676 | G102: =IF(G86=0,"",G101/G86) -> 0.072279224 | H102: =IF(H86=0,"",H101/H86) -> 0.057784274
B103: 2021-23 trades | E103: 732 | F103: 849 | G103: 905 | H103: 775
B104: 2021-23 total R after spread | E104: 70.958 | F104: 39.52 | G104: 59.719 | H104: 53.926
B105: R per trade, 2021-23 | E105: =IF(E103=0,"",E104/E103) -> 0.096937158 | F105: =IF(F103=0,"",F104/F103) -> 0.046548881 | G105: =IF(G103=0,"",G104/G103) -> 0.065987845 | H105: =IF(H103=0,"",H104/H103) -> 0.069581935
B106: 2024-26 trades | E106: 740 | F106: 843 | G106: 900 | H106: 713
B107: 2024-26 total R after spread | E107: 57.421 | F107: 36.568 | G107: 70.744 | H107: 32.058
B108: R per trade, 2024-26 | E108: =IF(E106=0,"",E107/E106) -> 0.077595946 | F108: =IF(F106=0,"",F107/F106) -> 0.04337841 | G108: =IF(G106=0,"",G107/G106) -> 0.078604444 | H108: =IF(H106=0,"",H107/H106) -> 0.044962132
B109: R per trade if live costs are 0.05 R higher | E109: =IF(E102="","",E102-0.05) -> 0.037213995 | F109: =IF(F102="","",F102-0.05) -> -0.0050313239 | G109: =IF(G102="","",G102-0.05) -> 0.022279224 | H109: =IF(H102="","",H102-0.05) -> 0.0077842742
B110: 2021: total R after spread | E110: -25.41 | F110: 11.72 | G110: -1.23 | H110: -8.78
B111: 2022: total R after spread | E111: 37.91 | F111: 13.49 | G111: 20.99 | H111: 25.97
B112: 2023: total R after spread | E112: 58.46 | F112: 14.31 | G112: 39.96 | H112: 36.74
B113: 2024: total R after spread | E113: 8.7 | F113: 11.2 | G113: 16.11 | H113: 5.61
B114: 2025: total R after spread | E114: 63.55 | F114: 23.77 | G114: 54.83 | H114: 30.76
B115: 2026: total R after spread | E115: -14.83 | F115: 1.59 | G115: -0.19 | H115: -4.32
B116: Years positive (of 6) | E116: =COUNTIF(E110:E115,">0") -> 4 | F116: =COUNTIF(F110:F115,">0") -> 6 | G116: =COUNTIF(G110:G115,">0") -> 4 | H116: =COUNTIF(H110:H115,">0") -> 4
B117: Longest winning streak | E117: 7 | F117: 11 | G117: 6 | H117: 8
B118: Longest losing streak | E118: 21 | F118: 9 | G118: 13 | H118: 20
B119: Winning streaks of 5 or more (how often) | E119: 4 | F119: 33 | G119: 9 | H119: 9
B120: Losing streaks of 5 or more (how often) | E120: 68 | F120: 22 | G120: 70 | H120: 56
B121: Deepest fall from a peak (R, fixed risk) | E121: 37.22 | F121: 25.77 | G121: 37.95 | H121: 44.7
A122: MONEY - $10,000 start, $50 risk per trade (strategy / EA sizing: a stop-out loses $50 including the spread)
B123: Fixed $50 risk (Loss Recovery = Off): net profit ($) | E123: 6136.32 | F123: 3667.19 | G123: 6275.5 | H123: 4134.19
B124: deepest fall from a peak ($) | E124: 1830.99 | F124: 1261.28 | G124: 1807.29 | H124: 2037.7
...

Sheet M15 strategies
A1: M15: profitable settings for each scenario - what to set in the indicator and what to expect
A2: Pick the column for your goal and read down. Yellow cells = change this input to the value shown; grey = leave the default. All results are 2021-2026 on FxPro gold after the spread, and every setting here was profitable in both 2021-23 and 2024-26 with at least 4 of 6 years positive. Expect live results to be weaker.
A4: Group | B4: Input (exactly as in the indicator) | C4: MT5 EA input | D4: Default | E4: M15-S1 | F4: M15-S2 | G4: M15-S3 | H4: M15-S4 | I4: M15-S5 | J4: M15-S6 | K4: M15-S7 | L4: M15-S8 | M4: M15-S9
A5: WHEN TO USE IT
B6: Scenario | E6: Most profit | F6: Shortest losing streak | G6: Shortest losing streak - indicator only + Smoothest | H6: Longest winning streak | I6: Highest win rate | J6: Most trades a day | K6: Every year positive | L6: Simplest | M6: Asia session only
B7: Use it when | E7: Best R per trade after spread in both halves (ranked by the weaker half); the main recommendation. | F7: The fewest losses in a row, keeping a fair profit. May use a partial close (strategy / EA only). | G7: As above, without a partial close, so the indicator shows the same trades and results. The best profit for the deepest fall from a peak (total R / max drawdown in R), among the 25 strongest settings. | H7: The most wins in a row. | I7: The largest share of profitable trades. | J7: The most trades while still profitable in both halves. | K7: Profitable in all 6 years (2021-2026), best score. | L7: The fewest settings to change. | M7: Trades only in the Asia session (Indian time); for traders who can only watch that session.
B8: Works in | E8: Indicator, strategy and EA | F8: Strategy and EA only (partial close) | G8: Indicator, strategy and EA | H8: Strategy and EA only (partial close) | I8: Strategy and EA only (partial close) | J8: Indicator, strategy and EA | K8: Indicator, strategy and EA | L8: Indicator, strategy and EA | M8: Indicator, strategy and EA
A9: SETTINGS - change the yellow cells, leave the rest at the default
A10: SIGNAL MODEL | B10: Structure Lookback (bars) | C10: InpStructLen | D10: 10 | E10: 10 | F10: 10 | G10: 10 | H10: 10 | I10: 10 | J10: 10 | K10: 10 | L10: 10 | M10: 10
B11: Signal Break Lookback (bars) | C11: InpBrkLen | D11: 6 | E11: 6 | F11: 6 | G11: 6 | H11: 6 | I11: 6 | J11: 6 | K11: 8 | L11: 6 | M11: 6
B12: Entry Level Lookback (bars) | C12: InpEntryLen | D12: 6 | E12: 6 | F12: 6 | G12: 6 | H12: 6 | I12: 6 | J12: 6 | K12: 6 | L12: 6 | M12: 8
B13: Retest Window (bars) | C13: InpRetestBars | D13: 5 | E13: 5 | F13: 5 | G13: 5 | H13: 5 | I13: 5 | J13: 5 | K13: 5 | L13: 5 | M13: 5
B14: Min Displacement Range (x ATR) | C14: InpDispAtr | D14: 0.8 | E14: 0.8 | F14: 0.8 | G14: 0.8 | H14: 0.8 | I14: 0.8 | J14: 0.8 | K14: 0.8 | L14: 0.8 | M14: 0.8
B15: Min Displacement Body (% of range) | C15: InpBodyPct | D15: 55 | E15: 55 | F15: 55 | G15: 55 | H15: 55 | I15: 55 | J15: 55 | K15: 55 | L15: 55 | M15: 55
B16: Max Close Distance From Extreme (% of range) | C16: InpClosePct | D16: 25 | E16: 25 | F16: 25 | G16: 25 | H16: 25 | I16: 25 | J16: 25 | K16: 25 | L16: 25 | M16: 25
B17: Momentum Lookback (bars) | C17: InpMomLen | D17: 10 | E17: 10 | F17: 10 | G17: 10 | H17: 10 | I17: 10 | J17: 10 | K17: 10 | L17: 10 | M17: 10
B18: Min (x ATR) [same line as Momentum Lookback] | C18: InpMomAtr | D18: 0.85 | E18: 0.85 | F18: 0.85 | G18: 0.85 | H18: 0.85 | I18: 0.85 | J18: 0.85 | K18: 0.85 | L18: 0.85 | M18: 0.85
B19: Min CMO (clean move) | C19: InpCmoMin | D19: 20 | E19: 20 | F19: 30 | G19: 20 | H19: 20 | I19: 20 | J19: 20 | K19: 20 | L19: 20 | M19: 20
B20: Same-Direction Re-arm | C20: InpRearm | D20: Keep first | E20: Keep first | F20: Keep first | G20: Keep first | H20: Keep first | I20: Keep first | J20: Keep first | K20: Keep first | L20: Keep first | M20: Keep first
B21: Stop Mode | C21: InpStopMode | D21: ATR Model | E21: ATR Model | F21: ATR Model | G21: ATR Model | H21: ATR Model | I21: ATR Model | J21: ATR Model | K21: ATR Model | L21: ATR Model | M21: ATR Model
B22: Stop Distance (x ATR) | C22: InpStopAtr | D22: 1.8 | E22: 4 | F22: 4 | G22: 4 | H22: 4 | I22: 4 | J22: 4 | K22: 4 | L22: 4 | M22: 4
... B46: Shorts | C46: InpAllowShort | D46: On | E46: On | F46: On | G46: On | H46: On | I46: On | J46: On | K46: On | L46: On | M46: On
A47: VWAP | B47: Anchor | C47: InpVwapAnchor | D47: Session | E47: Session | F47: Session | G47: Session | H47: Session | I47: Session | J47: Session | K47: Session | L47: Session | M47: Session
B48: Source | C48: InpVwapSrc | D48: hlc3 | E48: hlc3 | F48: hlc3 | G48: hlc3 | H48: hlc3 | I48: hlc3 | J48: hlc3 | K48: hlc3 | L48: hlc3 | M48: hlc3
A49: ENTRY PRICE | B49: Entry Price | C49: InpEntryMode | D49: Model (body mid or 6-bar level) | E49: Model (body mid or 6-bar level) | F49: Model (body mid or 6-bar level) | G49: Model (body mid or 6-bar level) | H49: Model (body mid or 6-bar level) | I49: Model (body mid or 6-bar level) | J49: Model (body mid or 6-bar level) | K49: Model (body mid or 6-bar level) | L49: Model (body mid or 6-bar level) | M49: Model (body mid or 6-bar level)
B50: Custom % (0 = close, 50 = mid, 100 = low/high) | C50: InpEntryPct | D50: 50 | E50: 50 | F50: 50 | G50: 50 | H50: 50 | I50: 50 | J50: 50 | K50: 50 | L50: 50 | M50: 50
A51: TARGETS, EXIT AND STOP MOVES | B51: TP1 | C51: InpTp1R | D51: 0.6 | E51: 0.6 | F51: 0.6 | G51: 0.6 | H51: 0.6 | I51: 0.5 | J51: 0.6 | K51: 0.6 | L51: 0.6 | M51: 0.6
B52: TP2 | C52: InpTp2R | D52: 1 | E52: 1 | F52: 1 | G52: 1 | H52: 1 | I52: 1 | J52: 1 | K52: 1 | L52: 1 | M52: 1
B53: TP3 | C53: InpTp3R | D53: 1.5 | E53: 1.5 | F53: 1.5 | G53: 1.5 | H53: 1.5 | I53: 1.5 | J53: 1.5 | K53: 1.5 | L53: 1.5 | M53: 1.5
B54: TP4 | C54: InpTp4R | D54: 2 | E54: 2 | F54: 2 | G54: 2 | H54: 2 | I54: 2 | J54: 2 | K54: 2 | L54: 2 | M54: 2
B55: Final Exit At | C55: InpExitAt | D55: TP4 | E55: TP4 | F55: TP4 | G55: TP4 | H55: TP4 | I55: TP4 | J55: TP4 | K55: TP4 | L55: TP4 | M55: TP4
B56: When TP1 Hits, Move Stop To (R) [tick box] | C56: InpMv1On | D56: Off | E56: Off | F56: Off | G56: Off | H56: Off | I56: Off | J56: Off | K56: Off | L56: Off | M56: Off
B57: ... value (R) [same line] | C57: InpMv1R | D57: 0 | E57: 0 | F57: 0 | G57: 0 | H57: 0 | I57: 0 | J57: 0 | K57: 0 | L57: 0 | M57: 0
B58: When TP2 Hits, Move Stop To (R) [tick box] | C58: InpMv2On | D58: Off | E58: Off | F58: Off | G58: Off | H58: Off | I58: Off | J58: On | K58: Off | L58: Off | M58: Off
B59: ... value (R) [same line] | C59: InpMv2R | D59: 0.6 | E59: 0.6 | F59: 0.6 | G59: 0.6 | H59: 0.6 | I59: 0.6 | J59: 0.6 | K59: 0.6 | L59: 0.6 | M59: 0.6
B60: When TP3 Hits, Move Stop To (R) [tick box] | C60: InpMv3On | D60: Off | E60: On | F60: On | G60: On | H60: On | I60: On | J60: On | K60: On | L60: Off | M60: On
B61: ... value (R) [same line] | C61: InpMv3R | D61: 1 | E61: 1 | F61: 1 | G61: 1 | H61: 1 | I61: 1 | J61: 1 | K61: 1 | L61: 1 | M61: 1
A62: ACCURACY FILTERS | B62: Don't Chase: Skip Signals Beyond [tick box] | C62: InpNoChase | D62: Off | E62: Off | F62: Off | G62: Off | H62: Off | I62: Off | J62: Off | K62: Off | L62: Off | M62: Off
B63: σ From VWAP [same line] | C63: InpNoChaseSig | D63: 2.4 | E63: 2.4 | F63: 2.4 | G63: 2.4 | H63: 2.4 | I63: 2.4 | J63: 2.4 | K63: 2.4 | L63: 2.4 | M63: 2.4
B64: After A Loss, No Same-Direction Trade Until A Win | C64: InpLossBlock | D64: Off | E64: Off | F64: Off | G64: Off | H64: Off | I64: Off | J64: Off | K64: Off | L64: Off | M64: Off
B65: Skip Signals Too Close To VWAP: Min Distance [tick box] | C65: InpMinVwOn | D65: Off | E65: Off | F65: Off | G65: Off | H65: Off | I65: Off | J65: Off | K65: Off | L65: Off | M65: Off
B66: x ATR [same line] | C66: InpMinVwAtr | D66: 1 | E66: 1 | F66: 1 | G66: 1 | H66: 1 | I66: 1 | J66: 1 | K66: 1 | L66: 1 | M66: 1
B67: Skip Choppy Sessions: Max VWAP Crosses [tick box] | C67: InpChopOn | D67: Off | E67: Off | F67: Off | G67: Off | H67: On | I67: Off | J67: Off | K67: Off | L67: Off | M67: Off
B68: Per 100 Bars [same line] | C68: InpChopMax | D68: 12 | E68: 12 | F68: 12 | G68: 12 | H68: 16 | I68: 12 | J68: 12 | K68: 12 | L68: 12 | M68: 12
B69: Skip When The 1h EMA20 Moved More Than [tick box] | C69: InpEmaOn | D69: Off | E69: Off | F69: On | G69: On | H69: Off | I69: Off | J69: Off | K69: Off | L69: Off | M69: On
B70: ATR In 3 Hours [same line] | C70: InpEmaMax | D70: 1.65 | E70: 1.65 | F70: 1.2 | G70: 1.2 | H70: 1.65 | I70: 1.65 | J70: 1.65 | K70: 1.65 | L70: 1.65 | M70: 1.2
A71: DAYS AND HOURS | B71: Time Zone | C71: InpUserGMT = 5.5 | D71: Asia/Kolkata | E71: Asia/Kolkata | F71: Asia/Kolkata | G71: Asia/Kolkata | H71: Asia/Kolkata | I71: Asia/Kolkata | J71: Asia/Kolkata | K71: Asia/Kolkata | L71: Asia/Kolkata | M71: Asia/Kolkata
B72: Trade Only On The Ticked Days | C72: InpDayOn | D72: Off | E72: Off | F72: Off | G72: Off | H72: Off | I72: Off | J72: Off | K72: Off | L72: Off | M72: Off
B73: Mon Tue Wed Thu Fri Sat Sun [ticks] | C73: InpMon ... InpSun | D73: all ticked | E73: all ticked | F73: all ticked | G73: all ticked | H73: all ticked | I73: all ticked | J73: all ticked | K73: all ticked | L73: all ticked | M73: all ticked
B74: Trade Only Between [tick box] | C74: InpHoursOn | D74: Off | E74: Off | F74: Off | G74: Off | H74: Off | I74: Off | J74: Off | K74: Off | L74: Off | M74: Off
B75: session, Indian time [same line] | C75: InpStartH:M - InpEndH:M | D75: 0600-2300 | E75: 0600-2300 | F75: 0600-2300 | G75: 0600-2300 | H75: 0600-2300 | I75: 0600-2300 | J75: 0600-2300 | K75: 0600-2300 | L75: 0600-2300 | M75: 0600-2300
B76: Trade Only In Kill Zones (Indian time) | C76: InpKzOn | D76: Off | E76: Off | F76: Off | G76: Off | H76: Off | I76: Off | J76: Off | K76: Off | L76: Off | M76: On
B77: Asia 05:30-09:30 | C77: InpKzAsia | D77: On | E77: On | F77: On | G77: On | H77: On | I77: On | J77: On | K77: On | L77: On | M77: On
B78: London 11:30-14:30 | C78: InpKzLon | D78: On | E78: On | F78: On | G78: On | H78: On | I78: On | J78: On | K78: On | L78: On | M78: Off
B79: New York 16:30-19:30 | C79: InpKzNy | D79: On | E79: On | F79: On | G79: On | H79: On | I79: On | J79: On | K79: On | L79: On | M79: Off
B80: London Close 19:30-21:30 | C80: InpKzLc | D80: On | E80: On | F80: On | G80: On | H80: On | I80: On | J80: On | K80: On | L80: On | M80: Off
B81: Shift All Kill Zones (hours) | C81: InpKzShift | D81: 0 | E81: 0 | F81: 0 | G81: 0 | H81: 0 | I81: 0 | J81: 0 | K81: 0 | L81: 0 | M81: 0
A82: PARTIAL PROFITS (strategy / EA only) | B82: Close % At TP1 | C82: InpP1 | D82: 0 | E82: 0 | F82: 70 | G82: 0 | H82: 70 | I82: 70 | J82: 0 | K82: 0 | L82: 0 | M82: 0
B83: Close % At TP2 | C83: InpP2 | D83: 0 | E83: 0 | F83: 0 | G83: 0 | H83: 0 | I83: 0 | J83: 0 | K83: 0 | L83: 0 | M83: 0
B84: Close % At TP3 | C84: InpP3 | D84: 0 | E84: 0 | F84: 0 | G84: 0 | H84: 0 | I84: 0 | J84: 0 | K84: 0 | L84: 0 | M84: 0
A85: WHAT TO EXPECT - 2021-2026, FxPro gold, after the spread (blue = backtest result, black = formula)
B86: Trades | E86: 1388 | F86: 1137 | G86: 1129 | H86: 1207 | I86: 1388 | J86: 1776 | K86: 1377 | L86: 1179 | M86: 712
B87: Trades per day | E87: =E86/1485 -> 0.93468013 | F87: =F86/1485 -> 0.76565657 | G87: =G86/1485 -> 0.76026936 | H87: =H86/1485 -> 0.81279461 | I87: =I86/1485 -> 0.93468013 | J87: =J86/1485 -> 1.1959596 | K87: =K86/1485 -> 0.92727273 | L87: =L86/1485 -> 0.79393939 | M87: =M86/1485 -> 0.47946128
B88: Wins (closed at the final target) | E88: 349 | F88: 301 | G88: 283 | H88: 307 | I88: 349 | J88: 241 | K88: 357 | L88: 437 | M88: 167
B89: Win % (closed at the final target) | E89: =IF(E86=0,"",E88/E86) -> 0.25144092 | F89: =IF(F86=0,"",F88/F86) -> 0.26473175 | G89: =IF(G86=0,"",G88/G86) -> 0.2506643 | H89: =IF(H86=0,"",H88/H86) -> 0.25434963 | I89: =IF(I86=0,"",I88/I86) -> 0.25144092 | J89: =IF(J86=0,"",J88/J86) -> 0.1356982 | K89: =IF(K86=0,"",K88/K86) -> 0.25925926 | L89: =IF(L86=0,"",L88/L86) -> 0.3706531 | M89: =IF(M86=0,"",M88/M86) -> 0.23455056
B90: Profitable trades | E90: 630 | F90: 752 | G90: 510 | H90: 800 | I90: 969 | J90: 946 | K90: 628 | L90: 437 | M90: 306
B91: Profitable trades % | E91: =IF(E86=0,"",E90/E86) -> 0.45389049 | F91: =IF(F86=0,"",F90/F86) -> 0.66138962 | G91: =IF(G86=0,"",G90/G86) -> 0.45172719 | H91: =IF(H86=0,"",H90/H86) -> 0.66280033 | I91: =IF(I86=0,"",I90/I86) -> 0.6981268 | J91: =IF(J86=0,"",J90/J86) -> 0.53265766 | K91: =IF(K86=0,"",K90/K86) -> 0.45606391 | L91: =IF(L86=0,"",L90/L86) -> 0.3706531 | M91: =IF(M86=0,"",M90/M86) -> 0.42977528
B92: TP1 reached (count) | E92: 920 | F92: 752 | G92: 738 | H92: 800 | I92: 969 | J92: 1145 | K92: 915 | L92: 764 | M92: 446
B93: TP1 reached % (TP1 = R shown in TARGETS) | E93: =IF(E86=0,"",E92/E86) -> 0.66282421 | F93: =IF(F86=0,"",F92/F86) -> 0.66138962 | G93: =IF(G86=0,"",G92/G86) -> 0.65367582 | H93: =IF(H86=0,"",H92/H86) -> 0.66280033 | I93: =IF(I86=0,"",I92/I86) -> 0.6981268 | J93: =IF(J86=0,"",J92/J86) -> 0.64470721 | K93: =IF(K86=0,"",K92/K86) -> 0.66448802 | L93: =IF(L86=0,"",L92/L86) -> 0.64800679 | M93: =IF(M86=0,"",M92/M86) -> 0.62640449
B94: TP2 reached (count) | E94: 769 | F94: 630 | G94: 614 | H94: 667 | I94: 769 | J94: 946 | K94: 765 | L94: 638 | M94: 369
B95: TP2 reached % (TP2 = R shown in TARGETS) | E95: =IF(E86=0,"",E94/E86) -> 0.55403458 | F95: =IF(F86=0,"",F94/F86) -> 0.55408971 | G95: =IF(G86=0,"",G94/G86) -> 0.54384411 | H95: =IF(H86=0,"",H94/H86) -> 0.55260978 | I95: =IF(I86=0,"",I94/I86) -> 0.55403458 | J95: =IF(J86=0,"",J94/J86) -> 0.53265766 | K95: =IF(K86=0,"",K94/K86) -> 0.55555556 | L95: =IF(L86=0,"",L94/L86) -> 0.54113656 | M95: =IF(M86=0,"",M94/M86) -> 0.51825843
B96: TP3 reached (count) | E96: 630 | F96: 515 | G96: 510 | H96: 554 | I96: 630 | J96: 442 | K96: 628 | L96: 520 | M96: 306
B97: TP3 reached % (TP3 = R shown in TARGETS) | E97: =IF(E86=0,"",E96/E86) -> 0.45389049 | F97: =IF(F86=0,"",F96/F86) -> 0.45294635 | G97: =IF(G86=0,"",G96/G86) -> 0.45172719 | H97: =IF(H86=0,"",H96/H86) -> 0.45898923 | I97: =IF(I86=0,"",I96/I86) -> 0.45389049 | J97: =IF(J86=0,"",J96/J86) -> 0.24887387 | K97: =IF(K86=0,"",K96/K86) -> 0.45606391 | L97: =IF(L86=0,"",L96/L86) -> 0.44105174 | M97: =IF(M86=0,"",M96/M86) -> 0.42977528
B98: TP4 reached (count) | E98: 349 | F98: 301 | G98: 283 | H98: 307 | I98: 349 | J98: 241 | K98: 357 | L98: 437 | M98: 167
B99: TP4 reached % (TP4 = R shown in TARGETS) | E99: =IF(E86=0,"",E98/E86) -> 0.25144092 | F99: =IF(F86=0,"",F98/F86) -> 0.26473175 | G99: =IF(G86=0,"",G98/G86) -> 0.2506643 | H99: =IF(H86=0,"",H98/H86) -> 0.25434963 | I99: =IF(I86=0,"",I98/I86) -> 0.25144092 | J99: =IF(J86=0,"",J98/J86) -> 0.1356982 | K99: =IF(K86=0,"",K98/K86) -> 0.25925926 | L99: =IF(L86=0,"",L98/L86) -> 0.3706531 | M99: =IF(M86=0,"",M98/M86) -> 0.23455056
B100: Breakeven exits (stop moved to entry) | E100: 0 | F100: 0 | G100: 0 | H100: 0 | I100: 0 | J100: 0 | K100: 0 | L100: 0 | M100: 0
B101: Total R after spread | E101: 185.743 | F101: 75.549 | G101: 148.872 | H101: 84.761 | I101: 76.893 | J101: 110.163 | K101: 201.072 | L101: 98.671 | M101: 36.414
B102: R per trade after spread, 2021-2026 | E102: =IF(E86=0,"",E101/E86) -> 0.13382061 | F102: =IF(F86=0,"",F101/F86) -> 0.06644591 | G102: =IF(G86=0,"",G101/G86) -> 0.13186182 | H102: =IF(H86=0,"",H101/H86) -> 0.070224524 | I102: =IF(I86=0,"",I101/I86) -> 0.055398415 | J102: =IF(J86=0,"",J101/J86) -> 0.062028716 | K102: =IF(K86=0,"",K101/K86) -> 0.14602179 | L102: =IF(L86=0,"",L101/L86) -> 0.083690416 | M102: =IF(M86=0,"",M101/M86) -> 0.051143258
B103: 2021-23 trades | E103: 687 | F103: 585 | G103: 562 | H103: 603 | I103: 687 | J103: 883 | K103: 677 | L103: 609 | M103: 365
B104: 2021-23 total R after spread | E104: 92.918 | F104: 37.902 | G104: 75.487 | H104: 46.137 | I104: 46.018 | J104: 37.284 | K104: 98.246 | L104: 50.809 | M104: 25.929
B105: R per trade, 2021-23 | E105: =IF(E103=0,"",E104/E103) -> 0.13525182 | F105: =IF(F103=0,"",F104/F103) -> 0.064789744 | G105: =IF(G103=0,"",G104/G103) -> 0.13431851 | H105: =IF(H103=0,"",H104/H103) -> 0.076512438 | I105: =IF(I103=0,"",I104/I103) -> 0.066983988 | J105: =IF(J103=0,"",J104/J103) -> 0.042224236 | K105: =IF(K103=0,"",K104/K103) -> 0.14511965 | L105: =IF(L103=0,"",L104/L103) -> 0.083430213 | M105: =IF(M103=0,"",M104/M103) -> 0.071038356
B106: 2024-26 trades | E106: 701 | F106: 552 | G106: 567 | H106: 604 | I106: 701 | J106: 893 | K106: 700 | L106: 570 | M106: 347
B107: 2024-26 total R after spread | E107: 92.825 | F107: 37.648 | G107: 73.385 | H107: 38.624 | I107: 30.875 | J107: 72.879 | K107: 102.827 | L107: 47.862 | M107: 10.485
B108: R per trade, 2024-26 | E108: =IF(E106=0,"",E107/E106) -> 0.13241797 | F108: =IF(F106=0,"",F107/F106) -> 0.068202899 | G108: =IF(G106=0,"",G107/G106) -> 0.12942681 | H108: =IF(H106=0,"",H107/H106) -> 0.06394702 | I108: =IF(I106=0,"",I107/I106) -> 0.044044223 | J108: =IF(J106=0,"",J107/J106) -> 0.081611422 | K108: =IF(K106=0,"",K107/K106) -> 0.14689571 | L108: =IF(L106=0,"",L107/L106) -> 0.083968421 | M108: =IF(M106=0,"",M107/M106) -> 0.030216138
B109: R per trade if live costs are 0.05 R higher | E109: =IF(E102="","",E102-0.05) -> 0.083820605 | F109: =IF(F102="","",F102-0.05) -> 0.01644591 | G109: =IF(G102="","",G102-0.05) -> 0.081861825 | H109: =IF(H102="","",H102-0.05) -> 0.020224524 | I109: =IF(I102="","",I102-0.05) -> 0.005398415 | J109: =IF(J102="","",J102-0.05) -> 0.012028716 | K109: =IF(K102="","",K102-0.05) -> 0.096021786 | L109: =IF(L102="","",L102-0.05) -> 0.033690416 | M109: =IF(M102="","",M102-0.05) -> 0.0011432584
B110: 2021: total R after spread | E110: 17.96 | F110: 13.45 | G110: 24.89 | H110: 12.46 | I110: 13.41 | J110: 3.34 | K110: 22.11 | L110: 4.6 | M110: 2.89
B111: 2022: total R after spread | E111: 35.91 | F111: 14.84 | G111: 30.79 | H111: 9.8 | I111: 13.16 | J111: 10.13 | K111: 41.94 | L111: 40.37 | M111: 24.02
B112: 2023: total R after spread | E112: 39.05 | F112: 9.62 | G112: 19.81 | H112: 23.88 | I112: 19.45 | J112: 23.82 | K112: 34.19 | L112: 5.84 | M112: -0.98
B113: 2024: total R after spread | E113: 9.52 | F113: 21.91 | G113: 14.12 | H113: 3.08 | I113: -0.63 | J113: 18.07 | K113: 15.52 | L113: 0.86 | M113: -8.51
B114: 2025: total R after spread | E114: 55.44 | F114: 2.18 | G114: 39.03 | H114: 17.32 | I114: 17.99 | J114: 25.01 | K114: 57.41 | L114: 39.77 | M114: 9.69
B115: 2026: total R after spread | E115: 27.86 | F115: 13.55 | G115: 20.23 | H115: 18.23 | I115: 13.51 | J115: 29.8 | K115: 29.9 | L115: 7.23 | M115: 9.31
B116: Years positive (of 6) | E116: =COUNTIF(E110:E115,">0") -> 6 | F116: =COUNTIF(F110:F115,">0") -> 6 | G116: =COUNTIF(G110:G115,">0") -> 6 | H116: =COUNTIF(H110:H115,">0") -> 6 | I116: =COUNTIF(I110:I115,">0") -> 5 | J116: =COUNTIF(J110:J115,">0") -> 6 | K116: =COUNTIF(K110:K115,">0") -> 6 | L116: =COUNTIF(L110:L115,">0") -> 6 | M116: =COUNTIF(M110:M115,">0") -> 4
B117: Longest winning streak | E117: 8 | F117: 18 | G117: 6 | H117: 22 | I117: 21 | J117: 10 | K117: 8 | L117: 6 | M117: 6
B118: Longest losing streak | E118: 17 | F118: 5 | G118: 8 | H118: 6 | I118: 5 | J118: 11 | K118: 17 | L118: 18 | M118: 21
B119: Winning streaks of 5 or more (how often) | E119: 13 | F119: 47 | G119: 11 | H119: 53 | I119: 69 | J119: 33 | K119: 14 | L119: 5 | M119: 3
B120: Losing streaks of 5 or more (how often) | E120: 35 | F120: 3 | G120: 30 | H120: 3 | I120: 3 | J120: 18 | K120: 33 | L120: 45 | M120: 16
B121: Deepest fall from a peak (R, fixed risk) | E121: 23.23 | F121: 22.61 | G121: 14.36 | H121: 24.32 | I121: 19.15 | J121: 22.64 | K121: 23.23 | L121: 32.92 | M121: 23.46
A122: MONEY - $10,000 start, $50 risk per trade (strategy / EA sizing: a stop-out loses $50 including the spread)
B123: Fixed $50 risk (Loss Recovery = Off): net profit ($) | E123: 9076.9 | F123: 3704.09 | G123: 7274.17 | H123: 4150.61 | I123: 3772.06 | J123: 5431.6 | K123: 9830 | L123: 4808.57 | M123: 1746.78
B124: deepest fall from a peak ($) | E124: 1109.87 | F124: 1050.22 | G124: 708.81 | H124: 1155.65 | I124: 907.35 | J124: 1102.18 | K124: 1109.87 | L124: 1554.65 | M124: 1146.76
...

Sheet H1 strategies
A1: H1: profitable settings for each scenario - what to set in the indicator and what to expect
A2: Pick the column for your goal and read down. Yellow cells = change this input to the value shown; grey = leave the default. All results are 2021-2026 on FxPro gold after the spread, and every setting here was profitable in both 2021-23 and 2024-26 with at least 4 of 6 years positive. Expect live results to be weaker.
A4: Group | B4: Input (exactly as in the indicator) | C4: MT5 EA input | D4: Default | E4: H1-S1 | F4: H1-S2 | G4: H1-S3 | H4: H1-S4 | I4: H1-S5 | J4: H1-S6 | K4: H1-S7 | L4: H1-S8
A5: WHEN TO USE IT
B6: Scenario | E6: Most profit + Every year positive | F6: Shortest losing streak | G6: Shortest losing streak - indicator only | H6: Longest winning streak | I6: Highest win rate | J6: Most trades a day | K6: Smoothest | L6: Simplest
B7: Use it when | E7: Best R per trade after spread in both halves (ranked by the weaker half); the main recommendation. Profitable in all 6 years (2021-2026), best score. | F7: The fewest losses in a row, keeping a fair profit. May use a partial close (strategy / EA only). | G7: As above, without a partial close, so the indicator shows the same trades and results. | H7: The most wins in a row. | I7: The largest share of profitable trades. | J7: The most trades while still profitable in both halves. | K7: The best profit for the deepest fall from a peak (total R / max drawdown in R), among the 25 strongest settings. | L7: The fewest settings to change.
B8: Works in | E8: Indicator, strategy and EA | F8: Strategy and EA only (partial close) | G8: Indicator, strategy and EA | H8: Strategy and EA only (partial close) | I8: Strategy and EA only (partial close) | J8: Indicator, strategy and EA | K8: Indicator, strategy and EA | L8: Indicator, strategy and EA
A9: SETTINGS - change the yellow cells, leave the rest at the default
A10: SIGNAL MODEL | B10: Structure Lookback (bars) | C10: InpStructLen | D10: 10 | E10: 10 | F10: 20 | G10: 10 | H10: 20 | I10: 10 | J10: 20 | K10: 20 | L10: 10
B11: Signal Break Lookback (bars) | C11: InpBrkLen | D11: 6 | E11: 6 | F11: 6 | G11: 6 | H11: 6 | I11: 6 | J11: 6 | K11: 6 | L11: 6
B12: Entry Level Lookback (bars) | C12: InpEntryLen | D12: 6 | E12: 6 | F12: 6 | G12: 6 | H12: 6 | I12: 6 | J12: 6 | K12: 6 | L12: 6
B13: Retest Window (bars) | C13: InpRetestBars | D13: 5 | E13: 5 | F13: 5 | G13: 5 | H13: 5 | I13: 5 | J13: 5 | K13: 5 | L13: 5
B14: Min Displacement Range (x ATR) | C14: InpDispAtr | D14: 0.8 | E14: 0.65 | F14: 0.8 | G14: 0.8 | H14: 0.5 | I14: 0.8 | J14: 0.5 | K14: 0.8 | L14: 0.8
B15: Min Displacement Body (% of range) | C15: InpBodyPct | D15: 55 | E15: 55 | F15: 55 | G15: 60 | H15: 55 | I15: 55 | J15: 45 | K15: 55 | L15: 55
B16: Max Close Distance From Extreme (% of range) | C16: InpClosePct | D16: 25 | E16: 25 | F16: 25 | G16: 25 | H16: 25 | I16: 25 | J16: 25 | K16: 25 | L16: 25
B17: Momentum Lookback (bars) | C17: InpMomLen | D17: 10 | E17: 5 | F17: 10 | G17: 10 | H17: 5 | I17: 10 | J17: 10 | K17: 10 | L17: 10
B18: Min (x ATR) [same line as Momentum Lookback] | C18: InpMomAtr | D18: 0.85 | E18: 0.85 | F18: 0.85 | G18: 0.85 | H18: 0.85 | I18: 0.85 | J18: 0.85 | K18: 0.85 | L18: 0.85
B19: Min CMO (clean move) | C19: InpCmoMin | D19: 20 | E19: 20 | F19: 20 | G19: 20 | H19: 20 | I19: 20 | J19: 20 | K19: 20 | L19: 20
B20: Same-Direction Re-arm | C20: InpRearm | D20: Keep first | E20: Keep first | F20: Keep first | G20: Keep first | H20: Keep first | I20: Keep first | J20: Keep first | K20: Keep first | L20: Keep first
B21: Stop Mode | C21: InpStopMode | D21: ATR Model | E21: ATR Model | F21: ATR Model | G21: ATR Model | H21: ATR Model | I21: ATR Model | J21: ATR Model | K21: ATR Model | L21: ATR Model
B22: Stop Distance (x ATR) | C22: InpStopAtr | D22: 1.8 | E22: 2.4 | F22: 2.2 | G22: 2.2 | H22: 2.2 | I22: 2.2 | J22: 2.2 | K22: 2.2 | L22: 1.8
... B46: Shorts | C46: InpAllowShort | D46: On | E46: On | F46: On | G46: On | H46: On | I46: On | J46: On | K46: On | L46: On
A47: VWAP | B47: Anchor | C47: InpVwapAnchor | D47: Session | E47: Session | F47: Month | G47: Session | H47: Month | I47: Month | J47: Month | K47: Month | L47: Month
B48: Source | C48: InpVwapSrc | D48: hlc3 | E48: hlc3 | F48: hlc3 | G48: hlc3 | H48: hlc3 | I48: hlc3 | J48: hlc3 | K48: hlc3 | L48: hlc3
A49: ENTRY PRICE | B49: Entry Price | C49: InpEntryMode | D49: Model (body mid or 6-bar level) | E49: Model (body mid or 6-bar level) | F49: Model (body mid or 6-bar level) | G49: Model (body mid or 6-bar level) | H49: Model (body mid or 6-bar level) | I49: Model (body mid or 6-bar level) | J49: Model (body mid or 6-bar level) | K49: Model (body mid or 6-bar level) | L49: Model (body mid or 6-bar level)
B50: Custom % (0 = close, 50 = mid, 100 = low/high) | C50: InpEntryPct | D50: 50 | E50: 50 | F50: 50 | G50: 50 | H50: 50 | I50: 50 | J50: 50 | K50: 50 | L50: 50
A51: TARGETS, EXIT AND STOP MOVES | B51: TP1 | C51: InpTp1R | D51: 0.6 | E51: 0.6 | F51: 0.6 | G51: 0.6 | H51: 0.6 | I51: 0.6 | J51: 0.6 | K51: 0.6 | L51: 0.6
B52: TP2 | C52: InpTp2R | D52: 1 | E52: 1 | F52: 1 | G52: 1 | H52: 1 | I52: 1 | J52: 1 | K52: 1 | L52: 1
B53: TP3 | C53: InpTp3R | D53: 1.5 | E53: 1.5 | F53: 1.5 | G53: 1.5 | H53: 1.5 | I53: 1.5 | J53: 1.5 | K53: 1.5 | L53: 1.5
B54: TP4 | C54: InpTp4R | D54: 2 | E54: 2 | F54: 2 | G54: 2 | H54: 2 | I54: 2 | J54: 3 | K54: 2 | L54: 2
B55: Final Exit At | C55: InpExitAt | D55: TP4 | E55: TP4 | F55: TP4 | G55: TP4 | H55: TP4 | I55: TP4 | J55: TP4 | K55: TP4 | L55: TP4
B56: When TP1 Hits, Move Stop To (R) [tick box] | C56: InpMv1On | D56: Off | E56: Off | F56: Off | G56: Off | H56: Off | I56: Off | J56: Off | K56: Off | L56: Off
B57: ... value (R) [same line] | C57: InpMv1R | D57: 0 | E57: 0 | F57: 0 | G57: 0 | H57: 0 | I57: 0 | J57: 0 | K57: 0 | L57: 0
B58: When TP2 Hits, Move Stop To (R) [tick box] | C58: InpMv2On | D58: Off | E58: Off | F58: Off | G58: Off | H58: Off | I58: Off | J58: Off | K58: Off | L58: Off
B59: ... value (R) [same line] | C59: InpMv2R | D59: 0.6 | E59: 0.6 | F59: 0.6 | G59: 0.6 | H59: 0.6 | I59: 0.6 | J59: 0.6 | K59: 0.6 | L59: 0.6
B60: When TP3 Hits, Move Stop To (R) [tick box] | C60: InpMv3On | D60: Off | E60: Off | F60: Off | G60: Off | H60: Off | I60: Off | J60: Off | K60: Off | L60: Off
B61: ... value (R) [same line] | C61: InpMv3R | D61: 1 | E61: 1 | F61: 1 | G61: 1 | H61: 1 | I61: 1 | J61: 1 | K61: 1 | L61: 1
A62: ACCURACY FILTERS | B62: Don't Chase: Skip Signals Beyond [tick box] | C62: InpNoChase | D62: Off | E62: On | F62: On | G62: On | H62: On | I62: On | J62: Off | K62: On | L62: On
B63: σ From VWAP [same line] | C63: InpNoChaseSig | D63: 2.4 | E63: 2 | F63: 1.25 | G63: 2 | H63: 1.25 | I63: 1.25 | J63: 2.4 | K63: 1.25 | L63: 2.2
B64: After A Loss, No Same-Direction Trade Until A Win | C64: InpLossBlock | D64: Off | E64: Off | F64: Off | G64: Off | H64: Off | I64: Off | J64: Off | K64: Off | L64: Off
B65: Skip Signals Too Close To VWAP: Min Distance [tick box] | C65: InpMinVwOn | D65: Off | E65: Off | F65: Off | G65: Off | H65: Off | I65: Off | J65: Off | K65: Off | L65: Off
B66: x ATR [same line] | C66: InpMinVwAtr | D66: 1 | E66: 1 | F66: 1 | G66: 1 | H66: 1 | I66: 1 | J66: 1 | K66: 1 | L66: 1
B67: Skip Choppy Sessions: Max VWAP Crosses [tick box] | C67: InpChopOn | D67: Off | E67: Off | F67: Off | G67: Off | H67: Off | I67: Off | J67: Off | K67: Off | L67: Off
B68: Per 100 Bars [same line] | C68: InpChopMax | D68: 12 | E68: 12 | F68: 12 | G68: 12 | H68: 12 | I68: 12 | J68: 12 | K68: 12 | L68: 12
B69: Skip When The 1h EMA20 Moved More Than [tick box] | C69: InpEmaOn | D69: Off | E69: Off | F69: Off | G69: Off | H69: Off | I69: Off | J69: Off | K69: Off | L69: Off
B70: ATR In 3 Hours [same line] | C70: InpEmaMax | D70: 1.65 | E70: 1.65 | F70: 1.65 | G70: 1.65 | H70: 1.65 | I70: 1.65 | J70: 1.65 | K70: 1.65 | L70: 1.65
A71: DAYS AND HOURS | B71: Time Zone | C71: InpUserGMT = 5.5 | D71: Asia/Kolkata | E71: Asia/Kolkata | F71: Asia/Kolkata | G71: Asia/Kolkata | H71: Asia/Kolkata | I71: Asia/Kolkata | J71: Asia/Kolkata | K71: Asia/Kolkata | L71: Asia/Kolkata
B72: Trade Only On The Ticked Days | C72: InpDayOn | D72: Off | E72: Off | F72: Off | G72: Off | H72: Off | I72: Off | J72: Off | K72: Off | L72: Off
B73: Mon Tue Wed Thu Fri Sat Sun [ticks] | C73: InpMon ... InpSun | D73: all ticked | E73: all ticked | F73: all ticked | G73: all ticked | H73: all ticked | I73: all ticked | J73: all ticked | K73: all ticked | L73: all ticked
B74: Trade Only Between [tick box] | C74: InpHoursOn | D74: Off | E74: Off | F74: Off | G74: Off | H74: Off | I74: Off | J74: Off | K74: Off | L74: Off
B75: session, Indian time [same line] | C75: InpStartH:M - InpEndH:M | D75: 0600-2300 | E75: 0600-2300 | F75: 0600-2300 | G75: 0600-2300 | H75: 0600-2300 | I75: 0600-2300 | J75: 0600-2300 | K75: 0600-2300 | L75: 0600-2300
B76: Trade Only In Kill Zones (Indian time) | C76: InpKzOn | D76: Off | E76: Off | F76: Off | G76: Off | H76: Off | I76: Off | J76: Off | K76: Off | L76: Off
B77: Asia 05:30-09:30 | C77: InpKzAsia | D77: On | E77: On | F77: On | G77: On | H77: On | I77: On | J77: On | K77: On | L77: On
B78: London 11:30-14:30 | C78: InpKzLon | D78: On | E78: On | F78: On | G78: On | H78: On | I78: On | J78: On | K78: On | L78: On
B79: New York 16:30-19:30 | C79: InpKzNy | D79: On | E79: On | F79: On | G79: On | H79: On | I79: On | J79: On | K79: On | L79: On
B80: London Close 19:30-21:30 | C80: InpKzLc | D80: On | E80: On | F80: On | G80: On | H80: On | I80: On | J80: On | K80: On | L80: On
B81: Shift All Kill Zones (hours) | C81: InpKzShift | D81: 0 | E81: 0 | F81: 0 | G81: 0 | H81: 0 | I81: 0 | J81: 0 | K81: 0 | L81: 0
A82: PARTIAL PROFITS (strategy / EA only) | B82: Close % At TP1 | C82: InpP1 | D82: 0 | E82: 0 | F82: 70 | G82: 0 | H82: 70 | I82: 70 | J82: 0 | K82: 0 | L82: 0
B83: Close % At TP2 | C83: InpP2 | D83: 0 | E83: 0 | F83: 0 | G83: 0 | H83: 0 | I83: 0 | J83: 0 | K83: 0 | L83: 0
B84: Close % At TP3 | C84: InpP3 | D84: 0 | E84: 0 | F84: 0 | G84: 0 | H84: 0 | I84: 0 | J84: 0 | K84: 0 | L84: 0
A85: WHAT TO EXPECT - 2021-2026, FxPro gold, after the spread (blue = backtest result, black = formula)
B86: Trades | E86: 186 | F86: 195 | G86: 228 | H86: 261 | I86: 200 | J86: 542 | K86: 208 | L86: 498
B87: Trades per day | E87: =E86/1485 -> 0.12525253 | F87: =F86/1485 -> 0.13131313 | G87: =G86/1485 -> 0.15353535 | H87: =H86/1485 -> 0.17575758 | I87: =I86/1485 -> 0.13468013 | J87: =J86/1485 -> 0.36498316 | K87: =K86/1485 -> 0.14006734 | L87: =L86/1485 -> 0.33535354
B88: Wins (closed at the final target) | E88: 84 | F88: 86 | G88: 95 | H88: 110 | I88: 86 | J88: 154 | K88: 92 | L88: 187
B89: Win % (closed at the final target) | E89: =IF(E86=0,"",E88/E86) -> 0.4516129 | F89: =IF(F86=0,"",F88/F86) -> 0.44102564 | G89: =IF(G86=0,"",G88/G86) -> 0.41666667 | H89: =IF(H86=0,"",H88/H86) -> 0.42145594 | I89: =IF(I86=0,"",I88/I86) -> 0.43 | J89: =IF(J86=0,"",J88/J86) -> 0.28413284 | K89: =IF(K86=0,"",K88/K86) -> 0.44230769 | L89: =IF(L86=0,"",L88/L86) -> 0.37550201
B90: Profitable trades | E90: 84 | F90: 139 | G90: 95 | H90: 174 | I90: 144 | J90: 154 | K90: 92 | L90: 187
B91: Profitable trades % | E91: =IF(E86=0,"",E90/E86) -> 0.4516129 | F91: =IF(F86=0,"",F90/F86) -> 0.71282051 | G91: =IF(G86=0,"",G90/G86) -> 0.41666667 | H91: =IF(H86=0,"",H90/H86) -> 0.66666667 | I91: =IF(I86=0,"",I90/I86) -> 0.72 | J91: =IF(J86=0,"",J90/J86) -> 0.28413284 | K91: =IF(K86=0,"",K90/K86) -> 0.44230769 | L91: =IF(L86=0,"",L90/L86) -> 0.37550201
B92: TP1 reached (count) | E92: 122 | F92: 139 | G92: 144 | H92: 174 | I92: 144 | J92: 347 | K92: 146 | L92: 304
B93: TP1 reached % (TP1 = R shown in TARGETS) | E93: =IF(E86=0,"",E92/E86) -> 0.65591398 | F93: =IF(F86=0,"",F92/F86) -> 0.71282051 | G93: =IF(G86=0,"",G92/G86) -> 0.63157895 | H93: =IF(H86=0,"",H92/H86) -> 0.66666667 | I93: =IF(I86=0,"",I92/I86) -> 0.72 | J93: =IF(J86=0,"",J92/J86) -> 0.6402214 | K93: =IF(K86=0,"",K92/K86) -> 0.70192308 | L93: =IF(L86=0,"",L92/L86) -> 0.61044177
B94: TP2 reached (count) | E94: 105 | F94: 111 | G94: 122 | H94: 140 | I94: 114 | J94: 279 | K94: 117 | L94: 253
B95: TP2 reached % (TP2 = R shown in TARGETS) | E95: =IF(E86=0,"",E94/E86) -> 0.56451613 | F95: =IF(F86=0,"",F94/F86) -> 0.56923077 | G95: =IF(G86=0,"",G94/G86) -> 0.53508772 | H95: =IF(H86=0,"",H94/H86) -> 0.53639847 | I95: =IF(I86=0,"",I94/I86) -> 0.57 | J95: =IF(J86=0,"",J94/J86) -> 0.51476015 | K95: =IF(K86=0,"",K94/K86) -> 0.5625 | L95: =IF(L86=0,"",L94/L86) -> 0.50803213
B96: TP3 reached (count) | E96: 99 | F96: 94 | G96: 106 | H96: 123 | I96: 96 | J96: 232 | K96: 100 | L96: 206
B97: TP3 reached % (TP3 = R shown in TARGETS) | E97: =IF(E86=0,"",E96/E86) -> 0.53225806 | F97: =IF(F86=0,"",F96/F86) -> 0.48205128 | G97: =IF(G86=0,"",G96/G86) -> 0.46491228 | H97: =IF(H86=0,"",H96/H86) -> 0.47126437 | I97: =IF(I86=0,"",I96/I86) -> 0.48 | J97: =IF(J86=0,"",J96/J86) -> 0.42804428 | K97: =IF(K86=0,"",K96/K86) -> 0.48076923 | L97: =IF(L86=0,"",L96/L86) -> 0.41365462
B98: TP4 reached (count) | E98: 84 | F98: 86 | G98: 95 | H98: 110 | I98: 86 | J98: 154 | K98: 92 | L98: 187
B99: TP4 reached % (TP4 = R shown in TARGETS) | E99: =IF(E86=0,"",E98/E86) -> 0.4516129 | F99: =IF(F86=0,"",F98/F86) -> 0.44102564 | G99: =IF(G86=0,"",G98/G86) -> 0.41666667 | H99: =IF(H86=0,"",H98/H86) -> 0.42145594 | I99: =IF(I86=0,"",I98/I86) -> 0.43 | J99: =IF(J86=0,"",J98/J86) -> 0.28413284 | K99: =IF(K86=0,"",K98/K86) -> 0.44230769 | L99: =IF(L86=0,"",L98/L86) -> 0.37550201
B100: Breakeven exits (stop moved to entry) | E100: 0 | F100: 0 | G100: 0 | H100: 0 | I100: 0 | J100: 0 | K100: 0 | L100: 0
B101: Total R after spread | E101: 62.706 | F101: 34.415 | G101: 52.819 | H101: 28.18 | I101: 34.854 | J101: 64.328 | K101: 64.2 | L101: 52.332
B102: R per trade after spread, 2021-2026 | E102: =IF(E86=0,"",E101/E86) -> 0.33712903 | F102: =IF(F86=0,"",F101/F86) -> 0.17648718 | G102: =IF(G86=0,"",G101/G86) -> 0.23166228 | H102: =IF(H86=0,"",H101/H86) -> 0.10796935 | I102: =IF(I86=0,"",I101/I86) -> 0.17427 | J102: =IF(J86=0,"",J101/J86) -> 0.11868635 | K102: =IF(K86=0,"",K101/K86) -> 0.30865385 | L102: =IF(L86=0,"",L101/L86) -> 0.10508434
B103: 2021-23 trades | E103: 95 | F103: 98 | G103: 111 | H103: 127 | I103: 101 | J103: 280 | K103: 102 | L103: 244
B104: 2021-23 total R after spread | E104: 34.369 | F104: 20.912 | G104: 14.714 | H104: 12.687 | I104: 22.243 | J104: 40.266 | K104: 42.009 | L104: 23.661
B105: R per trade, 2021-23 | E105: =IF(E103=0,"",E104/E103) -> 0.36177895 | F105: =IF(F103=0,"",F104/F103) -> 0.21338776 | G105: =IF(G103=0,"",G104/G103) -> 0.13255856 | H105: =IF(H103=0,"",H104/H103) -> 0.099897638 | I105: =IF(I103=0,"",I104/I103) -> 0.22022772 | J105: =IF(J103=0,"",J104/J103) -> 0.14380714 | K105: =IF(K103=0,"",K104/K103) -> 0.41185294 | L105: =IF(L103=0,"",L104/L103) -> 0.096971311
B106: 2024-26 trades | E106: 91 | F106: 97 | G106: 117 | H106: 134 | I106: 99 | J106: 262 | K106: 106 | L106: 254
B107: 2024-26 total R after spread | E107: 28.337 | F107: 13.503 | G107: 38.105 | H107: 15.493 | I107: 12.611 | J107: 24.062 | K107: 22.191 | L107: 28.67
B108: R per trade, 2024-26 | E108: =IF(E106=0,"",E107/E106) -> 0.3113956 | F108: =IF(F106=0,"",F107/F106) -> 0.13920619 | G108: =IF(G106=0,"",G107/G106) -> 0.32568376 | H108: =IF(H106=0,"",H107/H106) -> 0.1156194 | I108: =IF(I106=0,"",I107/I106) -> 0.12738384 | J108: =IF(J106=0,"",J107/J106) -> 0.091839695 | K108: =IF(K106=0,"",K107/K106) -> 0.20934906 | L108: =IF(L106=0,"",L107/L106) -> 0.11287402
B109: R per trade if live costs are 0.05 R higher | E109: =IF(E102="","",E102-0.05) -> 0.28712903 | F109: =IF(F102="","",F102-0.05) -> 0.12648718 | G109: =IF(G102="","",G102-0.05) -> 0.18166228 | H109: =IF(H102="","",H102-0.05) -> 0.057969349 | I109: =IF(I102="","",I102-0.05) -> 0.12427 | J109: =IF(J102="","",J102-0.05) -> 0.068686347 | K109: =IF(K102="","",K102-0.05) -> 0.25865385 | L109: =IF(L102="","",L102-0.05) -> 0.055084337
B110: 2021: total R after spread | E110: 4.97 | F110: 9.42 | G110: -2.29 | H110: 8.32 | I110: 10.64 | J110: 19.52 | K110: 19.97 | L110: 1.34
B111: 2022: total R after spread | E111: 22.33 | F111: 10.61 | G111: 8.11 | H111: 1.34 | I111: 11.82 | J111: 19.37 | K111: 15.04 | L111: 23.3
B112: 2023: total R after spread | E112: 7.07 | F112: 0.88 | G112: 8.9 | H112: 3.03 | I112: -0.21 | J112: 1.38 | K112: 7 | L112: -0.97
B113: 2024: total R after spread | E113: 7.67 | F113: 2.18 | G113: 2.63 | H113: -2.76 | I113: 2.18 | J113: 11.96 | K113: 7.54 | L113: 20.82
B114: 2025: total R after spread | E114: 12.75 | F114: 9.66 | G114: 15.58 | H114: 7.12 | I114: 8.76 | J114: 20.36 | K114: 10.77 | L114: 8.2
B115: 2026: total R after spread | E115: 7.92 | F115: 1.66 | G115: 19.89 | H115: 11.13 | I115: 1.66 | J115: -8.26 | K115: 3.88 | L115: -0.35
B116: Years positive (of 6) | E116: =COUNTIF(E110:E115,">0") -> 6 | F116: =COUNTIF(F110:F115,">0") -> 6 | G116: =COUNTIF(G110:G115,">0") -> 5 | H116: =COUNTIF(H110:H115,">0") -> 5 | I116: =COUNTIF(I110:I115,">0") -> 5 | J116: =COUNTIF(J110:J115,">0") -> 5 | K116: =COUNTIF(K110:K115,">0") -> 6 | L116: =COUNTIF(L110:L115,">0") -> 4
B117: Longest winning streak | E117: 8 | F117: 12 | G117: 7 | H117: 18 | I117: 13 | J117: 4 | K117: 10 | L117: 5
B118: Longest losing streak | E118: 8 | F118: 3 | G118: 6 | H118: 6 | I118: 4 | J118: 16 | K118: 7 | L118: 12
B119: Winning streaks of 5 or more (how often) | E119: 2 | F119: 9 | G119: 2 | H119: 10 | I119: 9 | J119: 0 | K119: 1 | L119: 5
B120: Losing streaks of 5 or more (how often) | E120: 3 | F120: 0 | G120: 5 | H120: 1 | I120: 0 | J120: 25 | K120: 3 | L120: 17
B121: Deepest fall from a peak (R, fixed risk) | E121: 8.11 | F121: 5.8 | G121: 7.73 | H121: 7.89 | I121: 6.32 | J121: 19.14 | K121: 8.08 | L121: 23.94
A122: MONEY - $10,000 start, $50 risk per trade (strategy / EA sizing: a stop-out loses $50 including the spread)
B123: Fixed $50 risk (Loss Recovery = Off): net profit ($) | E123: 3087.46 | F123: 1682.55 | G123: 2619.59 | H123: 1385.37 | I123: 1707.02 | J123: 3143.01 | K123: 3132.76 | L123: 2557.3
B124: deepest fall from a peak ($) | E124: 400 | F124: 288.64 | G124: 373.01 | H124: 389.82 | I124: 301.47 | J124: 952.09 | K124: 402.13 | L124: 1158.16
...

Sheet All profitable settings
A1: Every profitable setting found (2021-2026, after spread): profitable in 2021-23 AND 2024-26, at least 4 of 6 years positive, enough trades
A2: Use the filter arrows: e.g. Longest losing streak <= 6, or Works in = Indicator. Identical results are listed once (fewest changes). Ranked per timeframe by the weaker half.
A4: Timeframe | B4: Rank | C4: Settings to change (indicator names) | D4: Number of changes | E4: Works in | F4: Trades | G4: Trades per day | H4: Profitable trades % | I4: TP1 reached % | J4: R per trade 2021-23 | K4: R per trade 2024-26 | L4: R per trade 2021-2026 | M4: Total R after spread | N4: Years positive | O4: Longest winning streak | P4: Longest losing streak
A5: M1 | B5: 1 | C5: Stop Distance (x ATR) = 4 | Cooldown After Exit (bars) = 8 | Anchor = Month | Trade Only In Kill Zones (Indian time) = On: London Close 19:30-21:30 | D5: 4 | E5: Indicator, strategy and EA | F5: 1958 | G5: =F5/1485 -> 1.3185185 | H5: 0.3662 | I5: 0.6297 | J5: 0.0545 | K5: 0.0601 | L5: 0.0573 | M5: 112.15 | N5: 4 | O5: 8 | P5: 14
A6: M1 | B6: 2 | C6: Stop Distance (x ATR) = 4 | Cooldown After Exit (bars) = 12 | Anchor = Month | Trade Only In Kill Zones (Indian time) = On: London Close 19:30-21:30 | D6: 4 | E6: Indicator, strategy and EA | F6: 1928 | G6: =F6/1485 -> 1.2983165 | H6: 0.3646 | I6: 0.6307 | J6: 0.0498 | K6: 0.0553 | L6: 0.0526 | M6: 101.32 | N6: 5 | O6: 7 | P6: 13
A7: M1 | B7: 3 | C7: Stop Distance (x ATR) = 4 | Anchor = Month | Don't Chase: Skip Signals Beyond ... sigma From VWAP = On, 2.2 | Trade Only In Kill Zones (Indian time) = On: London Close 19:30-21:30 | D7: 4 | E7: Indicator, strategy and EA | F7: 1768 | G7: =F7/1485 -> 1.1905724 | H7: 0.3631 | I7: 0.625 | J7: 0.0481 | K7: 0.0461 | L7: 0.0471 | M7: 83.31 | N7: 5 | O7: 6 | P7: 14
A8: M1 | B8: 4 | C8: Stop Distance (x ATR) = 4 | Cooldown After Exit (bars) = 20 | Anchor = Month | Trade Only In Kill Zones (Indian time) = On: London Close 19:30-21:30 | D8: 4 | E8: Indicator, strategy and EA | F8: 1869 | G8: =F8/1485 -> 1.2585859 | H8: 0.3638 | I8: 0.6356 | J8: 0.0426 | K8: 0.0566 | L8: 0.0496 | M8: 92.62 | N8: 5 | O8: 7 | P8: 13
A9: M1 | B9: 5 | C9: Stop Distance (x ATR) = 4 | Anchor = Month | Don't Chase: Skip Signals Beyond ... sigma From VWAP = On, 2.6 | Trade Only In Kill Zones (Indian time) = On: London Close 19:30-21:30 | D9: 4 | E9: Indicator, strategy and EA | F9: 1877 | G9: =F9/1485 -> 1.2639731 | H9: 0.3612 | I9: 0.6239 | J9: 0.0475 | K9: 0.0362 | L9: 0.0418 | M9: 78.49 | N9: 4 | O9: 6 | P9: 14
A10: M1 | B10: 6 | C10: Stop Distance (x ATR) = 4 | Anchor = Month | Skip Signals Too Close To VWAP: Min Distance (x ATR) = On, 0.75 | Trade Only In Kill Zones (Indian time) = On: London Close 19:30-21:30 | D10: 4 | E10: Indicator, strategy and EA | F10: 2001 | G10: =F10/1485 -> 1.3474747 | H10: 0.3613 | I10: 0.6262 | J10: 0.0513 | K10: 0.0343 | L10: 0.0428 | M10: 85.56 | N10: 4 | O10: 8 | P10: 14
A11: M1 | B11: 7 | C11: Stop Distance (x ATR) = 4 | Anchor = Month | Trade Only In Kill Zones (Indian time) = On: London Close 19:30-21:30 | D11: 3 | E11: Indicator, strategy and EA | F11: 2006 | G11: =F11/1485 -> 1.3508418 | H11: 0.3609 | I11: 0.6261 | J11: 0.0489 | K11: 0.0341 | L11: 0.0415 | M11: 83.21 | N11: 4 | O11: 8 | P11: 14
A12: M1 | B12: 8 | C12: Stop Distance (x ATR) = 4 | Anchor = Month | Skip Choppy Sessions: Max VWAP Crosses Per 100 Bars = On, 6 | Trade Only In Kill Zones (Indian time) = On: London Close 19:30-21:30 | D12: 4 | E12: Indicator, strategy and EA | F12: 2003 | G12: =F12/1485 -> 1.3488215 | H12: 0.3615 | I12: 0.6266 | J12: 0.0522 | K12: 0.0341 | L12: 0.0431 | M12: 86.4 | N12: 4 | O12: 8 | P12: 14
A13: M1 | B13: 9 | C13: Stop Distance (x ATR) = 4 | Cooldown After Exit (bars) = 8 | Anchor = Month | Trade Only In Kill Zones (Indian time) = On: London Close 19:30-21:30 | Close % At TP1 = 30 | D13: 5 | E13: Strategy and EA only (partial close) | F13: 1958 | G13: =F13/1485 -> 1.3185185 | H13: 0.3662 | I13: 0.6297 | J13: 0.0318 | K13: 0.0281 | L13: 0.03 | M13: 58.69 | N13: 4 | O13: 8 | P13: 14
A14: M1 | B14: 10 | C14: Stop Distance (x ATR) = 4 | Cooldown After Exit (bars) = 30 | Anchor = Month | Trade Only In Kill Zones (Indian time) = On: London Close 19:30-21:30 | D14: 4 | E14: Indicator, strategy and EA | F14: 1802 | G14: =F14/1485 -> 1.213468 | H14: 0.3646 | I14: 0.626 | J14: 0.0286 | K14: 0.075 | L14: 0.0516 | M14: 93 | N14: 4 | O14: 7 | P14: 12
A15: M1 | B15: 11 | C15: Stop Distance (x ATR) = 4 | Cooldown After Exit (bars) = 12 | Anchor = Month | Trade Only In Kill Zones (Indian time) = On: London Close 19:30-21:30 | Close % At TP1 = 30 | D15: 5 | E15: Strategy and EA only (partial close) | F15: 1928 | G15: =F15/1485 -> 1.2983165 | H15: 0.3646 | I15: 0.6307 | J15: 0.0275 | K15: 0.0267 | L15: 0.0271 | M15: 52.3 | N15: 4 | O15: 7 | P15: 13
A16: M1 | B16: 12 | C16: Min Displacement Range (x ATR) = 0.4 | Stop Distance (x ATR) = 4 | Anchor = Month | Trade Only In Kill Zones (Indian time) = On: London Close 19:30-21:30 | D16: 4 | E16: Indicator, strategy and EA | F16: 2111 | G16: =F16/1485 -> 1.4215488 | H16: 0.3614 | I16: 0.6239 | J16: 0.0632 | K16: 0.0249 | L16: 0.0439 | M16: 92.74 | N16: 4 | O16: 7 | P16: 14
... A4170: H1 | B4170: 1942 | C4170: Structure Lookback (bars) = 20 | Min Displacement Range (x ATR) = 0.5 | Min Displacement Body (% of range) = 45 | Stop Distance (x ATR) = 2.2 | TP4 (R) = 3 | Anchor = Month | Don't Chase: Skip Signals Beyond ... sigma From VWAP = On, 2 | Close % At TP1 = 30 | D4170: 8 | E4170: Strategy and EA only (partial close) | F4170: 371 | G4170: =F4170/1485 -> 0.24983165 | H4170: 0.2938 | I4170: 0.6469 | J4170: 0.2179 | K4170: 0.0001 | L4170: 0.1146 | M4170: 42.5 | N4170: 5 | O4170: 3 | P4170: 13

Sheet Recovery rules
A1: All 19 loss-recovery rules of the strategy + Off, on each timeframe and setting (2021-2026, after spread)
A2: $10,000 start, $50 base risk, sized like the strategy (a stop-out loses the computed risk incl. spread), no leverage limit. "$500 cap" = Hard Cap on, Clamp. Ranked only if the account survived, made money, never risked more than $500 (5% of the start) on one trade and never fell more than 40% from a peak. Exact recovery, Oscar's Grind and Crooks divide by the R of the final target, like the strategy. Crooks with Start again, splits and random orders: sheet Crooks A and B test.
A4: SUMMARY - every rule on the 8 profitable best / low-streak settings (all timeframes)
A5: Recovery rule | B5: Hard cap | C5: Account survived (of 8) | D5: Eligible (survived, profitable, max risk <= $500, drawdown <= 40%) | E5: Average rank (1 = best) | F5: Profit / drawdown vs Off (average) | G5: Net profit vs Off (average) | H5: Verdict
A6: Off | B6: none | C6: 8 | D6: 8 | E6: 2.1 | F6: 1 | G6: 1 | H6: baseline
A7: Off | B7: $500 | C7: 8 | D7: 8 | E7: 2.1 | F7: 1 | G7: 1 | H7: baseline
A8: Crooks B | B8: $500 | C8: 8 | D8: 8 | E8: 3.4 | F8: 0.948 | G8: 1.38 | H8: about as good as Off, more profit
A9: % of equity | B9: $500 | C9: 8 | D9: 8 | E9: 5.4 | F9: 0.812 | G9: 2.89 | H9: worse risk-adjusted than Off
A10: Paroli | B10: none | C10: 8 | D10: 8 | E10: 6 | F10: 0.806 | G10: 1.79 | H10: worse risk-adjusted than Off
A11: Paroli | B11: $500 | C11: 8 | D11: 8 | E11: 6 | F11: 0.806 | G11: 1.79 | H11: worse risk-adjusted than Off
A12: % of equity | B12: none | C12: 8 | D12: 7 | E12: 5.4 | F12: 0.807 | G12: 2.6 | H12: worse risk-adjusted than Off
A13: Crooks B | B13: none | C13: 8 | D13: 6 | E13: 3.3 | F13: 1.008 | G13: 1.27 | H13: about as good as Off, more profit
A14: Rule C: carry the losses | B14: $500 | C14: 7 | D14: 6 | E14: 5 | F14: 0.944 | G14: 2.25 | H14: about as good as Off, more profit
A15: Crooks A | B15: $500 | C15: 8 | D15: 6 | E15: 6.2 | F15: 0.691 | G15: 1.31 | H15: much worse than Off
A16: Oscar's Grind | B16: $500 | C16: 8 | D16: 5 | E16: 8.8 | F16: 0.728 | G16: 2.53 | H16: worse risk-adjusted than Off
A17: Reverse D'Alembert | B17: $500 | C17: 8 | D17: 4 | E17: 4.5 | F17: 0.921 | G17: 4.99 | H17: about as good as Off, more profit
... A40: Exact recovery at final TP | B40: none | C40: 4 | D40: 1 | E40: 14 | F40: 0.705 | G40: 1.61 | H40: worse risk-adjusted than Off
A41: Rules that were never eligible (blew the account, needed more than $500 on one trade or fell more than 40% in every case) are not listed. Detail per timeframe below.
A43: Timeframe | B43: Settings | C43: Recovery rule | D43: Rule detail | E43: Hard cap | F43: Net profit ($) | G43: Max drawdown ($) | H43: Max drawdown % | I43: Largest risk on one trade ($) | J43: Account blown? | K43: Profit / max drawdown | L43: Profit factor | M43: Worst run of losing trades ($) | N43: Rank (survived, by profit / drawdown)
A44: M1 | B44: Default settings | C44: Off | D44: fixed $50 risk | E44: none | F44: -10035.04 | G44: 10184.86 | H44: 1.0035 | I44: 50 | J44: YES, after 482 trades | K44: =IF(G44=0,"",F44/G44) -> -0.98528993 | L44: 0.43 | M44: 800 | N44: -
A45: M1 | B45: Default settings | C45: Off | D45: fixed $50 risk | E45: $500 | F45: -10035.04 | G45: 10184.86 | H45: 1.0035 | I45: 50 | J45: YES, after 482 trades | K45: =IF(G45=0,"",F45/G45) -> -0.98528993 | L45: 0.43 | M45: 800 | N45: -
A46: M1 | B46: Default settings | C46: Recover all losses on the next trade | D46: risk = $50 + all open losses | E46: none | F46: -10147.44 | G46: 12750 | H46: 1.0117 | I46: 6400 | J46: YES, after 35 trades | K46: =IF(G46=0,"",F46/G46) -> -0.79587765 | L46: 0.432 | M46: 12750 | N46: -
A47: M1 | B47: Default settings | C47: Recover all losses on the next trade | D47: risk = $50 + all open losses | E47: $500 | F47: -10237.77 | G47: 10715.68 | H47: 1.0227 | I47: 500 | J47: YES, after 48 trades | K47: =IF(G47=0,"",F47/G47) -> -0.95540087 | L47: 0.346 | M47: 5000 | N47: -
A48: M1 | B48: Default settings | C48: Recover losses over N trades | D48: N = 3 | E48: none | F48: -10095.38 | G48: 10315.54 | H48: 1.0093 | I48: 2616.39 | J48: YES, after 36 trades | K48: =IF(G48=0,"",F48/G48) -> -0.97865744 | L48: 0.21 | M48: 9679.74 | N48: -
A49: M1 | B49: Default settings | C49: Recover losses over N trades | D49: N = 3 | E49: $500 | F49: -10168.81 | G49: 10388.98 | H49: 1.0165 | I49: 500 | J49: YES, after 57 trades | K49: =IF(G49=0,"",F49/G49) -> -0.97880735 | L49: 0.34 | M49: 4802.46 | N49: -
A50: M1 | B50: Default settings | C50: Recover a % of losses per trade | D50: 50% of open losses | E50: none | F50: -10064.5 | G50: 10315.47 | H50: 1.0063 | I50: 3471.82 | J50: YES, after 37 trades | K50: =IF(G50=0,"",F50/G50) -> -0.97567052 | L50: 0.262 | M50: 10234.85 | N50: -
A51: M1 | B51: Default settings | C51: Recover a % of losses per trade | D51: 50% of open losses | E51: $500 | F51: -10061.26 | G51: 10312.23 | H51: 1.006 | I51: 500 | J51: YES, after 55 trades | K51: =IF(G51=0,"",F51/G51) -> -0.97566288 | L51: 0.36 | M51: 4962.48 | N51: -
A52: M1 | B52: Default settings | C52: Martingale (multiply after each loss) | D52: x2 after each loss | E52: none | F52: -10147.44 | G52: 12750 | H52: 1.0117 | I52: 6400 | J52: YES, after 35 trades | K52: =IF(G52=0,"",F52/G52) -> -0.79587765 | L52: 0.432 | M52: 12750 | N52: -
A53: M1 | B53: Default settings | C53: Martingale (multiply after each loss) | D53: x2 after each loss | E53: $500 | F53: -10237.77 | G53: 10715.68 | H53: 1.0227 | I53: 500 | J53: YES, after 48 trades | K53: =IF(G53=0,"",F53/G53) -> -0.95540087 | L53: 0.346 | M53: 5000 | N53: -
A54: M1 | B54: Default settings | C54: Exact recovery at final TP | D54: sized so the final TP repays open losses | E54: none | F54: -10064.5 | G54: 10315.47 | H54: 1.0063 | I54: 3471.82 | J54: YES, after 37 trades | K54: =IF(G54=0,"",F54/G54) -> -0.97567052 | L54: 0.262 | M54: 10234.85 | N54: -
A55: M1 | B55: Default settings | C55: Exact recovery at final TP | D55: sized so the final TP repays open losses | E55: $500 | F55: -10061.26 | G55: 10312.23 | H55: 1.006 | I55: 500 | J55: YES, after 55 trades | K55: =IF(G55=0,"",F55/G55) -> -0.97566288 | L55: 0.36 | M55: 4962.48 | N55: -
... A83: M1 | B83: Default settings | C83: Crooks B | D83: as Crooks A, recovery = loss / 3 / final TP R; resets when all is won back | E83: $500 | F83: -10127.2 | G83: 10277.03 | H83: 1.0125 | I83: 500 | J83: YES, after 230 trades | K83: =IF(G83=0,"",F83/G83) -> -0.98542089 | L83: 0.627 | M83: 2380 | N83: -
A85: M1 | B85: Best settings (profit) | C85: Off | D85: fixed $50 risk | E85: none | F85: 5441.57 | G85: 1480.81 | H85: 0.1332 | I85: 50 | J85: no | K85: =IF(G85=0,"",F85/G85) -> 3.6747253 | L85: 1.088 | M85: 700 | N85: 2
A86: M1 | B86: Best settings (profit) | C86: Off | D86: fixed $50 risk | E86: $500 | F86: 5441.57 | G86: 1480.81 | H86: 0.1332 | I86: 50 | J86: no | K86: =IF(G86=0,"",F86/G86) -> 3.6747253 | L86: 1.088 | M86: 700 | N86: 2
A87: M1 | B87: Best settings (profit) | C87: Recover all losses on the next trade | D87: risk = $50 + all open losses | E87: none | F87: -28959.9 | G87: 51150 | H87: 1.589 | I87: 25600 | J87: YES, after 162 trades | K87: =IF(G87=0,"",F87/G87) -> -0.56617595 | L87: 0.599 | M87: 51150 | N87: -
A88: M1 | B88: Best settings (profit) | C88: Recover all losses on the next trade | D88: risk = $50 + all open losses | E88: $500 | F88: 52339.87 | G88: 13558.1 | H88: 0.4959 | I88: 500 | J88: no | K88: =IF(G88=0,"",F88/G88) -> 3.8604133 | L88: 1.116 | M88: 7000 | N88: -
A89: M1 | B89: Best settings (profit) | C89: Recover losses over N trades | D89: N = 3 | E89: none | F89: 36461.3 | G89: 14332.43 | H89: 0.5516 | I89: 4827.48 | J89: no | K89: =IF(G89=0,"",F89/G89) -> 2.543972 | L89: 1.193 | M89: 14224.38 | N89: -
A90: M1 | B90: Best settings (profit) | C90: Recover losses over N trades | D90: N = 3 | E90: $500 | F90: 29934.97 | G90: 8712.49 | H90: 0.3639 | I90: 500 | J90: no | K90: =IF(G90=0,"",F90/G90) -> 3.4358685 | L90: 1.128 | M90: 5777.5 | N90: 4
A91: M1 | B91: Best settings (profit) | C91: Recover a % of losses per trade | D91: 50% of open losses | E91: none | F91: 59799.66 | G91: 29092.93 | H91: 0.595 | I91: 14596.46 | J91: no | K91: =IF(G91=0,"",F91/G91) -> 2.0554705 | L91: 1.276 | M91: 29092.93 | N91: -
A92: M1 | B92: Best settings (profit) | C92: Recover a % of losses per trade | D92: 50% of open losses | E92: $500 | F92: 38963.44 | G92: 12674.16 | H92: 0.3948 | I92: 500 | J92: no | K92: =IF(G92=0,"",F92/G92) -> 3.0742424 | L92: 1.127 | M92: 5888.39 | N92: 7
A93: M1 | B93: Best settings (profit) | C93: Martingale (multiply after each loss) | D93: x2 after each loss | E93: none | F93: -28959.9 | G93: 51150 | H93: 1.589 | I93: 25600 | J93: YES, after 162 trades | K93: =IF(G93=0,"",F93/G93) -> -0.56617595 | L93: 0.599 | M93: 51150 | N93: -
A94: M1 | B94: Best settings (profit) | C94: Martingale (multiply after each loss) | D94: x2 after each loss | E94: $500 | F94: 51709.55 | G94: 13558.1 | H94: 0.5315 | I94: 500 | J94: no | K94: =IF(G94=0,"",F94/G94) -> 3.813923 | L94: 1.112 | M94: 7000 | N94: -
A95: M1 | B95: Best settings (profit) | C95: Exact recovery at final TP | D95: sized so the final TP repays open losses | E95: none | F95: 59799.66 | G95: 29092.93 | H95: 0.595 | I95: 14596.46 | J95: no | K95: =IF(G95=0,"",F95/G95) -> 2.0554705 | L95: 1.276 | M95: 29092.93 | N95: -
A96: M1 | B96: Best settings (profit) | C96: Exact recovery at final TP | D96: sized so the final TP repays open losses | E96: $500 | F96: 38963.44 | G96: 12674.16 | H96: 0.3948 | I96: 500 | J96: no | K96: =IF(G96=0,"",F96/G96) -> 3.0742424 | L96: 1.127 | M96: 5888.39 | N96: 8
A97: M1 | B97: Best settings (profit) | C97: Step-up (+$ per loss in a row) | D97: +$25 per loss in a row | E97: none | F97: 50188.71 | G97: 23247.02 | H97: 0.4956 | I97: 1950 | J97: no | K97: =IF(G97=0,"",F97/G97) -> 2.1589309 | L97: 1.163 | M97: 9625 | N97: -
A98: M1 | B98: Best settings (profit) | C98: Step-up (+$ per loss in a row) | D98: +$25 per loss in a row | E98: $500 | F98: 37510.17 | G98: 11611.98 | H98: 0.5941 | I98: 500 | J98: no | K98: =IF(G98=0,"",F98/G98) -> 3.2302992 | L98: 1.121 | M98: 6625 | N98: -
A99: M1 | B99: Best settings (profit) | C99: Fibonacci | D99: 1,1,2,3,5... units | E99: none | F99: 94535.62 | G99: 49300 | H99: 0.7118 | I99: 30500 | J99: no | K99: =IF(G99=0,"",F99/G99) -> 1.9175582 | L99: 1.396 | M99: 49300 | N99: -
A100: M1 | B100: Best settings (profit) | C100: Fibonacci | D100: 1,1,2,3,5... units | E100: $500 | F100: 42905.76 | G100: 12808.1 | H100: 0.5314 | I100: 500 | J100: no | K100: =IF(G100=0,"",F100/G100) -> 3.3498926 | L100: 1.122 | M100: 7000 | N100: -
A101: M1 | B101: Best settings (profit) | C101: D'Alembert | D101: +1 unit after a loss, -1 after a win | E101: none | F101: -10955.37 | G101: 13491.79 | H101: 1.0762 | I101: 1850 | J101: YES, after 100 trades | K101: =IF(G101=0,"",F101/G101) -> -0.81200271 | L101: 0.82 | M101: 8250 | N101: -
A102: M1 | B102: Best settings (profit) | C102: D'Alembert | D102: +1 unit after a loss, -1 after a win | E102: $500 | F102: -10009.8 | G102: 11640.56 | H102: 1.0008 | I102: 500 | J102: YES, after 251 trades | K102: =IF(G102=0,"",F102/G102) -> -0.85990708 | L102: 0.874 | M102: 5000 | N102: -
A103: M1 | B103: Best settings (profit) | C103: Rule C: carry the losses | D103: carried losses / 3 | E103: none | F103: 18740.77 | G103: 6943.37 | H103: 0.2834 | I103: 2314.46 | J103: no | K103: =IF(G103=0,"",F103/G103) -> 2.6990885 | L103: 1.18 | M103: 6828.41 | N103: -
A104: M1 | B104: Best settings (profit) | C104: Rule C: carry the losses | D104: carried losses / 3 | E104: $500 | F104: 17975.08 | G104: 4689.09 | H104: 0.2549 | I104: 500 | J104: no | K104: =IF(G104=0,"",F104/G104) -> 3.8333834 | L104: 1.164 | M104: 4032.74 | N104: 1
A105: M1 | B105: Best settings (profit) | C105: Rule C split | D105: Rule C with profit steps | E105: none | F105: -10766.87 | G105: 13344.93 | H105: 1.061 | I105: 3336.23 | J105: YES, after 253 trades | K105: =IF(G105=0,"",F105/G105) -> -0.80681352 | L105: 0.718 | M105: 12008.93 | N105: -
A106: M1 | B106: Best settings (profit) | C106: Rule C split | D106: Rule C with profit steps | E106: $500 | F106: 58981.63 | G106: 14696.99 | H106: 0.5892 | I106: 500 | J106: no | K106: =IF(G106=0,"",F106/G106) -> 4.0131775 | L106: 1.109 | M106: 7000 | N106: -
A107: M1 | B107: Best settings (profit) | C107: Labouchere | D107: 1-2-3 line | E107: none | F107: -11024.97 | G107: 18823.63 | H107: 1.0576 | I107: 8100 | J107: YES, after 41 trades | K107: =IF(G107=0,"",F107/G107) -> -0.5856984 | L107: 0.751 | M107: 16800 | N107: -
A108: M1 | B108: Best settings (profit) | C108: Labouchere | D108: 1-2-3 line | E108: $500 | F108: 58371.61 | G108: 13808.1 | H108: 0.9749 | I108: 500 | J108: no | K108: =IF(G108=0,"",F108/G108) -> 4.2273455 | L108: 1.102 | M108: 7000 | N108: -
A109: M1 | B109: Best settings (profit) | C109: Grand Martingale | D109: x2 + 1 unit | E109: none | F109: -28546.45 | G109: 53400 | H109: 1.5321 | I109: 26050 | J109: YES, after 162 trades | K109: =IF(G109=0,"",F109/G109) -> -0.53457772 | L109: 0.646 | M109: 53400 | N109: -
A110: M1 | B110: Best settings (profit) | C110: Grand Martingale | D110: x2 + 1 unit | E110: $500 | F110: 48510.58 | G110: 13808.1 | H110: 0.8943 | I110: 500 | J110: no | K110: =IF(G110=0,"",F110/G110) -> 3.5131973 | L110: 1.093 | M110: 7000 | N110: -
A111: M1 | B111: Best settings (profit) | C111: Paroli | D111: x2 after a win, 3-win reset | E111: none | F111: 8461.03 | G111: 3186.14 | H111: 0.2945 | I111: 200 | J111: no | K111: =IF(G111=0,"",F111/G111) -> 2.6555738 | L111: 1.09 | M111: 850 | N111: 9
A112: M1 | B112: Best settings (profit) | C112: Paroli | D112: x2 after a win, 3-win reset | E112: $500 | F112: 8461.03 | G112: 3186.14 | H112: 0.2945 | I112: 200 | J112: no | K112: =IF(G112=0,"",F112/G112) -> 2.6555738 | L112: 1.09 | M112: 850 | N112: 9
A113: M1 | B113: Best settings (profit) | C113: Reverse D'Alembert | D113: +1 unit after a win | E113: none | F113: 11225.1 | G113: 4549.29 | H113: 0.4296 | I113: 500 | J113: no | K113: =IF(G113=0,"",F113/G113) -> 2.46744 | L113: 1.078 | M113: 1700 | N113: -
A114: M1 | B114: Best settings (profit) | C114: Reverse D'Alembert | D114: +1 unit after a win | E114: $500 | F114: 11225.1 | G114: 4549.29 | H114: 0.4296 | I114: 500 | J114: no | K114: =IF(G114=0,"",F114/G114) -> 2.46744 | L114: 1.078 | M114: 1700 | N114: -
A115: M1 | B115: Best settings (profit) | C115: Delayed recovery | D115: starts after 2 losses | E115: none | F115: 33879.14 | G115: 13427.27 | H115: 0.5201 | I115: 4525.76 | J115: no | K115: =IF(G115=0,"",F115/G115) -> 2.5231592 | L115: 1.193 | M115: 13335.35 | N115: -
A116: M1 | B116: Best settings (profit) | C116: Delayed recovery | D116: starts after 2 losses | E116: $500 | F116: 28053.35 | G116: 8212.64 | H116: 0.346 | I116: 500 | J116: no | K116: =IF(G116=0,"",F116/G116) -> 3.4158748 | L116: 1.127 | M116: 5663.61 | N116: 5
A117: M1 | B117: Best settings (profit) | C117: % of equity | D117: 1% of equity | E117: none | F117: 14597.56 | G117: 5849.53 | H117: 0.2604 | I117: 254.53 | J117: no | K117: =IF(G117=0,"",F117/G117) -> 2.4955099 | L117: 1.081 | M117: 3016.84 | N117: 10
A118: M1 | B118: Best settings (profit) | C118: % of equity | D118: 1% of equity | E118: $500 | F118: 14597.56 | G118: 5849.53 | H118: 0.2604 | I118: 254.53 | J118: no | K118: =IF(G118=0,"",F118/G118) -> 2.4955099 | L118: 1.081 | M118: 3016.84 | N118: 10
A119: M1 | B119: Best settings (profit) | C119: Oscar's Grind | D119: +1 unit after a win until +1 unit up | E119: none | F119: 26879.92 | G119: 13834.1 | H119: 0.4532 | I119: 1500 | J119: no | K119: =IF(G119=0,"",F119/G119) -> 1.9430191 | L119: 1.144 | M119: 5250 | N119: -
A120: M1 | B120: Best settings (profit) | C120: Oscar's Grind | D120: +1 unit after a win until +1 unit up | E120: $500 | F120: 25996 | G120: 10509.76 | H120: 0.3699 | I120: 500 | J120: no | K120: =IF(G120=0,"",F120/G120) -> 2.4735103 | L120: 1.152 | M120: 4000 | N120: 11
A121: M1 | B121: Best settings (profit) | C121: Crooks A | D121: base, base, then every 2nd trade risks loss / final TP R; resets on a recovery win | E121: none | F121: 22796.93 | G121: 11834.35 | H121: 0.7327 | I121: 5873.01 | J121: no | K121: =IF(G121=0,"",F121/G121) -> 1.9263356 | L121: 1.23 | M121: 9567.07 | N121: -
A122: M1 | B122: Best settings (profit) | C122: Crooks A | D122: base, base, then every 2nd trade risks loss / final TP R; resets on a recovery win | E122: $500 | F122: 13448.03 | G122: 4076.58 | H122: 0.3542 | I122: 500 | J122: no | K122: =IF(G122=0,"",F122/G122) -> 3.298851 | L122: 1.159 | M122: 2304.2 | N122: 6
A123: M1 | B123: Best settings (profit) | C123: Crooks B | D123: as Crooks A, recovery = loss / 3 / final TP R; resets when all is won back | E123: none | F123: 9377.98 | G123: 2652.08 | H123: 0.154 | I123: 425.53 | J123: no | K123: =IF(G123=0,"",F123/G123) -> 3.5360849 | L123: 1.129 | M123: 1331.63 | N123: 3
A124: M1 | B124: Best settings (profit) | C124: Crooks B | D124: as Crooks A, recovery = loss / 3 / final TP R; resets when all is won back | E124: $500 | F124: 9377.98 | G124: 2652.08 | H124: 0.154 | I124: 425.53 | J124: no | K124: =IF(G124=0,"",F124/G124) -> 3.5360849 | L124: 1.129 | M124: 1331.63 | N124: 3
A126: M1 | B126: Best settings with short losing streaks | C126: Off | D126: fixed $50 risk | E126: none | F126: 4561.27 | G126: 1467.44 | H126: 0.1443 | I126: 50 | J126: no | K126: =IF(G126=0,"",F126/G126) -> 3.1083179 | L126: 1.08 | M126: 600 | N126: 3
A127: M1 | B127: Best settings with short losing streaks | C127: Off | D127: fixed $50 risk | E127: $500 | F127: 4561.27 | G127: 1467.44 | H127: 0.1443 | I127: 50 | J127: no | K127: =IF(G127=0,"",F127/G127) -> 3.1083179 | L127: 1.08 | M127: 600 | N127: 3
A128: M1 | B128: Best settings with short losing streaks | C128: Recover all losses on the next trade | D128: risk = $50 + all open losses | E128: none | F128: -32233.59 | G128: 51150 | H128: 1.7689 | I128: 25600 | J128: YES, after 149 trades | K128: =IF(G128=0,"",F128/G128) -> -0.63017771 | L128: 0.53 | M128: 51150 | N128: -
A129: M1 | B129: Best settings with short losing streaks | C129: Recover all losses on the next trade | D129: risk = $50 + all open losses | E129: $500 | F129: 42541.54 | G129: 11870.63 | H129: 0.6519 | I129: 500 | J129: no | K129: =IF(G129=0,"",F129/G129) -> 3.5837643 | L129: 1.099 | M129: 6000 | N129: -
A130: M1 | B130: Best settings with short losing streaks | C130: Recover losses over N trades | D130: N = 3 | E130: none | F130: 33053.67 | G130: 6550.92 | H130: 0.4593 | I130: 2233.64 | J130: no | K130: =IF(G130=0,"",F130/G130) -> 5.0456531 | L130: 1.228 | M130: 6323.57 | N130: -
A131: M1 | B131: Best settings with short losing streaks | C131: Recover losses over N trades | D131: N = 3 | E131: $500 | F131: 30367.83 | G131: 7070.5 | H131: 0.508 | I131: 500 | J131: no | K131: =IF(G131=0,"",F131/G131) -> 4.2950046 | L131: 1.186 | M131: 5000 | N131: -
A132: M1 | B132: Best settings with short losing streaks | C132: Recover a % of losses per trade | D132: 50% of open losses | E132: none | F132: 54532.77 | G132: 12874.63 | H132: 0.4168 | I132: 6487.32 | J132: no | K132: =IF(G132=0,"",F132/G132) -> 4.2356767 | L132: 1.315 | M132: 12874.63 | N132: -
A133: M1 | B133: Best settings with short losing streaks | C133: Recover a % of losses per trade | D133: 50% of open losses | E133: $500 | F133: 37535.47 | G133: 9190.43 | H133: 0.5479 | I133: 500 | J133: no | K133: =IF(G133=0,"",F133/G133) -> 4.0841908 | L133: 1.139 | M133: 6000 | N133: -
A134: M1 | B134: Best settings with short losing streaks | C134: Martingale (multiply after each loss) | D134: x2 after each loss | E134: none | F134: -32233.59 | G134: 51150 | H134: 1.7689 | I134: 25600 | J134: YES, after 149 trades | K134: =IF(G134=0,"",F134/G134) -> -0.63017771 | L134: 0.53 | M134: 51150 | N134: -
A135: M1 | B135: Best settings with short losing streaks | C135: Martingale (multiply after each loss) | D135: x2 after each loss | E135: $500 | F135: 42304.03 | G135: 12040.16 | H135: 0.6672 | I135: 500 | J135: no | K135: =IF(G135=0,"",F135/G135) -> 3.5135771 | L135: 1.095 | M135: 6000 | N135: -
A136: M1 | B136: Best settings with short losing streaks | C136: Exact recovery at final TP | D136: sized so the final TP repays open losses | E136: none | F136: 54532.77 | G136: 12874.63 | H136: 0.4168 | I136: 6487.32 | J136: no | K136: =IF(G136=0,"",F136/G136) -> 4.2356767 | L136: 1.315 | M136: 12874.63 | N136: -
A137: M1 | B137: Best settings with short losing streaks | C137: Exact recovery at final TP | D137: sized so the final TP repays open losses | E137: $500 | F137: 37535.47 | G137: 9190.43 | H137: 0.5479 | I137: 500 | J137: no | K137: =IF(G137=0,"",F137/G137) -> 4.0841908 | L137: 1.139 | M137: 6000 | N137: -
A138: M1 | B138: Best settings with short losing streaks | C138: Step-up (+$ per loss in a row) | D138: +$25 per loss in a row | E138: none | F138: -10163.08 | G138: 10741.21 | H138: 1.0154 | I138: 1425 | J138: YES, after 99 trades | K138: =IF(G138=0,"",F138/G138) -> -0.94617645 | L138: 0.761 | M138: 5750 | N138: -
A139: M1 | B139: Best settings with short losing streaks | C139: Step-up (+$ per loss in a row) | D139: +$25 per loss in a row | E139: $500 | F139: 29752.23 | G139: 11401.67 | H139: 0.6853 | I139: 500 | J139: no | K139: =IF(G139=0,"",F139/G139) -> 2.6094625 | L139: 1.087 | M139: 5300 | N139: -
... A144: M1 | B144: Best settings with short losing streaks | C144: Rule C: carry the losses | D144: carried losses / 3 | E144: none | F144: 17270.82 | G144: 2922.89 | H144: 0.2395 | I144: 974.3 | J144: no | K144: =IF(G144=0,"",F144/G144) -> 5.9088163 | L144: 1.201 | M144: 2858.3 | N144: -
A145: M1 | B145: Best settings with short losing streaks | C145: Rule C: carry the losses | D145: carried losses / 3 | E145: $500 | F145: 16914.3 | G145: 3178.25 | H145: 0.2698 | I145: 500 | J145: no | K145: =IF(G145=0,"",F145/G145) -> 5.321891 | L145: 1.193 | M145: 2579.53 | N145: 1
A146: M1 | B146: Best settings with short losing streaks | C146: Rule C split | D146: Rule C with profit steps | E146: none | F146: -11768.27 | G146: 16423.24 | H146: 1.1207 | I146: 4105.81 | J146: YES, after 321 trades | K146: =IF(G146=0,"",F146/G146) -> -0.71656202 | L146: 0.788 | M146: 15498.39 | N146: -
A147: M1 | B147: Best settings with short losing streaks | C147: Rule C split | D147: Rule C with profit steps | E147: $500 | F147: 50663.19 | G147: 14012.75 | H147: 0.671 | I147: 500 | J147: no | K147: =IF(G147=0,"",F147/G147) -> 3.6155066 | L147: 1.105 | M147: 6000 | N147: -
A148: M1 | B148: Best settings with short losing streaks | C148: Labouchere | D148: 1-2-3 line | E148: none | F148: -10824.93 | G148: 14514.26 | H148: 1.0603 | I148: 6600 | J148: YES, after 36 trades | K148: =IF(G148=0,"",F148/G148) -> -0.74581343 | L148: 0.761 | M148: 12600 | N148: -
A149: M1 | B149: Best settings with short losing streaks | C149: Labouchere | D149: 1-2-3 line | E149: $500 | F149: -10391.26 | G149: 12194.91 | H149: 1.0331 | I149: 500 | J149: YES, after 233 trades | K149: =IF(G149=0,"",F149/G149) -> -0.85209813 | L149: 0.865 | M149: 5000 | N149: -
A150: M1 | B150: Best settings with short losing streaks | C150: Grand Martingale | D150: x2 + 1 unit | E150: none | F150: -31774.6 | G150: 53400 | H150: 1.6885 | I150: 26050 | J150: YES, after 149 trades | K150: =IF(G150=0,"",F150/G150) -> -0.59502996 | L150: 0.585 | M150: 53400 | N150: -
A151: M1 | B151: Best settings with short losing streaks | C151: Grand Martingale | D151: x2 + 1 unit | E151: $500 | F151: -10315.88 | G151: 12598.42 | H151: 1.0257 | I151: 500 | J151: YES, after 321 trades | K151: =IF(G151=0,"",F151/G151) -> -0.81882331 | L151: 0.9 | M151: 5000 | N151: -
A152: M1 | B152: Best settings with short losing streaks | C152: Paroli | D152: x2 after a win, 3-win reset | E152: none | F152: 5027.13 | G152: 3489.39 | H152: 0.3412 | I152: 200 | J152: no | K152: =IF(G152=0,"",F152/G152) -> 1.4406902 | L152: 1.057 | M152: 750 | N152: 6
A153: M1 | B153: Best settings with short losing streaks | C153: Paroli | D153: x2 after a win, 3-win reset | E153: $500 | F153: 5027.13 | G153: 3489.39 | H153: 0.3412 | I153: 200 | J153: no | K153: =IF(G153=0,"",F153/G153) -> 1.4406902 | L153: 1.057 | M153: 750 | N153: 6
A154: M1 | B154: Best settings with short losing streaks | C154: Reverse D'Alembert | D154: +1 unit after a win | E154: none | F154: 12991.95 | G154: 3996.72 | H154: 0.393 | I154: 500 | J154: no | K154: =IF(G154=0,"",F154/G154) -> 3.250653 | L154: 1.095 | M154: 1950 | N154: 2
A155: M1 | B155: Best settings with short losing streaks | C155: Reverse D'Alembert | D155: +1 unit after a win | E155: $500 | F155: 12991.95 | G155: 3996.72 | H155: 0.393 | I155: 500 | J155: no | K155: =IF(G155=0,"",F155/G155) -> 3.250653 | L155: 1.095 | M155: 1950 | N155: 2
A156: M1 | B156: Best settings with short losing streaks | C156: Delayed recovery | D156: starts after 2 losses | E156: none | F156: 31079.46 | G156: 6132.11 | H156: 0.4347 | I156: 2094.04 | J156: no | K156: =IF(G156=0,"",F156/G156) -> 5.0683142 | L156: 1.232 | M156: 5928.35 | N156: -
A157: M1 | B157: Best settings with short losing streaks | C157: Delayed recovery | D157: starts after 2 losses | E157: $500 | F157: 28879.31 | G157: 6612.83 | H157: 0.4751 | I157: 500 | J157: no | K157: =IF(G157=0,"",F157/G157) -> 4.3671635 | L157: 1.193 | M157: 4918.69 | N157: -
...

Sheet Rule C split test
A1: Rule C and Rule C split with the loss split over 1, 2, 3, 4 or 5 trades (2021-2026, after spread)
A2: Rule C: carried = how far closed equity is below its last high; next risk = max(base, carried / split). Rule C split: the same, and the base steps up with total profit (200 -> 200/3, 500 -> 500/5, 1000 -> 1000/8, then +1 part per +500). $10,000 start, $50 base, hard cap $500 with Clamp unless shown. Partial closes update the carried losses per part.
A4: WHAT IT SHOWS
A5: 1. With the best settings (profitable signals) and the hard cap on, Rule C split at split 2 or 3 made 5-9x the profit of fixed risk (Off), and per $ staked it lost about the same as Off.
A6: 2. Without the hard cap, Rule C split at split 1-3 blew the $10,000 account on M1, M5 and M15. With the default settings every Rule C variant blew the account.
A7: 3. Split 3 was the better choice than 2 on most cases: similar profit with a smaller drawdown (M15 best: 33% vs 46%). Drawdowns are still far larger than Off (16-70% vs 3-17%).
A8: 4. The cap action matters: "Start again" (forget the carried losses when the risk would pass the cap) kept M5 alive where Clamp blew it, and gave M15 its best profit for the drawdown.
A9: 5. Stress test (part 3): add 0.05-0.10 R of extra cost per trade (live slippage, weaker edge). H1 stays clearly profitable; M15 holds to about 0.05 R; M1 and M5 blow up - their edge is too thin.
A11: PART 1 - split 1 to 5, without and with the $500 hard cap (Clamp)
A12: Timeframe | B12: Settings | C12: Rule | D12: Split | E12: Hard cap | F12: Net profit ($) | G12: Max drawdown ($) | H12: Max drawdown % | I12: Average stake ($) | J12: Largest stake ($) | K12: Account blown? | L12: Profit / max drawdown | M12: vs Off (1 = same) | N12: Profit per $ of average stake | O12: Max drawdown per $ of average stake | P12: 2021-23 alone: net ($) | Q12: 2024-26 alone: net ($)
A13: M1 | B13: Default settings | C13: Off (fixed $50) | D13: - | E13: - | F13: -10035.04 | G13: 10184.86 | H13: 1.0035 | I13: 50 | J13: 50 | K13: YES, after 482 trades | L13: =IF(G13=0,"",F13/G13) -> -0.98528993 | M13: 1 | N13: =IF(I13=0,"",F13/I13) -> -200.7008 | O13: =IF(I13=0,"",G13/I13) -> 203.6972 | P13: BLOWN | Q13: BLOWN
A14: M1 | B14: Default settings | C14: Rule C | D14: 1 | E14: none | F14: -11542.87 | G14: 12800 | H14: 1.1371 | I14: 495.95 | J14: 6400 | K14: YES, after 36 trades | L14: =IF(G14=0,"",F14/G14) -> -0.90178672 | M14: =IF(OR(L13="",L13<=0,L14=""),"",L14/L13) | N14: =IF(I14=0,"",F14/I14) -> -23.274262 | O14: =IF(I14=0,"",G14/I14) -> 25.809053 | P14: BLOWN | Q14: BLOWN
A15: M1 | B15: Default settings | C15: Rule C | D15: 1 | E15: $500 | F15: -10372.82 | G15: 10667.63 | H15: 1.0362 | I15: 387.04 | J15: 500 | K15: YES, after 49 trades | L15: =IF(G15=0,"",F15/G15) -> -0.97236406 | M15: =IF(OR(L13="",L13<=0,L15=""),"",L15/L13) | N15: =IF(I15=0,"",F15/I15) -> -26.800382 | O15: =IF(I15=0,"",G15/I15) -> 27.562087 | P15: BLOWN | Q15: BLOWN
A16: M1 | B16: Default settings | C16: Rule C | D16: 2 | E16: none | F16: -12357.22 | G16: 12531.92 | H16: 1.2317 | I16: 493.42 | J16: 4177.31 | K16: YES, after 42 trades | L16: =IF(G16=0,"",F16/G16) -> -0.9860596 | M16: =IF(OR(L13="",L13<=0,L16=""),"",L16/L13) | N16: =IF(I16=0,"",F16/I16) -> -25.044019 | O16: =IF(I16=0,"",G16/I16) -> 25.398079 | P16: BLOWN | Q16: BLOWN
A17: M1 | B17: Default settings | C17: Rule C | D17: 2 | E17: $500 | F17: -10102.43 | G17: 10277.13 | H17: 1.0101 | I17: 317.1 | J17: 500 | K17: YES, after 70 trades | L17: =IF(G17=0,"",F17/G17) -> -0.98300109 | M17: =IF(OR(L13="",L13<=0,L17=""),"",L17/L13) | N17: =IF(I17=0,"",F17/I17) -> -31.858814 | O17: =IF(I17=0,"",G17/I17) -> 32.409745 | P17: BLOWN | Q17: BLOWN
A18: M1 | B18: Default settings | C18: Rule C | D18: 3 | E18: none | F18: -12514.58 | G18: 12664.41 | H18: 1.2477 | I18: 446.12 | J18: 3166.1 | K18: YES, after 42 trades | L18: =IF(G18=0,"",F18/G18) -> -0.98816921 | M18: =IF(OR(L13="",L13<=0,L18=""),"",L18/L13) | N18: =IF(I18=0,"",F18/I18) -> -28.052049 | O18: =IF(I18=0,"",G18/I18) -> 28.3879 | P18: BLOWN | Q18: BLOWN
A19: M1 | B19: Default settings | C19: Rule C | D19: 3 | E19: $500 | F19: -10456.31 | G19: 10606.13 | H19: 1.045 | I19: 298.43 | J19: 500 | K19: YES, after 63 trades | L19: =IF(G19=0,"",F19/G19) -> -0.98587421 | M19: =IF(OR(L13="",L13<=0,L19=""),"",L19/L13) | N19: =IF(I19=0,"",F19/I19) -> -35.037731 | O19: =IF(I19=0,"",G19/I19) -> 35.539758 | P19: BLOWN | Q19: BLOWN
A20: M1 | B20: Default settings | C20: Rule C | D20: 4 | E20: none | F20: -10778.99 | G20: 10928.82 | H20: 1.0767 | I20: 415.27 | J20: 2185.76 | K20: YES, after 49 trades | L20: =IF(G20=0,"",F20/G20) -> -0.98629038 | M20: =IF(OR(L13="",L13<=0,L20=""),"",L20/L13) | N20: =IF(I20=0,"",F20/I20) -> -25.956582 | O20: =IF(I20=0,"",G20/I20) -> 26.317384 | P20: BLOWN | Q20: BLOWN
A21: M1 | B21: Default settings | C21: Rule C | D21: 4 | E21: $500 | F21: -10066.81 | G21: 10216.63 | H21: 1.0066 | I21: 294.45 | J21: 500 | K21: YES, after 67 trades | L21: =IF(G21=0,"",F21/G21) -> -0.98533567 | M21: =IF(OR(L13="",L13<=0,L21=""),"",L21/L13) | N21: =IF(I21=0,"",F21/I21) -> -34.188521 | O21: =IF(I21=0,"",G21/I21) -> 34.697334 | P21: BLOWN | Q21: BLOWN
A22: M1 | B22: Default settings | C22: Rule C | D22: 5 | E22: none | F22: -10831.28 | G22: 10981.1 | H22: 1.0819 | I22: 387.62 | J22: 1896.58 | K22: YES, after 55 trades | L22: =IF(G22=0,"",F22/G22) -> -0.98635656 | M22: =IF(OR(L13="",L13<=0,L22=""),"",L22/L13) | N22: =IF(I22=0,"",F22/I22) -> -27.943037 | O22: =IF(I22=0,"",G22/I22) -> 28.32955 | P22: BLOWN | Q22: BLOWN
A23: M1 | B23: Default settings | C23: Rule C | D23: 5 | E23: $500 | F23: -10165.7 | G23: 10315.53 | H23: 1.0163 | I23: 290.36 | J23: 500 | K23: YES, after 71 trades | L23: =IF(G23=0,"",F23/G23) -> -0.9854753 | M23: =IF(OR(L13="",L13<=0,L23=""),"",L23/L13) | N23: =IF(I23=0,"",F23/I23) -> -35.010676 | O23: =IF(I23=0,"",G23/I23) -> 35.526691 | P23: BLOWN | Q23: BLOWN
A24: M1 | B24: Default settings | C24: Rule C split | D24: 1 | E24: none | F24: -10718.14 | G24: 12800 | H24: 1.0594 | I24: 628.1 | J24: 6400 | K24: YES, after 34 trades | L24: =IF(G24=0,"",F24/G24) -> -0.83735469 | M24: =IF(OR(L13="",L13<=0,L24=""),"",L24/L13) | N24: =IF(I24=0,"",F24/I24) -> -17.064385 | O24: =IF(I24=0,"",G24/I24) -> 20.378921 | P24: BLOWN | Q24: BLOWN
A25: M1 | B25: Default settings | C25: Rule C split | D25: 1 | E25: $500 | F25: -10179.94 | G25: 10499.01 | H25: 1.0174 | I25: 391.84 | J25: 500 | K25: YES, after 48 trades | L25: =IF(G25=0,"",F25/G25) -> -0.96960952 | M25: =IF(OR(L13="",L13<=0,L25=""),"",L25/L13) | N25: =IF(I25=0,"",F25/I25) -> -25.979839 | O25: =IF(I25=0,"",G25/I25) -> 26.794125 | P25: BLOWN | Q25: BLOWN
A26: M1 | B26: Default settings | C26: Rule C split | D26: 2 | E26: none | F26: -12357.22 | G26: 12531.92 | H26: 1.2317 | I26: 493.42 | J26: 4177.31 | K26: YES, after 42 trades | L26: =IF(G26=0,"",F26/G26) -> -0.9860596 | M26: =IF(OR(L13="",L13<=0,L26=""),"",L26/L13) | N26: =IF(I26=0,"",F26/I26) -> -25.044019 | O26: =IF(I26=0,"",G26/I26) -> 25.398079 | P26: BLOWN | Q26: BLOWN
A27: M1 | B27: Default settings | C27: Rule C split | D27: 2 | E27: $500 | F27: -10102.43 | G27: 10277.13 | H27: 1.0101 | I27: 317.1 | J27: 500 | K27: YES, after 70 trades | L27: =IF(G27=0,"",F27/G27) -> -0.98300109 | M27: =IF(OR(L13="",L13<=0,L27=""),"",L27/L13) | N27: =IF(I27=0,"",F27/I27) -> -31.858814 | O27: =IF(I27=0,"",G27/I27) -> 32.409745 | P27: BLOWN | Q27: BLOWN
A28: M1 | B28: Default settings | C28: Rule C split | D28: 3 | E28: none | F28: -12514.58 | G28: 12664.41 | H28: 1.2477 | I28: 446.12 | J28: 3166.1 | K28: YES, after 42 trades | L28: =IF(G28=0,"",F28/G28) -> -0.98816921 | M28: =IF(OR(L13="",L13<=0,L28=""),"",L28/L13) | N28: =IF(I28=0,"",F28/I28) -> -28.052049 | O28: =IF(I28=0,"",G28/I28) -> 28.3879 | P28: BLOWN | Q28: BLOWN
A29: M1 | B29: Default settings | C29: Rule C split | D29: 3 | E29: $500 | F29: -10456.31 | G29: 10606.13 | H29: 1.045 | I29: 298.43 | J29: 500 | K29: YES, after 63 trades | L29: =IF(G29=0,"",F29/G29) -> -0.98587421 | M29: =IF(OR(L13="",L13<=0,L29=""),"",L29/L13) | N29: =IF(I29=0,"",F29/I29) -> -35.037731 | O29: =IF(I29=0,"",G29/I29) -> 35.539758 | P29: BLOWN | Q29: BLOWN
A30: M1 | B30: Default settings | C30: Rule C split | D30: 4 | E30: none | F30: -10778.99 | G30: 10928.82 | H30: 1.0767 | I30: 415.27 | J30: 2185.76 | K30: YES, after 49 trades | L30: =IF(G30=0,"",F30/G30) -> -0.98629038 | M30: =IF(OR(L13="",L13<=0,L30=""),"",L30/L13) | N30: =IF(I30=0,"",F30/I30) -> -25.956582 | O30: =IF(I30=0,"",G30/I30) -> 26.317384 | P30: BLOWN | Q30: BLOWN
A31: M1 | B31: Default settings | C31: Rule C split | D31: 4 | E31: $500 | F31: -10066.81 | G31: 10216.63 | H31: 1.0066 | I31: 294.45 | J31: 500 | K31: YES, after 67 trades | L31: =IF(G31=0,"",F31/G31) -> -0.98533567 | M31: =IF(OR(L13="",L13<=0,L31=""),"",L31/L13) | N31: =IF(I31=0,"",F31/I31) -> -34.188521 | O31: =IF(I31=0,"",G31/I31) -> 34.697334 | P31: BLOWN | Q31: BLOWN
A32: M1 | B32: Default settings | C32: Rule C split | D32: 5 | E32: none | F32: -10831.28 | G32: 10981.1 | H32: 1.0819 | I32: 387.62 | J32: 1896.58 | K32: YES, after 55 trades | L32: =IF(G32=0,"",F32/G32) -> -0.98635656 | M32: =IF(OR(L13="",L13<=0,L32=""),"",L32/L13) | N32: =IF(I32=0,"",F32/I32) -> -27.943037 | O32: =IF(I32=0,"",G32/I32) -> 28.32955 | P32: BLOWN | Q32: BLOWN
A33: M1 | B33: Default settings | C33: Rule C split | D33: 5 | E33: $500 | F33: -10165.7 | G33: 10315.53 | H33: 1.0163 | I33: 290.36 | J33: 500 | K33: YES, after 71 trades | L33: =IF(G33=0,"",F33/G33) -> -0.9854753 | M33: =IF(OR(L13="",L13<=0,L33=""),"",L33/L13) | N33: =IF(I33=0,"",F33/I33) -> -35.010676 | O33: =IF(I33=0,"",G33/I33) -> 35.526691 | P33: BLOWN | Q33: BLOWN
A35: M1 | B35: Best settings (profit) | C35: Off (fixed $50) | D35: - | E35: - | F35: 5441.57 | G35: 1480.81 | H35: 0.1332 | I35: 50 | J35: 50 | K35: no | L35: =IF(G35=0,"",F35/G35) -> 3.6747253 | M35: 1 | N35: =IF(I35=0,"",F35/I35) -> 108.8314 | O35: =IF(I35=0,"",G35/I35) -> 29.6162 | P35: 2544.19 | Q35: 2897.39
A36: M1 | B36: Best settings (profit) | C36: Rule C | D36: 1 | E36: none | F36: -14587.48 | G36: 25600 | H36: 1.2183 | I36: 302.45 | J36: 12800 | K36: YES, after 162 trades | L36: =IF(G36=0,"",F36/G36) -> -0.56982344 | M36: =IF(OR(L35="",L35<=0,L36=""),"",L36/L35) -> -0.15506559 | N36: =IF(I36=0,"",F36/I36) -> -48.231046 | O36: =IF(I36=0,"",G36/I36) -> 84.64209 | P36: BLOWN | Q36: BLOWN
A37: M1 | B37: Best settings (profit) | C37: Rule C | D37: 1 | E37: $500 | F37: 45461.97 | G37: 13108.1 | H37: 0.4775 | I37: 299.87 | J37: 500 | K37: no | L37: =IF(G37=0,"",F37/G37) -> 3.4682349 | M37: =IF(OR(L35="",L35<=0,L37=""),"",L37/L35) -> 0.94380793 | N37: =IF(I37=0,"",F37/I37) -> 151.6056 | O37: =IF(I37=0,"",G37/I37) -> 43.712609 | P37: 24204.3 | Q37: 20757.23
A38: M1 | B38: Best settings (profit) | C38: Rule C | D38: 2 | E38: none | F38: 29312.68 | G38: 12974.63 | H38: 0.3816 | I38: 98.07 | J38: 6487.32 | K38: no | L38: =IF(G38=0,"",F38/G38) -> 2.2592305 | M38: =IF(OR(L35="",L35<=0,L38=""),"",L38/L35) -> 0.61480255 | N38: =IF(I38=0,"",F38/I38) -> 298.89548 | O38: =IF(I38=0,"",G38/I38) -> 132.29968 | P38: 13643.04 | Q38: 15669.64
A39: M1 | B39: Best settings (profit) | C39: Rule C | D39: 2 | E39: $500 | F39: 27201.9 | G39: 4680.46 | H39: 0.3806 | I39: 103.53 | J39: 500 | K39: no | L39: =IF(G39=0,"",F39/G39) -> 5.8118005 | M39: =IF(OR(L35="",L35<=0,L39=""),"",L39/L35) -> 1.5815605 | N39: =IF(I39=0,"",F39/I39) -> 262.74413 | O39: =IF(I39=0,"",G39/I39) -> 45.208732 | P39: 12629.51 | Q39: 14572.4
A40: M1 | B40: Best settings (profit) | C40: Rule C | D40: 3 | E40: none | F40: 18740.77 | G40: 6943.37 | H40: 0.2834 | I40: 86.22 | J40: 2314.46 | K40: no | L40: =IF(G40=0,"",F40/G40) -> 2.6990885 | M40: =IF(OR(L35="",L35<=0,L40=""),"",L40/L35) -> 0.73450074 | N40: =IF(I40=0,"",F40/I40) -> 217.35989 | O40: =IF(I40=0,"",G40/I40) -> 80.530851 | P40: 8694.75 | Q40: 10036.31
A41: M1 | B41: Best settings (profit) | C41: Rule C | D41: 3 | E41: $500 | F41: 17975.08 | G41: 4689.09 | H41: 0.2549 | I41: 90.19 | J41: 500 | K41: no | L41: =IF(G41=0,"",F41/G41) -> 3.8333834 | M41: =IF(OR(L35="",L35<=0,L41=""),"",L41/L35) -> 1.0431755 | N41: =IF(I41=0,"",F41/I41) -> 199.30236 | O41: =IF(I41=0,"",G41/I41) -> 51.991241 | P41: 8584.45 | Q41: 9380.91
A42: M1 | B42: Best settings (profit) | C42: Rule C | D42: 4 | E42: none | F42: 14599.84 | G42: 4698.07 | H42: 0.1996 | I42: 77.34 | J42: 1174.52 | K42: no | L42: =IF(G42=0,"",F42/G42) -> 3.107625 | M42: =IF(OR(L35="",L35<=0,L42=""),"",L42/L35) -> 0.84567547 | N42: =IF(I42=0,"",F42/I42) -> 188.77476 | O42: =IF(I42=0,"",G42/I42) -> 60.745668 | P42: 6708.84 | Q42: 7838.6
A43: M1 | B43: Best settings (profit) | C43: Rule C | D43: 4 | E43: $500 | F43: 14350.53 | G43: 4438.03 | H43: 0.1895 | I43: 78.81 | J43: 500 | K43: no | L43: =IF(G43=0,"",F43/G43) -> 3.2335361 | M43: =IF(OR(L35="",L35<=0,L43=""),"",L43/L35) -> 0.87993952 | N43: =IF(I43=0,"",F43/I43) -> 182.09022 | O43: =IF(I43=0,"",G43/I43) -> 56.313031 | P43: 6708.84 | Q43: 7589.3
A44: M1 | B44: Best settings (profit) | C44: Rule C | D44: 5 | E44: none | F44: 12352.54 | G44: 3899.8 | H44: 0.2019 | I44: 71.03 | J44: 779.96 | K44: no | L44: =IF(G44=0,"",F44/G44) -> 3.1674804 | M44: =IF(OR(L35="",L35<=0,L44=""),"",L44/L35) -> 0.86196385 | N44: =IF(I44=0,"",F44/I44) -> 173.90596 | O44: =IF(I44=0,"",G44/I44) -> 54.903562 | P44: 5654.23 | Q44: 6637.2
A45: M1 | B45: Best settings (profit) | C45: Rule C | D45: 5 | E45: $500 | F45: 12262.1 | G45: 3762.65 | H45: 0.192 | I45: 71.45 | J45: 500 | K45: no | L45: =IF(G45=0,"",F45/G45) -> 3.2589 | M45: =IF(OR(L35="",L35<=0,L45=""),"",L45/L35) -> 0.88684179 | N45: =IF(I45=0,"",F45/I45) -> 171.61791 | O45: =IF(I45=0,"",G45/I45) -> 52.661302 | P45: 5654.23 | Q45: 6546.75
A46: M1 | B46: Best settings (profit) | C46: Rule C split | D46: 1 | E46: none | F46: -47660.86 | G46: 123076.92 | H46: 1.4409 | I46: 1751.95 | J46: 61538.46 | K46: YES, after 161 trades | L46: =IF(G46=0,"",F46/G46) -> -0.3872445 | M46: =IF(OR(L35="",L35<=0,L46=""),"",L46/L35) -> -0.10538053 | N46: =IF(I46=0,"",F46/I46) -> -27.204464 | O46: =IF(I46=0,"",G46/I46) -> 70.251388 | P46: BLOWN | Q46: BLOWN
A47: M1 | B47: Best settings (profit) | C47: Rule C split | D47: 1 | E47: $500 | F47: 54624.29 | G47: 14748.1 | H47: 0.9587 | I47: 485.15 | J47: 500 | K47: no | L47: =IF(G47=0,"",F47/G47) -> 3.7038188 | M47: =IF(OR(L35="",L35<=0,L47=""),"",L47/L35) -> 1.0079172 | N47: =IF(I47=0,"",F47/I47) -> 112.59258 | O47: =IF(I47=0,"",G47/I47) -> 30.399052 | P47: 25604.8 | Q47: 32671.92
A48: M1 | B48: Best settings (profit) | C48: Rule C split | D48: 2 | E48: none | F48: -11810.5 | G48: 16596.72 | H48: 1.1224 | I48: 274.17 | J48: 5532.24 | K48: YES, after 162 trades | L48: =IF(G48=0,"",F48/G48) -> -0.71161651 | M48: =IF(OR(L35="",L35<=0,L48=""),"",L48/L35) -> -0.19365162 | N48: =IF(I48=0,"",F48/I48) -> -43.077288 | O48: =IF(I48=0,"",G48/I48) -> 60.534413 | P48: BLOWN | Q48: BLOWN
A49: M1 | B49: Best settings (profit) | C49: Rule C split | D49: 2 | E49: $500 | F49: 60097.8 | G49: 14726.29 | H49: 0.7043 | I49: 462.85 | J49: 500 | K49: no | L49: =IF(G49=0,"",F49/G49) -> 4.0809871 | M49: =IF(OR(L35="",L35<=0,L49=""),"",L49/L35) -> 1.1105557 | N49: =IF(I49=0,"",F49/I49) -> 129.84293 | O49: =IF(I49=0,"",G49/I49) -> 31.81655 | P49: 30669.59 | Q49: 27036.37
A50: M1 | B50: Best settings (profit) | C50: Rule C split | D50: 3 | E50: none | F50: -10766.87 | G50: 13344.93 | H50: 1.061 | I50: 209.6 | J50: 3336.23 | K50: YES, after 253 trades | L50: =IF(G50=0,"",F50/G50) -> -0.80681352 | M50: =IF(OR(L35="",L35<=0,L50=""),"",L50/L35) -> -0.21955751 | N50: =IF(I50=0,"",F50/I50) -> -51.368655 | O50: =IF(I50=0,"",G50/I50) -> 63.668559 | P50: BLOWN | Q50: BLOWN
A51: M1 | B51: Best settings (profit) | C51: Rule C split | D51: 3 | E51: $500 | F51: 58981.63 | G51: 14696.99 | H51: 0.5892 | I51: 436.85 | J51: 500 | K51: no | L51: =IF(G51=0,"",F51/G51) -> 4.0131775 | M51: =IF(OR(L35="",L35<=0,L51=""),"",L51/L35) -> 1.0921027 | N51: =IF(I51=0,"",F51/I51) -> 135.01575 | O51: =IF(I51=0,"",G51/I51) -> 33.643104 | P51: 30064.4 | Q51: 23611.94
A52: M1 | B52: Best settings (profit) | C52: Rule C split | D52: 4 | E52: none | F52: 121682.91 | G52: 45739.7 | H52: 0.5173 | I52: 612.51 | J52: 11434.93 | K52: no | L52: =IF(G52=0,"",F52/G52) -> 2.6603347 | M52: =IF(OR(L35="",L35<=0,L52=""),"",L52/L35) -> 0.7239547 | N52: =IF(I52=0,"",F52/I52) -> 198.66273 | O52: =IF(I52=0,"",G52/I52) -> 74.675842 | P52: 45768.9 | Q52: BLOWN
A53: M1 | B53: Best settings (profit) | C53: Rule C split | D53: 4 | E53: $500 | F53: 57724.91 | G53: 14664.9 | H53: 0.5147 | I53: 412.12 | J53: 500 | K53: no | L53: =IF(G53=0,"",F53/G53) -> 3.9362635 | M53: =IF(OR(L35="",L35<=0,L53=""),"",L53/L35) -> 1.0711722 | N53: =IF(I53=0,"",F53/I53) -> 140.06821 | O53: =IF(I53=0,"",G53/I53) -> 35.584053 | P53: 28798.04 | Q53: 23039.73
A54: M1 | B54: Best settings (profit) | C54: Rule C split | D54: 5 | E54: none | F54: 99850.84 | G54: 37361.04 | H54: 0.5121 | I54: 539.09 | J54: 7472.21 | K54: no | L54: =IF(G54=0,"",F54/G54) -> 2.6725926 | M54: =IF(OR(L35="",L35<=0,L54=""),"",L54/L35) -> 0.72729045 | N54: =IF(I54=0,"",F54/I54) -> 185.22109 | O54: =IF(I54=0,"",G54/I54) -> 69.303901 | P54: 36023.95 | Q54: BLOWN
A55: M1 | B55: Best settings (profit) | C55: Rule C split | D55: 5 | E55: $500 | F55: 55798.86 | G55: 14597.14 | H55: 0.4147 | I55: 392.08 | J55: 500 | K55: no | L55: =IF(G55=0,"",F55/G55) -> 3.8225885 | M55: =IF(OR(L35="",L35<=0,L55=""),"",L55/L35) -> 1.0402379 | N55: =IF(I55=0,"",F55/I55) -> 142.31499 | O55: =IF(I55=0,"",G55/I55) -> 37.230004 | P55: 27137.31 | Q55: 24601.81
A57: M1 | B57: Best settings with short losing streaks | C57: Off (fixed $50) | D57: - | E57: - | F57: 4561.27 | G57: 1467.44 | H57: 0.1443 | I57: 50 | J57: 50 | K57: no | L57: =IF(G57=0,"",F57/G57) -> 3.1083179 | M57: 1 | N57: =IF(I57=0,"",F57/I57) -> 91.2254 | O57: =IF(I57=0,"",G57/I57) -> 29.3488 | P57: 1249.71 | Q57: 3311.56
A58: M1 | B58: Best settings with short losing streaks | C58: Rule C | D58: 1 | E58: none | F58: -16366.31 | G58: 25600 | H58: 1.331 | I58: 303.33 | J58: 12800 | K58: YES, after 149 trades | L58: =IF(G58=0,"",F58/G58) -> -0.63930898 | M58: =IF(OR(L57="",L57<=0,L58=""),"",L58/L57) -> -0.20567683 | N58: =IF(I58=0,"",F58/I58) -> -53.955461 | O58: =IF(I58=0,"",G58/I58) -> 84.396532 | P58: BLOWN | Q58: 267471.8
A59: M1 | B59: Best settings with short losing streaks | C59: Rule C | D59: 1 | E59: $500 | F59: 43885.15 | G59: 9959.55 | H59: 0.5124 | I59: 292.35 | J59: 500 | K59: no | L59: =IF(G59=0,"",F59/G59) -> 4.4063386 | M59: =IF(OR(L57="",L57<=0,L59=""),"",L59/L57) -> 1.4175959 | N59: =IF(I59=0,"",F59/I59) -> 150.11168 | O59: =IF(I59=0,"",G59/I59) -> 34.067214 | P59: 18183.03 | Q59: 24546.1
A60: M1 | B60: Best settings with short losing streaks | C60: Rule C | D60: 2 | E60: none | F60: 26511.99 | G60: 5766.5 | H60: 0.2507 | I60: 88.53 | J60: 2883.25 | K60: no | L60: =IF(G60=0,"",F60/G60) -> 4.5975878 | M60: =IF(OR(L57="",L57<=0,L60=""),"",L60/L57) -> 1.4791241 | N60: =IF(I60=0,"",F60/I60) -> 299.46899 | O60: =IF(I60=0,"",G60/I60) -> 65.136112 | P60: 11934.05 | Q60: 14522.53
A61: M1 | B61: Best settings with short losing streaks | C61: Rule C | D61: 2 | E61: $500 | F61: 24820.59 | G61: 6900.19 | H61: 0.545 | I61: 98.46 | J61: 500 | K61: no | L61: =IF(G61=0,"",F61/G61) -> 3.5970879 | M61: =IF(OR(L57="",L57<=0,L61=""),"",L61/L57) -> 1.1572458 | N61: =IF(I61=0,"",F61/I61) -> 252.08806 | O61: =IF(I61=0,"",G61/I61) -> 70.08115 | P61: 10926.86 | Q61: 13838.33
A62: M1 | B62: Best settings with short losing streaks | C62: Rule C | D62: 3 | E62: none | F62: 17270.82 | G62: 2922.89 | H62: 0.2395 | I62: 78.19 | J62: 974.3 | K62: no | L62: =IF(G62=0,"",F62/G62) -> 5.9088163 | M62: =IF(OR(L57="",L57<=0,L62=""),"",L62/L57) -> 1.9009691 | N62: =IF(I62=0,"",F62/I62) -> 220.88272 | O62: =IF(I62=0,"",G62/I62) -> 37.38189 | P62: 7529.66 | Q62: 9607.37
A63: M1 | B63: Best settings with short losing streaks | C63: Rule C | D63: 3 | E63: $500 | F63: 16914.3 | G63: 3178.25 | H63: 0.2698 | I63: 79.52 | J63: 500 | K63: no | L63: =IF(G63=0,"",F63/G63) -> 5.321891 | M63: =IF(OR(L57="",L57<=0,L63=""),"",L63/L57) -> 1.712145 | N63: =IF(I63=0,"",F63/I63) -> 212.70498 | O63: =IF(I63=0,"",G63/I63) -> 39.967933 | P63: 7394.76 | Q63: 9385.76
A64: M1 | B64: Best settings with short losing streaks | C64: Rule C | D64: 4 | E64: none | F64: 13407.83 | G64: 2614.68 | H64: 0.2319 | I64: 72.19 | J64: 653.67 | K64: no | L64: =IF(G64=0,"",F64/G64) -> 5.1279048 | M64: =IF(OR(L57="",L57<=0,L64=""),"",L64/L57) -> 1.6497363 | N64: =IF(I64=0,"",F64/I64) -> 185.72974 | O64: =IF(I64=0,"",G64/I64) -> 36.219421 | P64: 5631.99 | Q64: 7650.82
A65: M1 | B65: Best settings with short losing streaks | C65: Rule C | D65: 4 | E65: $500 | F65: 13304.69 | G65: 2919.95 | H65: 0.259 | I65: 72.56 | J65: 500 | K65: no | L65: =IF(G65=0,"",F65/G65) -> 4.5564787 | M65: =IF(OR(L57="",L57<=0,L65=""),"",L65/L57) -> 1.4658986 | N65: =IF(I65=0,"",F65/I65) -> 183.36122 | O65: =IF(I65=0,"",G65/I65) -> 40.241869 | P65: 5593 | Q65: 7586.67
A66: M1 | B66: Best settings with short losing streaks | C66: Rule C | D66: 5 | E66: none | F66: 11367.51 | G66: 2411.45 | H66: 0.1911 | I66: 67.29 | J66: 482.29 | K66: no | L66: =IF(G66=0,"",F66/G66) -> 4.7139729 | M66: =IF(OR(L57="",L57<=0,L66=""),"",L66/L57) -> 1.5165672 | N66: =IF(I66=0,"",F66/I66) -> 168.93313 | O66: =IF(I66=0,"",G66/I66) -> 35.836677 | P66: 4666.42 | Q66: 6601.96
A67: M1 | B67: Best settings with short losing streaks | C67: Rule C | D67: 5 | E67: $500 | F67: 11367.51 | G67: 2411.45 | H67: 0.1911 | I67: 67.29 | J67: 482.29 | K67: no | L67: =IF(G67=0,"",F67/G67) -> 4.7139729 | M67: =IF(OR(L57="",L57<=0,L67=""),"",L67/L57) -> 1.5165672 | N67: =IF(I67=0,"",F67/I67) -> 168.93313 | O67: =IF(I67=0,"",G67/I67) -> 35.836677 | P67: 4666.42 | Q67: 6601.96
A68: M1 | B68: Best settings with short losing streaks | C68: Rule C split | D68: 1 | E68: none | F68: -57211.96 | G68: 122352.94 | H68: 1.6283 | I68: 1754.04 | J68: 61176.47 | K68: YES, after 148 trades | L68: =IF(G68=0,"",F68/G68) -> -0.46759775 | M68: =IF(OR(L57="",L57<=0,L68=""),"",L68/L57) -> -0.15043434 | N68: =IF(I68=0,"",F68/I68) -> -32.617249 | O68: =IF(I68=0,"",G68/I68) -> 69.754931 | P68: BLOWN | Q68: BLOWN
A69: M1 | B69: Best settings with short losing streaks | C69: Rule C split | D69: 1 | E69: $500 | F69: 49345.47 | G69: 14209.31 | H69: 0.9025 | I69: 483.59 | J69: 500 | K69: no | L69: =IF(G69=0,"",F69/G69) -> 3.4727562 | M69: =IF(OR(L57="",L57<=0,L69=""),"",L69/L57) -> 1.1172462 | N69: =IF(I69=0,"",F69/I69) -> 102.03989 | O69: =IF(I69=0,"",G69/I69) -> 29.382969 | P69: 16093.03 | Q69: 34567.47
A70: M1 | B70: Best settings with short losing streaks | C70: Rule C split | D70: 2 | E70: none | F70: -10444.81 | G70: 13502.49 | H70: 1.0341 | I70: 213.43 | J70: 4500.83 | K70: YES, after 149 trades | L70: =IF(G70=0,"",F70/G70) -> -0.77354695 | M70: =IF(OR(L57="",L57<=0,L70=""),"",L70/L57) -> -0.24886353 | N70: =IF(I70=0,"",F70/I70) -> -48.937872 | O70: =IF(I70=0,"",G70/I70) -> 63.264255 | P70: BLOWN | Q70: 121917.67
A71: M1 | B71: Best settings with short losing streaks | C71: Rule C split | D71: 2 | E71: $500 | F71: 51668.5 | G71: 14117.68 | H71: 0.705 | I71: 456.55 | J71: 500 | K71: no | L71: =IF(G71=0,"",F71/G71) -> 3.6598435 | M71: =IF(OR(L57="",L57<=0,L71=""),"",L71/L57) -> 1.1774354 | N71: =IF(I71=0,"",F71/I71) -> 113.17161 | O71: =IF(I71=0,"",G71/I71) -> 30.922528 | P71: 18507.49 | Q71: 28342.43
A72: M1 | B72: Best settings with short losing streaks | C72: Rule C split | D72: 3 | E72: none | F72: -11768.27 | G72: 16423.24 | H72: 1.1207 | I72: 247.77 | J72: 4105.81 | K72: YES, after 321 trades | L72: =IF(G72=0,"",F72/G72) -> -0.71656202 | M72: =IF(OR(L57="",L57<=0,L72=""),"",L72/L57) -> -0.23053048 | N72: =IF(I72=0,"",F72/I72) -> -47.496751 | O72: =IF(I72=0,"",G72/I72) -> 66.284215 | P72: BLOWN | Q72: 73006.69
A73: M1 | B73: Best settings with short losing streaks | C73: Rule C split | D73: 3 | E73: $500 | F73: 50663.19 | G73: 14012.75 | H73: 0.671 | I73: 426 | J73: 500 | K73: no | L73: =IF(G73=0,"",F73/G73) -> 3.6155066 | M73: =IF(OR(L57="",L57<=0,L73=""),"",L73/L57) -> 1.1631714 | N73: =IF(I73=0,"",F73/I73) -> 118.92768 | O73: =IF(I73=0,"",G73/I73) -> 32.893779 | P73: 18030.1 | Q73: 23179.05
A74: M1 | B74: Best settings with short losing streaks | C74: Rule C split | D74: 4 | E74: none | F74: 110320.05 | G74: 24102.38 | H74: 0.7508 | I74: 544.67 | J74: 6025.59 | K74: no | L74: =IF(G74=0,"",F74/G74) -> 4.5771434 | M74: =IF(OR(L57="",L57<=0,L74=""),"",L74/L57) -> 1.4725468 | N74: =IF(I74=0,"",F74/I74) -> 202.54475 | O74: =IF(I74=0,"",G74/I74) -> 44.251345 | P74: 35998.65 | Q74: 55773.95
A75: M1 | B75: Best settings with short losing streaks | C75: Rule C split | D75: 4 | E75: $500 | F75: 49722.18 | G75: 14056.36 | H75: 0.5407 | I75: 406.14 | J75: 500 | K75: no | L75: =IF(G75=0,"",F75/G75) -> 3.5373439 | M75: =IF(OR(L57="",L57<=0,L75=""),"",L75/L57) -> 1.1380252 | N75: =IF(I75=0,"",F75/I75) -> 122.42621 | O75: =IF(I75=0,"",G75/I75) -> 34.609642 | P75: 17933.71 | Q75: 21571.65
A76: M1 | B76: Best settings with short losing streaks | C76: Rule C split | D76: 5 | E76: none | F76: 89450.88 | G76: 23234 | H76: 0.4444 | I76: 482.92 | J76: 4646.8 | K76: no | L76: =IF(G76=0,"",F76/G76) -> 3.8499991 | M76: =IF(OR(L57="",L57<=0,L76=""),"",L76/L57) -> 1.2386118 | N76: =IF(I76=0,"",F76/I76) -> 185.22919 | O76: =IF(I76=0,"",G76/I76) -> 48.111488 | P76: 26251.45 | Q76: 44603.61
A77: M1 | B77: Best settings with short losing streaks | C77: Rule C split | D77: 5 | E77: $500 | F77: 47033.41 | G77: 13918.9 | H77: 0.4371 | I77: 385.77 | J77: 500 | K77: no | L77: =IF(G77=0,"",F77/G77) -> 3.379104 | M77: =IF(OR(L57="",L57<=0,L77=""),"",L77/L57) -> 1.0871166 | N77: =IF(I77=0,"",F77/I77) -> 121.92086 | O77: =IF(I77=0,"",G77/I77) -> 36.080825 | P77: 15246.81 | Q77: 25093.14
A79: M5 | B79: Default settings | C79: Off (fixed $50) | D79: - | E79: - | F79: -10000.13 | G79: 10120.74 | H79: 1 | I79: 50 | J79: 50 | K79: YES, after 1091 trades | L79: =IF(G79=0,"",F79/G79) -> -0.98808289 | M79: 1 | N79: =IF(I79=0,"",F79/I79) -> -200.0026 | O79: =IF(I79=0,"",G79/I79) -> 202.4148 | P79: BLOWN | Q79: -3308.89
A80: M5 | B80: Default settings | C80: Rule C | D80: 1 | E80: none | F80: -11431.31 | G80: 12800 | H80: 1.1259 | I80: 743.18 | J80: 6400 | K80: YES, after 21 trades | L80: =IF(G80=0,"",F80/G80) -> -0.89307109 | M80: =IF(OR(L79="",L79<=0,L80=""),"",L80/L79) | N80: =IF(I80=0,"",F80/I80) -> -15.381617 | O80: =IF(I80=0,"",G80/I80) -> 17.223284 | P80: BLOWN | Q80: BLOWN
A81: M5 | B81: Default settings | C81: Rule C | D81: 1 | E81: $500 | F81: -10408.55 | G81: 10594.19 | H81: 1.0401 | I81: 443.97 | J81: 500 | K81: YES, after 85 trades | L81: =IF(G81=0,"",F81/G81) -> -0.98247719 | M81: =IF(OR(L79="",L79<=0,L81=""),"",L81/L79) | N81: =IF(I81=0,"",F81/I81) -> -23.444264 | O81: =IF(I81=0,"",G81/I81) -> 23.862401 | P81: BLOWN | Q81: BLOWN
A82: M5 | B82: Default settings | C82: Rule C | D82: 2 | E82: none | F82: -11140.08 | G82: 12249.47 | H82: 1.1026 | I82: 476.36 | J82: 5041.66 | K82: YES, after 173 trades | L82: =IF(G82=0,"",F82/G82) -> -0.90943363 | M82: =IF(OR(L79="",L79<=0,L82=""),"",L82/L79) | N82: =IF(I82=0,"",F82/I82) -> -23.385843 | O82: =IF(I82=0,"",G82/I82) -> 25.714733 | P82: BLOWN | Q82: 41839.14
A83: M5 | B83: Default settings | C83: Rule C | D83: 2 | E83: $500 | F83: -10403.18 | G83: 10942.85 | H83: 1.0383 | I83: 255.65 | J83: 500 | K83: YES, after 104 trades | L83: =IF(G83=0,"",F83/G83) -> -0.95068287 | M83: =IF(OR(L79="",L79<=0,L83=""),"",L83/L79) | N83: =IF(I83=0,"",F83/I83) -> -40.693057 | O83: =IF(I83=0,"",G83/I83) -> 42.804029 | P83: BLOWN | Q83: BLOWN
A84: M5 | B84: Default settings | C84: Rule C | D84: 3 | E84: none | F84: -12395.05 | G84: 12712.43 | H84: 1.2321 | I84: 258.22 | J84: 3178.11 | K84: YES, after 86 trades | L84: =IF(G84=0,"",F84/G84) -> -0.97503388 | M84: =IF(OR(L79="",L79<=0,L84=""),"",L84/L79) | N84: =IF(I84=0,"",F84/I84) -> -48.001898 | O84: =IF(I84=0,"",G84/I84) -> 49.231005 | P84: BLOWN | Q84: 23492.44
A85: M5 | B85: Default settings | C85: Rule C | D85: 3 | E85: $500 | F85: -10317.57 | G85: 10618.2 | H85: 1.0308 | I85: 226.89 | J85: 500 | K85: YES, after 104 trades | L85: =IF(G85=0,"",F85/G85) -> -0.97168729 | M85: =IF(OR(L79="",L79<=0,L85=""),"",L85/L79) | N85: =IF(I85=0,"",F85/I85) -> -45.473886 | O85: =IF(I85=0,"",G85/I85) -> 46.798889 | P85: BLOWN | Q85: BLOWN
A86: M5 | B86: Default settings | C86: Rule C | D86: 4 | E86: none | F86: -11527.46 | G86: 11732.27 | H86: 1.1497 | I86: 293.11 | J86: 2346.45 | K86: YES, after 99 trades | L86: =IF(G86=0,"",F86/G86) -> -0.98254302 | M86: =IF(OR(L79="",L79<=0,L86=""),"",L86/L79) | N86: =IF(I86=0,"",F86/I86) -> -39.328102 | O86: =IF(I86=0,"",G86/I86) -> 40.02685 | P86: BLOWN | Q86: BLOWN
A87: M5 | B87: Default settings | C87: Rule C | D87: 4 | E87: $500 | F87: -10105.27 | G87: 10310.09 | H87: 1.0103 | I87: 224.14 | J87: 500 | K87: YES, after 116 trades | L87: =IF(G87=0,"",F87/G87) -> -0.98013402 | M87: =IF(OR(L79="",L79<=0,L87=""),"",L87/L79) | N87: =IF(I87=0,"",F87/I87) -> -45.084635 | O87: =IF(I87=0,"",G87/I87) -> 45.998438 | P87: BLOWN | Q87: BLOWN
A88: M5 | B88: Default settings | C88: Rule C | D88: 5 | E88: none | F88: -11056.16 | G88: 11194.51 | H88: 1.1042 | I88: 221.54 | J88: 1865.75 | K88: YES, after 101 trades | L88: =IF(G88=0,"",F88/G88) -> -0.98764126 | M88: =IF(OR(L79="",L79<=0,L88=""),"",L88/L79) | N88: =IF(I88=0,"",F88/I88) -> -49.905931 | O88: =IF(I88=0,"",G88/I88) -> 50.530423 | P88: BLOWN | Q88: BLOWN
A89: M5 | B89: Default settings | C89: Rule C | D89: 5 | E89: $500 | F89: -10020.18 | G89: 10158.54 | H89: 1.002 | I89: 209.76 | J89: 500 | K89: YES, after 117 trades | L89: =IF(G89=0,"",F89/G89) -> -0.98637993 | M89: =IF(OR(L79="",L79<=0,L89=""),"",L89/L79) | N89: =IF(I89=0,"",F89/I89) -> -47.769737 | O89: =IF(I89=0,"",G89/I89) -> 48.429348 | P89: BLOWN | Q89: BLOWN
A90: M5 | B90: Default settings | C90: Rule C split | D90: 1 | E90: none | F90: -14631.31 | G90: 16000 | H90: 1.4074 | I90: 930.95 | J90: 8000 | K90: YES, after 20 trades | L90: =IF(G90=0,"",F90/G90) -> -0.91445687 | M90: =IF(OR(L79="",L79<=0,L90=""),"",L90/L79) | N90: =IF(I90=0,"",F90/I90) -> -15.716537 | O90: =IF(I90=0,"",G90/I90) -> 17.186745 | P90: BLOWN | Q90: BLOWN
A91: M5 | B91: Default settings | C91: Rule C split | D91: 1 | E91: $500 | F91: -10408.55 | G91: 10594.19 | H91: 1.0401 | I91: 443.97 | J91: 500 | K91: YES, after 85 trades | L91: =IF(G91=0,"",F91/G91) -> -0.98247719 | M91: =IF(OR(L79="",L79<=0,L91=""),"",L91/L79) | N91: =IF(I91=0,"",F91/I91) -> -23.444264 | O91: =IF(I91=0,"",G91/I91) -> 23.862401 | P91: BLOWN | Q91: BLOWN
A92: M5 | B92: Default settings | C92: Rule C split | D92: 2 | E92: none | F92: -14168.59 | G92: 14878.06 | H92: 1.3892 | I92: 411.02 | J92: 4959.35 | K92: YES, after 86 trades | L92: =IF(G92=0,"",F92/G92) -> -0.95231435 | M92: =IF(OR(L79="",L79<=0,L92=""),"",L92/L79) | N92: =IF(I92=0,"",F92/I92) -> -34.471778 | O92: =IF(I92=0,"",G92/I92) -> 36.197898 | P92: BLOWN | Q92: BLOWN
A93: M5 | B93: Default settings | C93: Rule C split | D93: 2 | E93: $500 | F93: -10307.6 | G93: 10962.61 | H93: 1.0289 | I93: 277.56 | J93: 500 | K93: YES, after 98 trades | L93: =IF(G93=0,"",F93/G93) -> -0.94025054 | M93: =IF(OR(L79="",L79<=0,L93=""),"",L93/L79) | N93: =IF(I93=0,"",F93/I93) -> -37.136475 | O93: =IF(I93=0,"",G93/I93) -> 39.496361 | P93: BLOWN | Q93: BLOWN
A94: M5 | B94: Default settings | C94: Rule C split | D94: 3 | E94: none | F94: -11350.29 | G94: 11653.06 | H94: 1.1311 | I94: 257.54 | J94: 2913.27 | K94: YES, after 85 trades | L94: =IF(G94=0,"",F94/G94) -> -0.97401798 | M94: =IF(OR(L79="",L79<=0,L94=""),"",L94/L79) | N94: =IF(I94=0,"",F94/I94) -> -44.07195 | O94: =IF(I94=0,"",G94/I94) -> 45.247573 | P94: BLOWN | Q94: BLOWN
A95: M5 | B95: Default settings | C95: Rule C split | D95: 3 | E95: $500 | F95: -10393.06 | G95: 10662.18 | H95: 1.0383 | I95: 232.28 | J95: 500 | K95: YES, after 103 trades | L95: =IF(G95=0,"",F95/G95) -> -0.97475938 | M95: =IF(OR(L79="",L79<=0,L95=""),"",L95/L79) | N95: =IF(I95=0,"",F95/I95) -> -44.743671 | O95: =IF(I95=0,"",G95/I95) -> 45.902273 | P95: BLOWN | Q95: BLOWN
A96: M5 | B96: Default settings | C96: Rule C split | D96: 4 | E96: none | F96: -12289.8 | G96: 12494.62 | H96: 1.2244 | I96: 309.06 | J96: 2498.92 | K96: YES, after 99 trades | L96: =IF(G96=0,"",F96/G96) -> -0.98360734 | M96: =IF(OR(L79="",L79<=0,L96=""),"",L96/L79) | N96: =IF(I96=0,"",F96/I96) -> -39.765094 | O96: =IF(I96=0,"",G96/I96) -> 40.427813 | P96: BLOWN | Q96: BLOWN
A97: M5 | B97: Default settings | C97: Rule C split | D97: 4 | E97: $500 | F97: -10003.09 | G97: 10207.91 | H97: 1.0003 | I97: 219.14 | J97: 500 | K97: YES, after 113 trades | L97: =IF(G97=0,"",F97/G97) -> -0.97993517 | M97: =IF(OR(L79="",L79<=0,L97=""),"",L97/L79) | N97: =IF(I97=0,"",F97/I97) -> -45.647029 | O97: =IF(I97=0,"",G97/I97) -> 46.581683 | P97: BLOWN | Q97: BLOWN
A98: M5 | B98: Default settings | C98: Rule C split | D98: 5 | E98: none | F98: -11056.16 | G98: 11194.51 | H98: 1.1042 | I98: 221.54 | J98: 1865.75 | K98: YES, after 101 trades | L98: =IF(G98=0,"",F98/G98) -> -0.98764126 | M98: =IF(OR(L79="",L79<=0,L98=""),"",L98/L79) | N98: =IF(I98=0,"",F98/I98) -> -49.905931 | O98: =IF(I98=0,"",G98/I98) -> 50.530423 | P98: BLOWN | Q98: BLOWN
A99: M5 | B99: Default settings | C99: Rule C split | D99: 5 | E99: $500 | F99: -10020.18 | G99: 10158.54 | H99: 1.002 | I99: 209.76 | J99: 500 | K99: YES, after 117 trades | L99: =IF(G99=0,"",F99/G99) -> -0.98637993 | M99: =IF(OR(L79="",L79<=0,L99=""),"",L99/L79) | N99: =IF(I99=0,"",F99/I99) -> -47.769737 | O99: =IF(I99=0,"",G99/I99) -> 48.429348 | P99: BLOWN | Q99: BLOWN
A101: M5 | B101: Best settings (profit) | C101: Off (fixed $50) | D101: - | E101: - | F101: 6136.32 | G101: 1830.99 | H101: 0.1725 | I101: 50 | J101: 50 | K101: no | L101: =IF(G101=0,"",F101/G101) -> 3.3513673 | M101: 1 | N101: =IF(I101=0,"",F101/I101) -> 122.7264 | O101: =IF(I101=0,"",G101/I101) -> 36.6198 | P101: 3333.68 | Q101: 2802.64
A102: M5 | B102: Best settings (profit) | C102: Rule C | D102: 1 | E102: none | F102: -31650.2 | G102: 51200 | H102: 1.7327 | I102: 654.13 | J102: 25600 | K102: YES, after 120 trades | L102: =IF(G102=0,"",F102/G102) -> -0.61816797 | M102: =IF(OR(L101="",L101<=0,L102=""),"",L102/L101) -> -0.18445247 | N102: =IF(I102=0,"",F102/I102) -> -48.385183 | O102: =IF(I102=0,"",G102/I102) -> 78.271903 | P102: BLOWN | Q102: BLOWN
A103: M5 | B103: Best settings (profit) | C103: Rule C | D103: 1 | E103: $500 | F103: 27434.04 | G103: 16609.9 | H103: 0.9689 | I103: 351.59 | J103: 500 | K103: no | L103: =IF(G103=0,"",F103/G103) -> 1.651668 | M103: =IF(OR(L101="",L101<=0,L103=""),"",L103/L101) -> 0.49283407 | N103: =IF(I103=0,"",F103/I103) -> 78.028499 | O103: =IF(I103=0,"",G103/I103) -> 47.242242 | P103: 25158.22 | Q103: BLOWN
A104: M5 | B104: Best settings (profit) | C104: Rule C | D104: 2 | E104: none | F104: -10779.91 | G104: 12974.63 | H104: 1.064 | I104: 170.78 | J104: 4324.88 | K104: YES, after 123 trades | L104: =IF(G104=0,"",F104/G104) -> -0.83084527 | M104: =IF(OR(L101="",L101<=0,L104=""),"",L104/L101) -> -0.24791233 | N104: =IF(I104=0,"",F104/I104) -> -63.121618 | O104: =IF(I104=0,"",G104/I104) -> 75.972772 | P104: BLOWN | Q104: BLOWN
A105: M5 | B105: Best settings (profit) | C105: Rule C | D105: 2 | E105: $500 | F105: -10049.18 | G105: 12079.88 | H105: 1.0041 | I105: 251.36 | J105: 500 | K105: YES, after 199 trades | L105: =IF(G105=0,"",F105/G105) -> -0.83189403 | M105: =IF(OR(L101="",L101<=0,L105=""),"",L105/L101) -> -0.24822526 | N105: =IF(I105=0,"",F105/I105) -> -39.979233 | O105: =IF(I105=0,"",G105/I105) -> 48.058084 | P105: BLOWN | Q105: BLOWN
A106: M5 | B106: Best settings (profit) | C106: Rule C | D106: 3 | E106: none | F106: -10232.3 | G106: 11224.64 | H106: 1.0211 | I106: 137.82 | J106: 2806.16 | K106: YES, after 127 trades | L106: =IF(G106=0,"",F106/G106) -> -0.91159271 | M106: =IF(OR(L101="",L101<=0,L106=""),"",L106/L101) -> -0.27200621 | N106: =IF(I106=0,"",F106/I106) -> -74.243941 | O106: =IF(I106=0,"",G106/I106) -> 81.444203 | P106: BLOWN | Q106: 10876.95
...

Sheet Crooks A and B test
A1: Crooks A and Crooks B loss recovery (FxPro MT5 gold, 2021-2026, after spread)
A2: HOW THE RULES WORK
A3: Crooks A: trades 1 and 2 of a cycle risk the base ($50). From trade 3, every other trade (3, 5, 7 ...) is a RECOVERY trade and the trades between risk the base. Recovery risk = max(base, loss to win back / final target R): e.g. $250 to win back with TP4 (2R) as the final target -> $125; with TP2 (1R) -> $250; with TP1 (0.6R) -> $417. Losses add to the loss to win back, wins reduce it (never below 0). A winning recovery trade starts a new cycle (base, base, recovery ...), even if not everything is back; so does winning everything back.
A4: Crooks B: the same alternation, but recovery risk = max(base, loss to win back / split / final target R), with split = the Rule C split setting, and a new cycle starts only when the whole loss is won back (a recovery win that leaves some of the loss keeps alternating). Split 1 = Crooks A sizing with the Crooks B reset.
A5: Example, 5 losses in a row, base $50, final target TP2 (1R), Crooks A: risks $50, $50, $100, $50, $250. Same with TP4 (2R): $50, $50, $50, $50, $100. Hard cap: only when it is switched on; "Start again" = forget the loss to win back and trade 1 of a new cycle at the base risk.
A6: Test: $10,000 start, $50 base, every trade sized like the strategy and the EA (a stop-out loses the computed risk incl. spread), no leverage limit. The EA's own sizing code was run on these trades and gave the same risk on every trade (1.9 million trades compared, every rule except % of equity).
A8: HOW TO SET IT
A9: TradingView strategy, group LOSS RECOVERY (strategy only): Loss Recovery = "Crooks A (base, base, then recovery every 2nd trade)" or "Crooks B (Crooks A with the loss split over N trades)"; for Crooks B also "Split The Loss Over This Many Trades (Rule C, Crooks B)" = 2-5. Group RISK: tick "Hard Cap: Max Loss Per Trade ($)", 500, and "If The Risk Would Exceed The Cap" = "Start again from the base risk". The final target is "Exit At" (TP1-TP4).
A10: MT5 EA, group LOSS RECOVERY: Loss recovery (InpRec) = Crooks A / Crooks B; InpCSplit = the split (Crooks B). RISK: InpCapOn = true, InpHardCap = 500, InpCapAction = Start again from the base risk. The EA keeps the cycle in memory: after an EA restart it starts at trade 1 of a new cycle.
A11: Chart table row "CROOKS: LOSS TO WIN BACK": the $ still to win back, the number of the next (or open) trade in the cycle and whether it is a base or a recovery trade.
A12: TP1 rule (switch "Crooks At Exit TP1: Bank The Loss At TP1, Rest To TP2", EA InpCrkT1; on by default): only with Final Exit At = TP1, on the recovery trades. The position is doubled, half closes at TP1 and banks the whole recovery amount, the other half runs to TP2 with its stop moved to the entry; the stop sits where a stop-out loses exactly the recovery amount (TP1 / 2 - 1.5 x costs = 0.3R with TP1 0.6R and no costs). Tested in part 6: it loses on gold - untick it.
A14: WHAT IT SHOWS
... A28: PART 1 - quick answer: the best settings per timeframe with the main Crooks choices ($500 cap, Start again) vs Off
A29: Timeframe | B29: Strategy | C29: Final target R | D29: Rule | E29: Split | F29: Hard cap | G29: Backtest net ($) | H29: Backtest deepest fall % | I29: Average risk ($) | J29: Largest risk ($) | K29: Random orders: median net ($) | L29: Random orders: worst 5% net ($) | M29: Random orders: 95% fall less than | N29: Random orders: account blown | O29: Random orders: fall > 40%
A30: M1 | B30: M1-S1: Most profit + Longest winning streak + Highest win rate + Smoothest + London close session only | C30: 2 | D30: Off (fixed $50) | E30: - | F30: none | G30: 5441.57 | H30: 0.1332 | I30: 50 | J30: 50 | K30: 5441.57 | L30: 5441.57 | M30: 0.2511 | N30: 0 | O30: 0
A31: M1 | B31: M1-S1: Most profit + Longest winning streak + Highest win rate + Smoothest + London close session only | C31: 2 | D31: Crooks A | E31: - | F31: $500, Start again | G31: 15765.65 | H31: 0.1767 | I31: 64.6 | J31: 468.84 | K31: 7418.98 | L31: 1873.78 | M31: 0.551 | N31: 0 | O31: 0.18
A32: M1 | B32: M1-S1: Most profit + Longest winning streak + Highest win rate + Smoothest + London close session only | C32: 2 | D32: Crooks B | E32: 2 | F32: $500, Start again | G32: 9183.3 | H32: 0.1925 | I32: 61.91 | J32: 498.91 | K32: 7297.48 | L32: 2835.2 | M32: 0.4762 | N32: 0 | O32: 0.114
A33: M1 | B33: M1-S1: Most profit + Longest winning streak + Highest win rate + Smoothest + London close session only | C33: 2 | D33: Crooks B | E33: 3 | F33: $500, Start again | G33: 9377.98 | H33: 0.154 | I33: 59.42 | J33: 425.53 | K33: 6957.32 | L33: 3271.18 | M33: 0.4991 | N33: 0 | O33: 0.106
A34: M1 | B34: M1-S1: Most profit + Longest winning streak + Highest win rate + Smoothest + London close session only | C34: 2 | D34: Crooks B | E34: 5 | F34: $500, Start again | G34: 7307.85 | H34: 0.1555 | I34: 53.81 | J34: 184.97 | K34: 7039.35 | L34: 3156.75 | M34: 0.4759 | N34: 0 | O34: 0.108
A36: M1 | B36: M1-S2: Shortest losing streak + Shortest losing streak - indicator only | C36: 2 | D36: Off (fixed $50) | E36: - | F36: none | G36: 4561.27 | H36: 0.1443 | I36: 50 | J36: 50 | K36: 4561.27 | L36: 4561.27 | M36: 0.2657 | N36: 0 | O36: 0.002
A37: M1 | B37: M1-S2: Shortest losing streak + Shortest losing streak - indicator only | C37: 2 | D37: Crooks A | E37: - | F37: $500, Start again | G37: 965.26 | H37: 0.3664 | I37: 67.54 | J37: 497.49 | K37: 6059.56 | L37: 653.98 | M37: 0.5682 | N37: 0.002 | O37: 0.218
A38: M1 | B38: M1-S2: Shortest losing streak + Shortest losing streak - indicator only | C38: 2 | D38: Crooks B | E38: 2 | F38: $500, Start again | G38: 5848.78 | H38: 0.2922 | I38: 61.97 | J38: 497.15 | K38: 6267.12 | L38: 1397.39 | M38: 0.5104 | N38: 0 | O38: 0.162
A39: M1 | B39: M1-S2: Shortest losing streak + Shortest losing streak - indicator only | C39: 2 | D39: Crooks B | E39: 3 | F39: $500, Start again | G39: 6363.53 | H39: 0.2288 | I39: 59.58 | J39: 451.59 | K39: 5907.6 | L39: 1534.54 | M39: 0.514 | N39: 0.002 | O39: 0.142
A40: M1 | B40: M1-S2: Shortest losing streak + Shortest losing streak - indicator only | C40: 2 | D40: Crooks B | E40: 5 | F40: $500, Start again | G40: 6515.37 | H40: 0.1455 | I40: 54.14 | J40: 186.53 | K40: 6114.51 | L40: 2084.64 | M40: 0.499 | N40: 0 | O40: 0.142
A42: M5 | B42: M5-S1: Most profit + Smoothest + New York session only | C42: 2.5 | D42: Off (fixed $50) | E42: - | F42: none | G42: 6136.32 | H42: 0.1725 | I42: 50 | J42: 50 | K42: 6136.32 | L42: 6136.32 | M42: 0.2218 | N42: 0 | O42: 0
A43: M5 | B43: M5-S1: Most profit + Smoothest + New York session only | C43: 2.5 | D43: Crooks A | E43: - | F43: $500, Start again | G43: 9244.49 | H43: 0.3077 | I43: 65.3 | J43: 490.68 | K43: 8656.81 | L43: 2898.07 | M43: 0.4728 | N43: 0 | O43: 0.116
A44: M5 | B44: M5-S1: Most profit + Smoothest + New York session only | C44: 2.5 | D44: Crooks B | E44: 2 | F44: $500, Start again | G44: 9315.46 | H44: 0.2183 | I44: 62.54 | J44: 460.36 | K44: 7669.36 | L44: 3736.86 | M44: 0.4519 | N44: 0 | O44: 0.076
A45: M5 | B45: M5-S1: Most profit + Smoothest + New York session only | C45: 2.5 | D45: Crooks B | E45: 3 | F45: $500, Start again | G45: 5978.11 | H45: 0.247 | I45: 61.82 | J45: 498.93 | K45: 8336.63 | L45: 3682.85 | M45: 0.4224 | N45: 0 | O45: 0.074
A46: M5 | B46: M5-S1: Most profit + Smoothest + New York session only | C46: 2.5 | D46: Crooks B | E46: 5 | F46: $500, Start again | G46: 7510.13 | H46: 0.1915 | I46: 56.36 | J46: 167.94 | K46: 7106.57 | L46: 6037.84 | M46: 0.3654 | N46: 0 | O46: 0.038
A48: M5 | B48: M5-S2: Shortest losing streak + Shortest losing streak - indicator only + Longest winning streak + Highest win rate + Every year positive | C48: 2 | D48: Off (fixed $50) | E48: - | F48: none | G48: 3667.19 | H48: 0.0948 | I48: 50 | J48: 50 | K48: 3667.19 | L48: 3667.19 | M48: 0.2015 | N48: 0 | O48: 0
A49: M5 | B49: M5-S2: Shortest losing streak + Shortest losing streak - indicator only + Longest winning streak + Highest win rate + Every year positive | C49: 2 | D49: Crooks A | E49: - | F49: $500, Start again | G49: 2116.38 | H49: 0.1925 | I49: 56.91 | J49: 465.54 | K49: 4248.93 | L49: 1960.95 | M49: 0.3174 | N49: 0 | O49: 0.018
A50: M5 | B50: M5-S2: Shortest losing streak + Shortest losing streak - indicator only + Longest winning streak + Highest win rate + Every year positive | C50: 2 | D50: Crooks B | E50: 2 | F50: $500, Start again | G50: 7890.52 | H50: 0.1059 | I50: 61.83 | J50: 401.7 | K50: 4869 | L50: 1605 | M50: 0.3877 | N50: 0 | O50: 0.042
A51: M5 | B51: M5-S2: Shortest losing streak + Shortest losing streak - indicator only + Longest winning streak + Highest win rate + Every year positive | C51: 2 | D51: Crooks B | E51: 3 | F51: $500, Start again | G51: 6090.06 | H51: 0.0941 | I51: 56.57 | J51: 223.27 | K51: 5166.79 | L51: 1174.4 | M51: 0.3987 | N51: 0 | O51: 0.048
A52: M5 | B52: M5-S2: Shortest losing streak + Shortest losing streak - indicator only + Longest winning streak + Highest win rate + Every year positive | C52: 2 | D52: Crooks B | E52: 5 | F52: $500, Start again | G52: 4334.53 | H52: 0.0907 | I52: 52.36 | J52: 123.4 | K52: 4398.77 | L52: 1188.69 | M52: 0.4089 | N52: 0 | O52: 0.052
A54: M15 | B54: M15-S1: Most profit | C54: 2 | D54: Off (fixed $50) | E54: - | F54: none | G54: 9076.9 | H54: 0.0876 | I54: 50 | J54: 50 | K54: 9076.9 | L54: 9076.9 | M54: 0.1261 | N54: 0 | O54: 0
A55: M15 | B55: M15-S1: Most profit | C55: 2 | D55: Crooks A | E55: - | F55: $500, Start again | G55: 12348.06 | H55: 0.1619 | I55: 60.42 | J55: 476.08 | K55: 11014.92 | L55: 7678.42 | M55: 0.2446 | N55: 0 | O55: 0.002
A56: M15 | B56: M15-S1: Most profit | C56: 2 | D56: Crooks B | E56: 2 | F56: $500, Start again | G56: 10778.3 | H56: 0.1625 | I56: 55.04 | J56: 402.67 | K56: 10716.65 | L56: 8229.78 | M56: 0.2448 | N56: 0 | O56: 0
A57: M15 | B57: M15-S1: Most profit | C57: 2 | D57: Crooks B | E57: 3 | F57: $500, Start again | G57: 10459.36 | H57: 0.1623 | I57: 54.07 | J57: 339.46 | K57: 10269.51 | L57: 7943.63 | M57: 0.2387 | N57: 0 | O57: 0
A58: M15 | B58: M15-S1: Most profit | C58: 2 | D58: Crooks B | E58: 5 | F58: $500, Start again | G58: 9302.47 | H58: 0.1115 | I58: 50.99 | J58: 132.9 | K58: 9416.96 | L58: 9141.46 | M58: 0.179 | N58: 0 | O58: 0
A60: M15 | B60: M15-S3: Shortest losing streak - indicator only + Smoothest | C60: 2 | D60: Off (fixed $50) | E60: - | F60: none | G60: 7274.17 | H60: 0.0514 | I60: 50 | J60: 50 | K60: 7274.17 | L60: 7274.17 | M60: 0.122 | N60: 0 | O60: 0
A61: M15 | B61: M15-S3: Shortest losing streak - indicator only + Smoothest | C61: 2 | D61: Crooks A | E61: - | F61: $500, Start again | G61: 11592.75 | H61: 0.0624 | I61: 57.58 | J61: 390.3 | K61: 8666.94 | L61: 5962.29 | M61: 0.2482 | N61: 0 | O61: 0
A62: M15 | B62: M15-S3: Shortest losing streak - indicator only + Smoothest | C62: 2 | D62: Crooks B | E62: 2 | F62: $500, Start again | G62: 9047.27 | H62: 0.0708 | I62: 53.67 | J62: 227.58 | K62: 9013.25 | L62: 6529.39 | M62: 0.2479 | N62: 0 | O62: 0
A63: M15 | B63: M15-S3: Shortest losing streak - indicator only + Smoothest | C63: 2 | D63: Crooks B | E63: 3 | F63: $500, Start again | G63: 7807.62 | H63: 0.0561 | I63: 51.37 | J63: 135.05 | K63: 8249.75 | L63: 5991.27 | M63: 0.2565 | N63: 0 | O63: 0
A64: M15 | B64: M15-S3: Shortest losing streak - indicator only + Smoothest | C64: 2 | D64: Crooks B | E64: 5 | F64: $500, Start again | G64: 7351.26 | H64: 0.0508 | I64: 50.12 | J64: 71.13 | K64: 7545.54 | L64: 7302.61 | M64: 0.1613 | N64: 0 | O64: 0
A66: H1 | B66: H1-S1: Most profit + Every year positive | C66: 2 | D66: Off (fixed $50) | E66: - | F66: none | G66: 3087.46 | H66: 0.0344 | I66: 50 | J66: 50 | K66: 3087.46 | L66: 3087.46 | M66: 0.0679 | N66: 0 | O66: 0
A67: H1 | B67: H1-S1: Most profit + Every year positive | C67: 2 | D67: Crooks A | E67: - | F67: $500, Start again | G67: 4250.81 | H67: 0.0515 | I67: 56.47 | J67: 287.5 | K67: 3874.75 | L67: 2441.08 | M67: 0.1467 | N67: 0 | O67: 0
A68: H1 | B68: H1-S1: Most profit + Every year positive | C68: 2 | D68: Crooks B | E68: 2 | F68: $500, Start again | G68: 3322.28 | H68: 0.0368 | I68: 51.11 | J68: 106.25 | K68: 3282.72 | L68: 3094.46 | M68: 0.111 | N68: 0 | O68: 0
A69: H1 | B69: H1-S1: Most profit + Every year positive | C69: 2 | D69: Crooks B | E69: 3 | F69: $500, Start again | G69: 3142.17 | H69: 0.0344 | I69: 50.15 | J69: 66.67 | K69: 3134.61 | L69: 3082.57 | M69: 0.0839 | N69: 0 | O69: 0
A70: H1 | B70: H1-S1: Most profit + Every year positive | C70: 2 | D70: Crooks B | E70: 5 | F70: $500, Start again | G70: 3087.46 | H70: 0.0344 | I70: 50 | J70: 50 | K70: 3087.46 | L70: 3086.76 | M70: 0.0702 | N70: 0 | O70: 0
A72: H1 | B72: H1-S3: Shortest losing streak - indicator only | C72: 2 | D72: Off (fixed $50) | E72: - | F72: none | G72: 2619.59 | H72: 0.0368 | I72: 50 | J72: 50 | K72: 2619.59 | L72: 2619.59 | M72: 0.0809 | N72: 0 | O72: 0
A73: H1 | B73: H1-S3: Shortest losing streak - indicator only | C73: 2 | D73: Crooks A | E73: - | F73: $500, Start again | G73: 4023.56 | H73: 0.0491 | I73: 56.89 | J73: 220.04 | K73: 3218.81 | L73: 1736.18 | M73: 0.1746 | N73: 0 | O73: 0
A74: H1 | B74: H1-S3: Shortest losing streak - indicator only | C74: 2 | D74: Crooks B | E74: 2 | F74: $500, Start again | G74: 2729.56 | H74: 0.0383 | I74: 50.74 | J74: 93.06 | K74: 2981.2 | L74: 2169.85 | M74: 0.1702 | N74: 0 | O74: 0
A75: H1 | B75: H1-S3: Shortest losing streak - indicator only | C75: 2 | D75: Crooks B | E75: 3 | F75: $500, Start again | G75: 2641.85 | H75: 0.037 | I75: 50.06 | J75: 62.41 | K75: 2742.12 | L75: 2613.99 | M75: 0.1072 | N75: 0 | O75: 0
A76: H1 | B76: H1-S3: Shortest losing streak - indicator only | C76: 2 | D76: Crooks B | E76: 5 | F76: $500, Start again | G76: 2619.59 | H76: 0.0368 | I76: 50 | J76: 50 | K76: 2624.54 | L76: 2614.82 | M76: 0.0845 | N76: 0 | O76: 0
A79: PART 2 - backtest: every strategy x Crooks A / Crooks B split 1-5 x hard cap (none / $500 Clamp / $500 Start again / $500 Stop trading); each half from a fresh $10,000
A80: Timeframe | B80: Strategy | C80: Final target R | D80: Rule | E80: Split | F80: Hard cap | G80: Net profit ($) | H80: Max drawdown ($) | I80: Max drawdown % | J80: Average risk ($) | K80: Largest risk ($) | L80: Worst run of losses ($) | M80: Account | N80: Profit / max drawdown | O80: vs Off (1 = same) | P80: 2021-23 net ($) | Q80: 2021-23 max drawdown % | R80: 2024-26 net ($) | S80: 2024-26 max drawdown % | T80: Eligible (whole run kept trading to the end, whole run and both halves profitable, risk <= $500, falls <= 40%)
A81: M1 | B81: Default settings | C81: 2 | D81: Off (fixed $50) | E81: - | F81: none | G81: -10035.04 | H81: 10184.86 | I81: 1.0035 | J81: 50 | K81: 50 | L81: 800 | M81: BLOWN after 483 trades | N81: =IF(H81=0,"",G81/H81) -> -0.98528993 | O81: 1 | P81: BLOWN | Q81: 1.0035 | R81: BLOWN | S81: 1.0036 | T81: =IF(AND(M81="survived",G81>0,K81<=500.005,I81<=0.4,ISNUMBER(P81),ISNUMBER(R81),P81>0,R81>0,Q81<=0.4,S81<=0.4),"yes","no") -> no
A82: M1 | B82: Default settings | C82: 2 | D82: Rule C split | E82: 3 | F82: $500, Start again | G82: -10158.99 | H82: 10308.82 | I82: 1.0157 | J82: 125.73 | K82: 499.87 | L82: 1843.61 | M82: BLOWN after 289 trades | N82: =IF(H82=0,"",G82/H82) -> -0.98546584 | O82: =IF(OR(N81="",N81<=0,N82=""),"",N82/N81) | P82: BLOWN | Q82: 1.0157 | R82: BLOWN | S82: 1.0107 | T82: =IF(AND(M82="survived",G82>0,K82<=500.005,I82<=0.4,ISNUMBER(P82),ISNUMBER(R82),P82>0,R82>0,Q82<=0.4,S82<=0.4),"yes","no") -> no
A83: M1 | B83: Default settings | C83: 2 | D83: Crooks A | E83: - | F83: none | G83: -11538.93 | H83: 11688.75 | I83: 1.1516 | J83: 129.54 | K83: 3396.32 | L83: 9381.28 | M83: BLOWN after 170 trades | N83: =IF(H83=0,"",G83/H83) -> -0.98718255 | O83: =IF(OR(N81="",N81<=0,N83=""),"",N83/N81) | P83: BLOWN | Q83: 1.1516 | R83: BLOWN | S83: 1.082 | T83: =IF(AND(M83="survived",G83>0,K83<=500.005,I83<=0.4,ISNUMBER(P83),ISNUMBER(R83),P83>0,R83>0,Q83<=0.4,S83<=0.4),"yes","no") -> no
A84: M1 | B84: Default settings | C84: 2 | D84: Crooks A | E84: - | F84: $500, Clamp | G84: -10155.95 | H84: 10305.77 | I84: 1.0154 | J84: 92.43 | K84: 500 | L84: 3153.84 | M84: BLOWN after 289 trades | N84: =IF(H84=0,"",G84/H84) -> -0.98546251 | O84: =IF(OR(N81="",N81<=0,N84=""),"",N84/N81) | P84: BLOWN | Q84: 1.0154 | R84: BLOWN | S84: 1.0139 | T84: =IF(AND(M84="survived",G84>0,K84<=500.005,I84<=0.4,ISNUMBER(P84),ISNUMBER(R84),P84>0,R84>0,Q84<=0.4,S84<=0.4),"yes","no") -> no
A85: M1 | B85: Default settings | C85: 2 | D85: Crooks A | E85: - | F85: $500, Start again | G85: -10393.05 | H85: 10542.88 | I85: 1.0387 | J85: 76.78 | K85: 456.25 | L85: 1725.72 | M85: BLOWN after 339 trades | N85: =IF(H85=0,"",G85/H85) -> -0.98578851 | O85: =IF(OR(N81="",N81<=0,N85=""),"",N85/N81) | P85: BLOWN | Q85: 1.0387 | R85: BLOWN | S85: 1.0192 | T85: =IF(AND(M85="survived",G85>0,K85<=500.005,I85<=0.4,ISNUMBER(P85),ISNUMBER(R85),P85>0,R85>0,Q85<=0.4,S85<=0.4),"yes","no") -> no
A86: M1 | B86: Default settings | C86: 2 | D86: Crooks A | E86: - | F86: $500, Stop trading | G86: -1546.07 | H86: 1727.9 | I86: 0.1702 | J86: 81.52 | K86: 456.25 | L86: 912.5 | M86: stopped by the cap | N86: =IF(H86=0,"",G86/H86) -> -0.89476822 | O86: =IF(OR(N81="",N81<=0,N86=""),"",N86/N81) | P86: -1546.07 | Q86: 0.1702 | R86: -920.92 | S86: 0.1422 | T86: =IF(AND(M86="survived",G86>0,K86<=500.005,I86<=0.4,ISNUMBER(P86),ISNUMBER(R86),P86>0,R86>0,Q86<=0.4,S86<=0.4),"yes","no") -> no
A87: M1 | B87: Default settings | C87: 2 | D87: Crooks B | E87: 1 | F87: none | G87: -12941.3 | H87: 13091.12 | I87: 1.2898 | J87: 713.38 | K87: 4929.2 | L87: 9317.83 | M87: BLOWN after 51 trades | N87: =IF(H87=0,"",G87/H87) -> -0.9885556 | O87: =IF(OR(N81="",N81<=0,N87=""),"",N87/N81) | P87: BLOWN | Q87: 1.2898 | R87: BLOWN | S87: 1.1768 | T87: =IF(AND(M87="survived",G87>0,K87<=500.005,I87<=0.4,ISNUMBER(P87),ISNUMBER(R87),P87>0,R87>0,Q87<=0.4,S87<=0.4),"yes","no") -> no
A88: M1 | B88: Default settings | C88: 2 | D88: Crooks B | E88: 1 | F88: $500, Clamp | G88: -10305.89 | H88: 10455.71 | I88: 1.0301 | J88: 251.43 | K88: 500 | L88: 2800 | M88: BLOWN after 175 trades | N88: =IF(H88=0,"",G88/H88) -> -0.98567099 | O88: =IF(OR(N81="",N81<=0,N88=""),"",N88/N81) | P88: BLOWN | Q88: 1.0301 | R88: BLOWN | S88: 1.0321 | T88: =IF(AND(M88="survived",G88>0,K88<=500.005,I88<=0.4,ISNUMBER(P88),ISNUMBER(R88),P88>0,R88>0,Q88<=0.4,S88<=0.4),"yes","no") -> no
A89: M1 | B89: Default settings | C89: 2 | D89: Crooks B | E89: 1 | F89: $500, Start again | G89: -10096.04 | H89: 10245.87 | I89: 1.0095 | J89: 90.88 | K89: 484.82 | L89: 1349.14 | M89: BLOWN after 253 trades | N89: =IF(H89=0,"",G89/H89) -> -0.98537655 | O89: =IF(OR(N81="",N81<=0,N89=""),"",N89/N81) | P89: BLOWN | Q89: 1.0095 | R89: BLOWN | S89: 1.0226 | T89: =IF(AND(M89="survived",G89>0,K89<=500.005,I89<=0.4,ISNUMBER(P89),ISNUMBER(R89),P89>0,R89>0,Q89<=0.4,S89<=0.4),"yes","no") -> no
A90: M1 | B90: Default settings | C90: 2 | D90: Crooks B | E90: 1 | F90: $500, Stop trading | G90: -1046.64 | H90: 1196.46 | I90: 0.1179 | J90: 85.32 | K90: 382.15 | L90: 720.26 | M90: stopped by the cap | N90: =IF(H90=0,"",G90/H90) -> -0.8747806 | O90: =IF(OR(N81="",N81<=0,N90=""),"",N90/N81) | P90: -1046.64 | Q90: 0.1179 | R90: -760.96 | S90: 0.1354 | T90: =IF(AND(M90="survived",G90>0,K90<=500.005,I90<=0.4,ISNUMBER(P90),ISNUMBER(R90),P90>0,R90>0,Q90<=0.4,S90<=0.4),"yes","no") -> no
A91: M1 | B91: Default settings | C91: 2 | D91: Crooks B | E91: 2 | F91: none | G91: -12424.56 | H91: 12574.39 | I91: 1.2389 | J91: 276.35 | K91: 2514.88 | L91: 3520 | M91: BLOWN after 193 trades | N91: =IF(H91=0,"",G91/H91) -> -0.98808451 | O91: =IF(OR(N81="",N81<=0,N91=""),"",N91/N81) | P91: BLOWN | Q91: 1.2389 | R91: BLOWN | S91: 1.0133 | T91: =IF(AND(M91="survived",G91>0,K91<=500.005,I91<=0.4,ISNUMBER(P91),ISNUMBER(R91),P91>0,R91>0,Q91<=0.4,S91<=0.4),"yes","no") -> no
A92: M1 | B92: Default settings | C92: 2 | D92: Crooks B | E92: 2 | F92: $500, Clamp | G92: -10055.32 | H92: 10205.15 | I92: 1.0055 | J92: 238.13 | K92: 500 | L92: 2800 | M92: BLOWN after 191 trades | N92: =IF(H92=0,"",G92/H92) -> -0.9853182 | O92: =IF(OR(N81="",N81<=0,N92=""),"",N92/N81) | P92: BLOWN | Q92: 1.0055 | R92: BLOWN | S92: 1.0068 | T92: =IF(AND(M92="survived",G92>0,K92<=500.005,I92<=0.4,ISNUMBER(P92),ISNUMBER(R92),P92>0,R92>0,Q92<=0.4,S92<=0.4),"yes","no") -> no
A93: M1 | B93: Default settings | C93: 2 | D93: Crooks B | E93: 2 | F93: $500, Start again | G93: -10088.76 | H93: 10238.58 | I93: 1.0087 | J93: 96.02 | K93: 488.42 | L93: 1639.89 | M93: BLOWN after 272 trades | N93: =IF(H93=0,"",G93/H93) -> -0.98536711 | O93: =IF(OR(N81="",N81<=0,N93=""),"",N93/N81) | P93: BLOWN | Q93: 1.0087 | R93: BLOWN | S93: 1.036 | T93: =IF(AND(M93="survived",G93>0,K93<=500.005,I93<=0.4,ISNUMBER(P93),ISNUMBER(R93),P93>0,R93>0,Q93<=0.4,S93<=0.4),"yes","no") -> no
A94: M1 | B94: Default settings | C94: 2 | D94: Crooks B | E94: 2 | F94: $500, Stop trading | G94: -2089.33 | H94: 2239.15 | I94: 0.2206 | J94: 87.73 | K94: 437.83 | L94: 1639.89 | M94: stopped by the cap | N94: =IF(H94=0,"",G94/H94) -> -0.93309068 | O94: =IF(OR(N81="",N81<=0,N94=""),"",N94/N81) | P94: -2089.33 | Q94: 0.2206 | R94: -1533.4 | S94: 0.2004 | T94: =IF(AND(M94="survived",G94>0,K94<=500.005,I94<=0.4,ISNUMBER(P94),ISNUMBER(R94),P94>0,R94>0,Q94<=0.4,S94<=0.4),"yes","no") -> no
A95: M1 | B95: Default settings | C95: 2 | D95: Crooks B | E95: 3 | F95: none | G95: -10148.03 | H95: 10297.85 | I95: 1.0146 | J95: 194.92 | K95: 1471.12 | L95: 2538.67 | M95: BLOWN after 193 trades | N95: =IF(H95=0,"",G95/H95) -> -0.98545133 | O95: =IF(OR(N81="",N81<=0,N95=""),"",N95/N81) | P95: BLOWN | Q95: 1.0146 | R95: BLOWN | S95: 1.1374 | T95: =IF(AND(M95="survived",G95>0,K95<=500.005,I95<=0.4,ISNUMBER(P95),ISNUMBER(R95),P95>0,R95>0,Q95<=0.4,S95<=0.4),"yes","no") -> no
A96: M1 | B96: Default settings | C96: 2 | D96: Crooks B | E96: 3 | F96: $500, Clamp | G96: -10127.2 | H96: 10277.03 | I96: 1.0125 | J96: 179.92 | K96: 500 | L96: 2380 | M96: BLOWN after 231 trades | N96: =IF(H96=0,"",G96/H96) -> -0.98542089 | O96: =IF(OR(N81="",N81<=0,N96=""),"",N96/N81) | P96: BLOWN | Q96: 1.0125 | R96: BLOWN | S96: 1.009 | T96: =IF(AND(M96="survived",G96>0,K96<=500.005,I96<=0.4,ISNUMBER(P96),ISNUMBER(R96),P96>0,R96>0,Q96<=0.4,S96<=0.4),"yes","no") -> no
A97: M1 | B97: Default settings | C97: 2 | D97: Crooks B | E97: 3 | F97: $500, Start again | G97: -10019.65 | H97: 10169.48 | I97: 1.0019 | J97: 85.39 | K97: 462.87 | L97: 1702.24 | M97: BLOWN after 292 trades | N97: =IF(H97=0,"",G97/H97) -> -0.9852667 | O97: =IF(OR(N81="",N81<=0,N97=""),"",N97/N81) | P97: BLOWN | Q97: 1.0019 | R97: BLOWN | S97: 1.0221 | T97: =IF(AND(M97="survived",G97>0,K97<=500.005,I97<=0.4,ISNUMBER(P97),ISNUMBER(R97),P97>0,R97>0,Q97<=0.4,S97<=0.4),"yes","no") -> no
A98: M1 | B98: Default settings | C98: 2 | D98: Crooks B | E98: 3 | F98: $500, Stop trading | G98: -2932.95 | H98: 3082.77 | I98: 0.3037 | J98: 109.29 | K98: 433.25 | L98: 1032 | M98: stopped by the cap | N98: =IF(H98=0,"",G98/H98) -> -0.95140085 | O98: =IF(OR(N81="",N81<=0,N98=""),"",N98/N81) | P98: -2932.95 | Q98: 0.3037 | R98: -2536.61 | S98: 0.2872 | T98: =IF(AND(M98="survived",G98>0,K98<=500.005,I98<=0.4,ISNUMBER(P98),ISNUMBER(R98),P98>0,R98>0,Q98<=0.4,S98<=0.4),"yes","no") -> no
A99: M1 | B99: Default settings | C99: 2 | D99: Crooks B | E99: 4 | F99: none | G99: -10717.83 | H99: 10867.66 | I99: 1.0707 | J99: 183.89 | K99: 1229.76 | L99: 2065.71 | M99: BLOWN after 211 trades | N99: =IF(H99=0,"",G99/H99) -> -0.98621322 | O99: =IF(OR(N81="",N81<=0,N99=""),"",N99/N81) | P99: BLOWN | Q99: 1.0707 | R99: BLOWN | S99: 1.0912 | T99: =IF(AND(M99="survived",G99>0,K99<=500.005,I99<=0.4,ISNUMBER(P99),ISNUMBER(R99),P99>0,R99>0,Q99<=0.4,S99<=0.4),"yes","no") -> no
A100: M1 | B100: Default settings | C100: 2 | D100: Crooks B | E100: 4 | F100: $500, Clamp | G100: -10134.21 | H100: 10284.03 | I100: 1.0132 | J100: 159.88 | K100: 500 | L100: 2065.71 | M100: BLOWN after 231 trades | N100: =IF(H100=0,"",G100/H100) -> -0.98543178 | O100: =IF(OR(N81="",N81<=0,N100=""),"",N100/N81) | P100: BLOWN | Q100: 1.0132 | R100: BLOWN | S100: 1.0188 | T100: =IF(AND(M100="survived",G100>0,K100<=500.005,I100<=0.4,ISNUMBER(P100),ISNUMBER(R100),P100>0,R100>0,Q100<=0.4,S100<=0.4),"yes","no") -> no
A101: M1 | B101: Default settings | C101: 2 | D101: Crooks B | E101: 4 | F101: $500, Start again | G101: -10124.99 | H101: 10274.81 | I101: 1.0123 | J101: 104.78 | K101: 453.22 | L101: 2065.71 | M101: BLOWN after 334 trades | N101: =IF(H101=0,"",G101/H101) -> -0.98541871 | O101: =IF(OR(N81="",N81<=0,N101=""),"",N101/N81) | P101: BLOWN | Q101: 1.0123 | R101: BLOWN | S101: 1.0044 | T101: =IF(AND(M101="survived",G101>0,K101<=500.005,I101<=0.4,ISNUMBER(P101),ISNUMBER(R101),P101>0,R101>0,Q101<=0.4,S101<=0.4),"yes","no") -> no
A102: M1 | B102: Default settings | C102: 2 | D102: Crooks B | E102: 4 | F102: $500, Stop trading | G102: -3979.14 | H102: 4128.97 | I102: 0.4068 | J102: 117.25 | K102: 453.22 | L102: 2065.71 | M102: stopped by the cap | N102: =IF(H102=0,"",G102/H102) -> -0.9637125 | O102: =IF(OR(N81="",N81<=0,N102=""),"",N102/N81) | P102: -3979.14 | Q102: 0.4068 | R102: -3813.43 | S102: 0.4091 | T102: =IF(AND(M102="survived",G102>0,K102<=500.005,I102<=0.4,ISNUMBER(P102),ISNUMBER(R102),P102>0,R102>0,Q102<=0.4,S102<=0.4),"yes","no") -> no
A103: M1 | B103: Default settings | C103: 2 | D103: Crooks B | E103: 5 | F103: none | G103: -10341.68 | H103: 10491.51 | I103: 1.0337 | J103: 156.79 | K103: 981.54 | L103: 1730 | M103: BLOWN after 219 trades | N103: =IF(H103=0,"",G103/H103) -> -0.98571893 | O103: =IF(OR(N81="",N81<=0,N103=""),"",N103/N81) | P103: BLOWN | Q103: 1.0337 | R103: BLOWN | S103: 1.0447 | T103: =IF(AND(M103="survived",G103>0,K103<=500.005,I103<=0.4,ISNUMBER(P103),ISNUMBER(R103),P103>0,R103>0,Q103<=0.4,S103<=0.4),"yes","no") -> no
A104: M1 | B104: Default settings | C104: 2 | D104: Crooks B | E104: 5 | F104: $500, Clamp | G104: -10211.57 | H104: 10361.39 | I104: 1.0208 | J104: 146.34 | K104: 500 | L104: 1730 | M104: BLOWN after 233 trades | N104: =IF(H104=0,"",G104/H104) -> -0.98554055 | O104: =IF(OR(N81="",N81<=0,N104=""),"",N104/N81) | P104: BLOWN | Q104: 1.0208 | R104: BLOWN | S104: 1.0339 | T104: =IF(AND(M104="survived",G104>0,K104<=500.005,I104<=0.4,ISNUMBER(P104),ISNUMBER(R104),P104>0,R104>0,Q104<=0.4,S104<=0.4),"yes","no") -> no
A105: M1 | B105: Default settings | C105: 2 | D105: Crooks B | E105: 5 | F105: $500, Start again | G105: -10182.04 | H105: 10331.86 | I105: 1.0179 | J105: 99.6 | K105: 476.08 | L105: 2440.39 | M105: BLOWN after 295 trades | N105: =IF(H105=0,"",G105/H105) -> -0.98549922 | O105: =IF(OR(N81="",N81<=0,N105=""),"",N105/N81) | P105: BLOWN | Q105: 1.0179 | R105: BLOWN | S105: 1.0407 | T105: =IF(AND(M105="survived",G105>0,K105<=500.005,I105<=0.4,ISNUMBER(P105),ISNUMBER(R105),P105>0,R105>0,Q105<=0.4,S105<=0.4),"yes","no") -> no
A106: M1 | B106: Default settings | C106: 2 | D106: Crooks B | E106: 5 | F106: $500, Stop trading | G106: -5013.92 | H106: 5236.88 | I106: 0.516 | J106: 105.32 | K106: 476.08 | L106: 1730 | M106: stopped by the cap | N106: =IF(H106=0,"",G106/H106) -> -0.95742503 | O106: =IF(OR(N81="",N81<=0,N106=""),"",N106/N81) | P106: -5013.92 | Q106: 0.516 | R106: -5020.19 | S106: 0.5244 | T106: =IF(AND(M106="survived",G106>0,K106<=500.005,I106<=0.4,ISNUMBER(P106),ISNUMBER(R106),P106>0,R106>0,Q106<=0.4,S106<=0.4),"yes","no") -> no
A108: M1 | B108: M1-S1: Most profit (+4 more goals) | C108: 2 | D108: Off (fixed $50) | E108: - | F108: none | G108: 5441.57 | H108: 1480.81 | I108: 0.1332 | J108: 50 | K108: 50 | L108: 700 | M108: survived | N108: =IF(H108=0,"",G108/H108) -> 3.6747253 | O108: 1 | P108: 2544.19 | Q108: 0.1332 | R108: 2897.39 | S108: 0.1215 | T108: =IF(AND(M108="survived",G108>0,K108<=500.005,I108<=0.4,ISNUMBER(P108),ISNUMBER(R108),P108>0,R108>0,Q108<=0.4,S108<=0.4),"yes","no") -> yes
A109: M1 | B109: M1-S1: Most profit (+4 more goals) | C109: 2 | D109: Rule C split | E109: 3 | F109: $500, Start again | G109: 17859.4 | H109: 10922.96 | I109: 0.4614 | J109: 187.57 | K109: 499.44 | L109: 5580.63 | M109: survived | N109: =IF(H109=0,"",G109/H109) -> 1.635033 | O109: =IF(OR(N108="",N108<=0,N109=""),"",N109/N108) -> 0.44494019 | P109: 1584.02 | Q109: 0.3067 | R109: 83.07 | S109: 0.5564 | T109: =IF(AND(M109="survived",G109>0,K109<=500.005,I109<=0.4,ISNUMBER(P109),ISNUMBER(R109),P109>0,R109>0,Q109<=0.4,S109<=0.4),"yes","no") -> no
A110: M1 | B110: M1-S1: Most profit (+4 more goals) | C110: 2 | D110: Crooks A | E110: - | F110: none | G110: 22796.93 | H110: 11834.35 | I110: 0.7327 | J110: 83.59 | K110: 5873.01 | L110: 9567.07 | M110: survived | N110: =IF(H110=0,"",G110/H110) -> 1.9263356 | O110: =IF(OR(N108="",N108<=0,N110=""),"",N110/N108) -> 0.52421214 | P110: 9914.31 | Q110: 0.7327 | R110: 12882.62 | S110: 0.4488 | T110: =IF(AND(M110="survived",G110>0,K110<=500.005,I110<=0.4,ISNUMBER(P110),ISNUMBER(R110),P110>0,R110>0,Q110<=0.4,S110<=0.4),"yes","no") -> no
A111: M1 | B111: M1-S1: Most profit (+4 more goals) | C111: 2 | D111: Crooks A | E111: - | F111: $500, Clamp | G111: 13448.03 | H111: 4076.58 | I111: 0.3542 | J111: 69.7 | K111: 500 | L111: 2304.2 | M111: survived | N111: =IF(H111=0,"",G111/H111) -> 3.298851 | O111: =IF(OR(N108="",N108<=0,N111=""),"",N111/N108) -> 0.89771363 | P111: 4215.13 | Q111: 0.3542 | R111: 9232.9 | S111: 0.2115 | T111: =IF(AND(M111="survived",G111>0,K111<=500.005,I111<=0.4,ISNUMBER(P111),ISNUMBER(R111),P111>0,R111>0,Q111<=0.4,S111<=0.4),"yes","no") -> yes
A112: M1 | B112: M1-S1: Most profit (+4 more goals) | C112: 2 | D112: Crooks A | E112: - | F112: $500, Start again | G112: 15765.65 | H112: 1990.86 | I112: 0.1767 | J112: 64.6 | K112: 468.84 | L112: 1518.75 | M112: survived | N112: =IF(H112=0,"",G112/H112) -> 7.9190149 | O112: =IF(OR(N108="",N108<=0,N112=""),"",N112/N108) -> 2.1549951 | P112: 6768.7 | Q112: 0.1767 | R112: 8996.94 | S112: 0.1154 | T112: =IF(AND(M112="survived",G112>0,K112<=500.005,I112<=0.4,ISNUMBER(P112),ISNUMBER(R112),P112>0,R112>0,Q112<=0.4,S112<=0.4),"yes","no") -> yes
A113: M1 | B113: M1-S1: Most profit (+4 more goals) | C113: 2 | D113: Crooks A | E113: - | F113: $500, Stop trading | G113: 188.52 | H113: 1077.55 | I113: 0.0956 | J113: 65.11 | K113: 342.52 | L113: 654.2 | M113: stopped by the cap | N113: =IF(H113=0,"",G113/H113) -> 0.17495244 | O113: =IF(OR(N108="",N108<=0,N113=""),"",N113/N108) -> 0.047609664 | P113: 188.52 | Q113: 0.0956 | R113: 5135.74 | S113: 0.0878 | T113: =IF(AND(M113="survived",G113>0,K113<=500.005,I113<=0.4,ISNUMBER(P113),ISNUMBER(R113),P113>0,R113>0,Q113<=0.4,S113<=0.4),"yes","no") -> no
A114: M1 | B114: M1-S1: Most profit (+4 more goals) | C114: 2 | D114: Crooks B | E114: 1 | F114: none | G114: 25674.3 | H114: 11834.35 | I114: 0.6929 | J114: 90.9 | K114: 5873.01 | L114: 9567.07 | M114: survived | N114: =IF(H114=0,"",G114/H114) -> 2.1694728 | O114: =IF(OR(N108="",N108<=0,N114=""),"",N114/N108) -> 0.59037685 | P114: 11725.35 | Q114: 0.6929 | R114: 13948.95 | S114: 0.442 | T114: =IF(AND(M114="survived",G114>0,K114<=500.005,I114<=0.4,ISNUMBER(P114),ISNUMBER(R114),P114>0,R114>0,Q114<=0.4,S114<=0.4),"yes","no") -> no
A115: M1 | B115: M1-S1: Most profit (+4 more goals) | C115: 2 | D115: Crooks B | E115: 1 | F115: $500, Clamp | G115: 21289.2 | H115: 7612.77 | I115: 0.4194 | J115: 101.77 | K115: 500 | L115: 2304.2 | M115: survived | N115: =IF(H115=0,"",G115/H115) -> 2.7965117 | O115: =IF(OR(N108="",N108<=0,N115=""),"",N115/N108) -> 0.76101243 | P115: 9142.49 | Q115: 0.4194 | R115: 12146.71 | S115: 0.4519 | T115: =IF(AND(M115="survived",G115>0,K115<=500.005,I115<=0.4,ISNUMBER(P115),ISNUMBER(R115),P115>0,R115>0,Q115<=0.4,S115<=0.4),"yes","no") -> no
A116: M1 | B116: M1-S1: Most profit (+4 more goals) | C116: 2 | D116: Crooks B | E116: 1 | F116: $500, Start again | G116: 13040.42 | H116: 3287.22 | I116: 0.1919 | J116: 66.34 | K116: 494.81 | L116: 1518.75 | M116: survived | N116: =IF(H116=0,"",G116/H116) -> 3.9670056 | O116: =IF(OR(N108="",N108<=0,N116=""),"",N116/N108) -> 1.079538 | P116: 5831.62 | Q116: 0.1919 | R116: 7208.8 | S116: 0.2078 | T116: =IF(AND(M116="survived",G116>0,K116<=500.005,I116<=0.4,ISNUMBER(P116),ISNUMBER(R116),P116>0,R116>0,Q116<=0.4,S116<=0.4),"yes","no") -> yes
A117: M1 | B117: M1-S1: Most profit (+4 more goals) | C117: 2 | D117: Crooks B | E117: 1 | F117: $500, Stop trading | G117: 260.86 | H117: 1077.55 | I117: 0.095 | J117: 67.57 | K117: 342.52 | L117: 654.2 | M117: stopped by the cap | N117: =IF(H117=0,"",G117/H117) -> 0.24208621 | O117: =IF(OR(N108="",N108<=0,N117=""),"",N117/N108) -> 0.065878724 | P117: 260.86 | Q117: 0.095 | R117: 736.95 | S117: 0.0914 | T117: =IF(AND(M117="survived",G117>0,K117<=500.005,I117<=0.4,ISNUMBER(P117),ISNUMBER(R117),P117>0,R117>0,Q117<=0.4,S117<=0.4),"yes","no") -> no
A118: M1 | B118: M1-S1: Most profit (+4 more goals) | C118: 2 | D118: Crooks B | E118: 2 | F118: none | G118: 12796.59 | H118: 3503.4 | I118: 0.1896 | J118: 68.34 | K118: 851.13 | L118: 2166.01 | M118: survived | N118: =IF(H118=0,"",G118/H118) -> 3.6526203 | O118: =IF(OR(N108="",N108<=0,N118=""),"",N118/N108) -> 0.99398458 | P118: 5736.28 | Q118: 0.1896 | R118: 7040.91 | S118: 0.254 | T118: =IF(AND(M118="survived",G118>0,K118<=500.005,I118<=0.4,ISNUMBER(P118),ISNUMBER(R118),P118>0,R118>0,Q118<=0.4,S118<=0.4),"yes","no") -> no
A119: M1 | B119: M1-S1: Most profit (+4 more goals) | C119: 2 | D119: Crooks B | E119: 2 | F119: $500, Clamp | G119: 12496.98 | H119: 3921.87 | I119: 0.2893 | J119: 72.63 | K119: 500 | L119: 1914.78 | M119: survived | N119: =IF(H119=0,"",G119/H119) -> 3.186485 | O119: =IF(OR(N108="",N108<=0,N119=""),"",N119/N108) -> 0.86713557 | P119: 5539.64 | Q119: 0.2893 | R119: 6937.94 | S119: 0.2358 | T119: =IF(AND(M119="survived",G119>0,K119<=500.005,I119<=0.4,ISNUMBER(P119),ISNUMBER(R119),P119>0,R119>0,Q119<=0.4,S119<=0.4),"yes","no") -> yes
A120: M1 | B120: M1-S1: Most profit (+4 more goals) | C120: 2 | D120: Crooks B | E120: 2 | F120: $500, Start again | G120: 9183.3 | H120: 2609.98 | I120: 0.1925 | J120: 61.91 | K120: 498.91 | L120: 1503.83 | M120: survived | N120: =IF(H120=0,"",G120/H120) -> 3.5185327 | O120: =IF(OR(N108="",N108<=0,N120=""),"",N120/N108) -> 0.95749543 | P120: 3954.68 | Q120: 0.1925 | R120: 5209.23 | S120: 0.1705 | T120: =IF(AND(M120="survived",G120>0,K120<=500.005,I120<=0.4,ISNUMBER(P120),ISNUMBER(R120),P120>0,R120>0,Q120<=0.4,S120<=0.4),"yes","no") -> yes
A121: M1 | B121: M1-S1: Most profit (+4 more goals) | C121: 2 | D121: Crooks B | E121: 2 | F121: $500, Stop trading | G121: 1151.98 | H121: 2494.55 | I121: 0.184 | J121: 65.11 | K121: 498.91 | L121: 1207.06 | M121: stopped by the cap | N121: =IF(H121=0,"",G121/H121) -> 0.46179872 | O121: =IF(OR(N108="",N108<=0,N121=""),"",N121/N108) -> 0.12566891 | P121: 1151.98 | Q121: 0.184 | R121: 1590.61 | S121: 0.1597 | T121: =IF(AND(M121="survived",G121>0,K121<=500.005,I121<=0.4,ISNUMBER(P121),ISNUMBER(R121),P121>0,R121>0,Q121<=0.4,S121<=0.4),"yes","no") -> no
A122: M1 | B122: M1-S1: Most profit (+4 more goals) | C122: 2 | D122: Crooks B | E122: 3 | F122: none | G122: 9377.98 | H122: 2652.08 | I122: 0.154 | J122: 59.42 | K122: 425.53 | L122: 1331.63 | M122: survived | N122: =IF(H122=0,"",G122/H122) -> 3.5360849 | O122: =IF(OR(N108="",N108<=0,N122=""),"",N122/N108) -> 0.96227189 | P122: 4106.61 | Q122: 0.1137 | R122: 5256.23 | S122: 0.2024 | T122: =IF(AND(M122="survived",G122>0,K122<=500.005,I122<=0.4,ISNUMBER(P122),ISNUMBER(R122),P122>0,R122>0,Q122<=0.4,S122<=0.4),"yes","no") -> yes
A123: M1 | B123: M1-S1: Most profit (+4 more goals) | C123: 2 | D123: Crooks B | E123: 3 | F123: $500, Clamp | G123: 9377.98 | H123: 2652.08 | I123: 0.154 | J123: 59.42 | K123: 425.53 | L123: 1331.63 | M123: survived | N123: =IF(H123=0,"",G123/H123) -> 3.5360849 | O123: =IF(OR(N108="",N108<=0,N123=""),"",N123/N108) -> 0.96227189 | P123: 4106.61 | Q123: 0.1137 | R123: 5256.23 | S123: 0.2024 | T123: =IF(AND(M123="survived",G123>0,K123<=500.005,I123<=0.4,ISNUMBER(P123),ISNUMBER(R123),P123>0,R123>0,Q123<=0.4,S123<=0.4),"yes","no") -> yes
A124: M1 | B124: M1-S1: Most profit (+4 more goals) | C124: 2 | D124: Crooks B | E124: 3 | F124: $500, Start again | G124: 9377.98 | H124: 2652.08 | I124: 0.154 | J124: 59.42 | K124: 425.53 | L124: 1331.63 | M124: survived | N124: =IF(H124=0,"",G124/H124) -> 3.5360849 | O124: =IF(OR(N108="",N108<=0,N124=""),"",N124/N108) -> 0.96227189 | P124: 4106.61 | Q124: 0.1137 | R124: 5256.23 | S124: 0.2024 | T124: =IF(AND(M124="survived",G124>0,K124<=500.005,I124<=0.4,ISNUMBER(P124),ISNUMBER(R124),P124>0,R124>0,Q124<=0.4,S124<=0.4),"yes","no") -> yes
A125: M1 | B125: M1-S1: Most profit (+4 more goals) | C125: 2 | D125: Crooks B | E125: 3 | F125: $500, Stop trading | G125: 9377.98 | H125: 2652.08 | I125: 0.154 | J125: 59.42 | K125: 425.53 | L125: 1331.63 | M125: survived | N125: =IF(H125=0,"",G125/H125) -> 3.5360849 | O125: =IF(OR(N108="",N108<=0,N125=""),"",N125/N108) -> 0.96227189 | P125: 4106.61 | Q125: 0.1137 | R125: 5256.23 | S125: 0.2024 | T125: =IF(AND(M125="survived",G125>0,K125<=500.005,I125<=0.4,ISNUMBER(P125),ISNUMBER(R125),P125>0,R125>0,Q125<=0.4,S125<=0.4),"yes","no") -> yes
...

Sheet Summary
A1: Accuracy per timeframe, settings and year (FxPro MT5 GOLD, 2021-2026)
A2: Every value links to the year-total rows of the year x month sheets (green).
A3: Trades per day = trades / trading days in the data (2026 = 2 Jan - 2 Oct). Year rows: 2021: 258 days, 2022: 258 days, 2023: 257 days, 2024: 259 days, 2025: 258 days, 2026: 195 days.
A4: Timeframe | B4: Settings | C4: Year | D4: Trades | E4: Trades per day | F4: Win % | G4: Profitable % | H4: TP1 % | I4: TP2 % | J4: TP3 % | K4: TP4 % | L4: Total R after spread | M4: R per trade | N4: R per trade after spread | O4: Longest win streak | P4: Longest losing streak
A5: M1 | B5: Default settings | C5: 2021 | D5: ='M1 default'!C18 -> 1290 | E5: =D5/258 -> 5 | F5: ='M1 default'!P18 -> 0.28449612 | G5: ='M1 default'!Q18 -> 0.28449612 | H5: ='M1 default'!R18 -> 0.54728682 | I5: ='M1 default'!S18 -> 0.43953488 | J5: ='M1 default'!T18 -> 0.35271318 | K5: ='M1 default'!U18 -> 0.28449612 | L5: ='M1 default'!M18 -> -964.0218 | M5: ='M1 default'!V18 -> -0.14651163 | N5: ='M1 default'!W18 -> -0.74730372 | O5: ='M1 default'!N18 -> 5 | P5: ='M1 default'!O18 -> 22
A6: M1 | B6: Default settings | C6: 2022 | D6: ='M1 default'!C31 -> 1290 | E6: =D6/258 -> 5 | F6: ='M1 default'!P31 -> 0.3124031 | G6: ='M1 default'!Q31 -> 0.3124031 | H6: ='M1 default'!R31 -> 0.57209302 | I6: ='M1 default'!S31 -> 0.45116279 | J6: ='M1 default'!T31 -> 0.36511628 | K6: ='M1 default'!U31 -> 0.3124031 | L6: ='M1 default'!M31 -> -843.493 | M6: ='M1 default'!V31 -> -0.062790698 | N6: ='M1 default'!W31 -> -0.65387054 | O6: ='M1 default'!N31 -> 6 | P6: ='M1 default'!O31 -> 16
A7: M1 | B7: Default settings | C7: 2023 | D7: ='M1 default'!C44 -> 1285 | E7: =D7/257 -> 5 | F7: ='M1 default'!P44 -> 0.32217899 | G7: ='M1 default'!Q44 -> 0.32217899 | H7: ='M1 default'!R44 -> 0.58988327 | I7: ='M1 default'!S44 -> 0.47081712 | J7: ='M1 default'!T44 -> 0.38599222 | K7: ='M1 default'!U44 -> 0.32217899 | L7: ='M1 default'!M44 -> -835.8046 | M7: ='M1 default'!V44 -> -0.033463035 | N7: ='M1 default'!W44 -> -0.6504316 | O7: ='M1 default'!N44 -> 6 | P7: ='M1 default'!O44 -> 17
A8: M1 | B8: Default settings | C8: 2024 | D8: ='M1 default'!C57 -> 1295 | E8: =D8/259 -> 5 | F8: ='M1 default'!P57 -> 0.30810811 | G8: ='M1 default'!Q57 -> 0.30810811 | H8: ='M1 default'!R57 -> 0.58069498 | I8: ='M1 default'!S57 -> 0.47413127 | J8: ='M1 default'!T57 -> 0.37065637 | K8: ='M1 default'!U57 -> 0.30810811 | L8: ='M1 default'!M57 -> -506.2309 | M8: ='M1 default'!V57 -> -0.075675676 | N8: ='M1 default'!W57 -> -0.39091189 | O8: ='M1 default'!N57 -> 5 | P8: ='M1 default'!O57 -> 20
A9: M1 | B9: Default settings | C9: 2025 | D9: ='M1 default'!C70 -> 1290 | E9: =D9/258 -> 5 | F9: ='M1 default'!P70 -> 0.34031008 | G9: ='M1 default'!Q70 -> 0.34031008 | H9: ='M1 default'!R70 -> 0.60232558 | I9: ='M1 default'!S70 -> 0.49689922 | J9: ='M1 default'!T70 -> 0.41007752 | K9: ='M1 default'!U70 -> 0.34031008 | L9: ='M1 default'!M70 -> -161.8691 | M9: ='M1 default'!V70 -> 0.020930233 | N9: ='M1 default'!W70 -> -0.12547992 | O9: ='M1 default'!N70 -> 6 | P9: ='M1 default'!O70 -> 19
A10: M1 | B10: Default settings | C10: 2026 | D10: ='M1 default'!C81 -> 975 | E10: =D10/195 -> 5 | F10: ='M1 default'!P81 -> 0.32717949 | G10: ='M1 default'!Q81 -> 0.32717949 | H10: ='M1 default'!R81 -> 0.61128205 | I10: ='M1 default'!S81 -> 0.49128205 | J10: ='M1 default'!T81 -> 0.39487179 | K10: ='M1 default'!U81 -> 0.32717949 | L10: ='M1 default'!M81 -> -95.7556 | M10: ='M1 default'!V81 -> -0.018461538 | N10: ='M1 default'!W81 -> -0.098210872 | O10: ='M1 default'!N81 -> 7 | P10: ='M1 default'!O81 -> 17
A11: M1 | B11: Default settings | C11: 2021-2026 | D11: ='M1 default'!C82 -> 7425 | E11: =D11/1485 -> 5 | F11: ='M1 default'!P82 -> 0.3152862 | G11: ='M1 default'!Q82 -> 0.3152862 | H11: ='M1 default'!R82 -> 0.58276094 | I11: ='M1 default'!S82 -> 0.46976431 | J11: ='M1 default'!T82 -> 0.37925926 | K11: ='M1 default'!U82 -> 0.3152862 | L11: ='M1 default'!M82 -> -3407.175 | M11: ='M1 default'!V82 -> -0.054141414 | N11: ='M1 default'!W82 -> -0.45887879 | O11: ='M1 default'!N82 -> 7 | P11: ='M1 default'!O82 -> 22
A13: M1 | B13: Best settings (profit) | C13: 2021 | D13: ='M1 best'!C18 -> 317 | E13: =D13/258 -> 1.2286822 | F13: ='M1 best'!P18 -> 0.3533123 | G13: ='M1 best'!Q18 -> 0.3533123 | H13: ='M1 best'!R18 -> 0.62776025 | I13: ='M1 best'!S18 -> 0.50473186 | J13: ='M1 best'!T18 -> 0.41324921 | K13: ='M1 best'!U18 -> 0.3533123 | L13: ='M1 best'!M18 -> -2.2631 | M13: ='M1 best'!V18 -> 0.059936909 | N13: ='M1 best'!W18 -> -0.0071391167 | O13: ='M1 best'!N18 -> 3 | P13: ='M1 best'!O18 -> 10
A14: M1 | B14: Best settings (profit) | C14: 2022 | D14: ='M1 best'!C31 -> 334 | E14: =D14/258 -> 1.2945736 | F14: ='M1 best'!P31 -> 0.36826347 | G14: ='M1 best'!Q31 -> 0.36826347 | H14: ='M1 best'!R31 -> 0.65269461 | I14: ='M1 best'!S31 -> 0.54491018 | J14: ='M1 best'!T31 -> 0.4491018 | K14: ='M1 best'!U31 -> 0.36826347 | L14: ='M1 best'!M31 -> 13.5364 | M14: ='M1 best'!V31 -> 0.10479042 | N14: ='M1 best'!W31 -> 0.040528144 | O14: ='M1 best'!N31 -> 5 | P14: ='M1 best'!O31 -> 12
A15: M1 | B15: Best settings (profit) | C15: 2023 | D15: ='M1 best'!C44 -> 329 | E15: =D15/257 -> 1.2801556 | F15: ='M1 best'!P44 -> 0.39817629 | G15: ='M1 best'!Q44 -> 0.39817629 | H15: ='M1 best'!R44 -> 0.67781155 | I15: ='M1 best'!S44 -> 0.56231003 | J15: ='M1 best'!T44 -> 0.45896657 | K15: ='M1 best'!U44 -> 0.39817629 | L15: ='M1 best'!M44 -> 42.1324 | M15: ='M1 best'!V44 -> 0.19452888 | N15: ='M1 best'!W44 -> 0.12806201 | O15: ='M1 best'!N44 -> 8 | P15: ='M1 best'!O44 -> 8
A16: M1 | B16: Best settings (profit) | C16: 2024 | D16: ='M1 best'!C57 -> 344 | E16: =D16/259 -> 1.3281853 | F16: ='M1 best'!P57 -> 0.34011628 | G16: ='M1 best'!Q57 -> 0.34011628 | H16: ='M1 best'!R57 -> 0.57848837 | I16: ='M1 best'!S57 -> 0.49127907 | J16: ='M1 best'!T57 -> 0.39244186 | K16: ='M1 best'!U57 -> 0.34011628 | L16: ='M1 best'!M57 -> -0.8116 | M16: ='M1 best'!V57 -> 0.020348837 | N16: ='M1 best'!W57 -> -0.0023593023 | O16: ='M1 best'!N57 -> 4 | P16: ='M1 best'!O57 -> 8
A17: M1 | B17: Best settings (profit) | C17: 2025 | D17: ='M1 best'!C70 -> 361 | E17: =D17/258 -> 1.3992248 | F17: ='M1 best'!P70 -> 0.37119114 | G17: ='M1 best'!Q70 -> 0.37119114 | H17: ='M1 best'!R70 -> 0.61772853 | I17: ='M1 best'!S70 -> 0.50692521 | J17: ='M1 best'!T70 -> 0.43490305 | K17: ='M1 best'!U70 -> 0.37119114 | L17: ='M1 best'!M70 -> 35.3455 | M17: ='M1 best'!V70 -> 0.11357341 | N17: ='M1 best'!W70 -> 0.097909972 | O17: ='M1 best'!N70 -> 5 | P17: ='M1 best'!O70 -> 12
A18: M1 | B18: Best settings (profit) | C18: 2026 | D18: ='M1 best'!C81 -> 273 | E18: =D18/195 -> 1.4 | F18: ='M1 best'!P81 -> 0.36630037 | G18: ='M1 best'!Q81 -> 0.36630037 | H18: ='M1 best'!R81 -> 0.62637363 | I18: ='M1 best'!S81 -> 0.51648352 | J18: ='M1 best'!T81 -> 0.4029304 | K18: ='M1 best'!U81 -> 0.36630037 | L18: ='M1 best'!M81 -> 24.2134 | M18: ='M1 best'!V81 -> 0.098901099 | N18: ='M1 best'!W81 -> 0.088693773 | O18: ='M1 best'!N81 -> 4 | P18: ='M1 best'!O81 -> 14
A19: M1 | B19: Best settings (profit) | C19: 2021-2026 | D19: ='M1 best'!C82 -> 1958 | E19: =D19/1485 -> 1.3185185 | F19: ='M1 best'!P82 -> 0.36618999 | G19: ='M1 best'!Q82 -> 0.36618999 | H19: ='M1 best'!R82 -> 0.62972421 | I19: ='M1 best'!S82 -> 0.52093973 | J19: ='M1 best'!T82 -> 0.42594484 | K19: ='M1 best'!U82 -> 0.36618999 | L19: ='M1 best'!M82 -> 112.153 | M19: ='M1 best'!V82 -> 0.098569969 | N19: ='M1 best'!W82 -> 0.057279367 | O19: ='M1 best'!N82 -> 8 | P19: ='M1 best'!O82 -> 14
A21: M1 | B21: Best settings with short losing streaks | C21: 2021 | D21: ='M1 low-streak'!C18 -> 291 | E21: =D21/258 -> 1.127907 | F21: ='M1 low-streak'!P18 -> 0.34707904 | G21: ='M1 low-streak'!Q18 -> 0.34707904 | H21: ='M1 low-streak'!R18 -> 0.62542955 | I21: ='M1 low-streak'!S18 -> 0.50859107 | J21: ='M1 low-streak'!T18 -> 0.41237113 | K21: ='M1 low-streak'!U18 -> 0.34707904 | L21: ='M1 low-streak'!M18 -> -7.7207 | M21: ='M1 low-streak'!V18 -> 0.041237113 | N21: ='M1 low-streak'!W18 -> -0.026531615 | O21: ='M1 low-streak'!N18 -> 3 | P21: ='M1 low-streak'!O18 -> 10
A22: M1 | B22: Best settings with short losing streaks | C22: 2022 | D22: ='M1 low-streak'!C31 -> 311 | E22: =D22/258 -> 1.2054264 | F22: ='M1 low-streak'!P31 -> 0.37299035 | G22: ='M1 low-streak'!Q31 -> 0.37299035 | H22: ='M1 low-streak'!R31 -> 0.65594855 | I22: ='M1 low-streak'!S31 -> 0.54340836 | J22: ='M1 low-streak'!T31 -> 0.4437299 | K22: ='M1 low-streak'!U31 -> 0.37299035 | L22: ='M1 low-streak'!M31 -> 16.5079 | M22: ='M1 low-streak'!V31 -> 0.11897106 | N22: ='M1 low-streak'!W31 -> 0.053080064 | O22: ='M1 low-streak'!N31 -> 6 | P22: ='M1 low-streak'!O31 -> 10
A23: M1 | B23: Best settings with short losing streaks | C23: 2023 | D23: ='M1 low-streak'!C44 -> 307 | E23: =D23/257 -> 1.1945525 | F23: ='M1 low-streak'!P44 -> 0.37459283 | G23: ='M1 low-streak'!Q44 -> 0.37459283 | H23: ='M1 low-streak'!R44 -> 0.65798046 | I23: ='M1 low-streak'!S44 -> 0.54397394 | J23: ='M1 low-streak'!T44 -> 0.43648208 | K23: ='M1 low-streak'!U44 -> 0.37459283 | L23: ='M1 low-streak'!M44 -> 17.2141 | M23: ='M1 low-streak'!V44 -> 0.1237785 | N23: ='M1 low-streak'!W44 -> 0.056071987 | O23: ='M1 low-streak'!N44 -> 7 | P23: ='M1 low-streak'!O44 -> 9
A24: M1 | B24: Best settings with short losing streaks | C24: 2024 | D24: ='M1 low-streak'!C57 -> 314 | E24: =D24/259 -> 1.2123552 | F24: ='M1 low-streak'!P57 -> 0.34076433 | G24: ='M1 low-streak'!Q57 -> 0.34076433 | H24: ='M1 low-streak'!R57 -> 0.57643312 | I24: ='M1 low-streak'!S57 -> 0.49044586 | J24: ='M1 low-streak'!T57 -> 0.39808917 | K24: ='M1 low-streak'!U57 -> 0.34076433 | L24: ='M1 low-streak'!M57 -> -0.1972 | M24: ='M1 low-streak'!V57 -> 0.022292994 | N24: ='M1 low-streak'!W57 -> -0.00062802548 | O24: ='M1 low-streak'!N57 -> 4 | P24: ='M1 low-streak'!O57 -> 9
A25: M1 | B25: Best settings with short losing streaks | C25: 2025 | D25: ='M1 low-streak'!C70 -> 329 | E25: =D25/258 -> 1.2751938 | F25: ='M1 low-streak'!P70 -> 0.38905775 | G25: ='M1 low-streak'!Q70 -> 0.38905775 | H25: ='M1 low-streak'!R70 -> 0.62006079 | I25: ='M1 low-streak'!S70 -> 0.50759878 | J25: ='M1 low-streak'!T70 -> 0.44072948 | K25: ='M1 low-streak'!U70 -> 0.38905775 | L25: ='M1 low-streak'!M70 -> 49.8029 | M25: ='M1 low-streak'!V70 -> 0.16717325 | N25: ='M1 low-streak'!W70 -> 0.1513766 | O25: ='M1 low-streak'!N70 -> 5 | P25: ='M1 low-streak'!O70 -> 11
A26: M1 | B26: Best settings with short losing streaks | C26: 2026 | D26: ='M1 low-streak'!C81 -> 250 | E26: =D26/195 -> 1.2820513 | F26: ='M1 low-streak'!P81 -> 0.36 | G26: ='M1 low-streak'!Q81 -> 0.36 | H26: ='M1 low-streak'!R81 -> 0.62 | I26: ='M1 low-streak'!S81 -> 0.512 | J26: ='M1 low-streak'!T81 -> 0.408 | K26: ='M1 low-streak'!U81 -> 0.36 | L26: ='M1 low-streak'!M81 -> 17.3958 | M26: ='M1 low-streak'!V81 -> 0.08 | N26: ='M1 low-streak'!W81 -> 0.0695832 | O26: ='M1 low-streak'!N81 -> 5 | P26: ='M1 low-streak'!O81 -> 12
A27: M1 | B27: Best settings with short losing streaks | C27: 2021-2026 | D27: ='M1 low-streak'!C82 -> 1802 | E27: =D27/1485 -> 1.213468 | F27: ='M1 low-streak'!P82 -> 0.36459489 | G27: ='M1 low-streak'!Q82 -> 0.36459489 | H27: ='M1 low-streak'!R82 -> 0.62597114 | I27: ='M1 low-streak'!S82 -> 0.51775805 | J27: ='M1 low-streak'!T82 -> 0.42397336 | K27: ='M1 low-streak'!U82 -> 0.36459489 | L27: ='M1 low-streak'!M82 -> 93.0028 | M27: ='M1 low-streak'!V82 -> 0.093784684 | N27: ='M1 low-streak'!W82 -> 0.051610877 | O27: ='M1 low-streak'!N82 -> 7 | P27: ='M1 low-streak'!O82 -> 12
A29: M5 | B29: Default settings | C29: 2021 | D29: ='M5 default'!C18 -> 1228 | E29: =D29/258 -> 4.7596899 | F29: ='M5 default'!P18 -> 0.31840391 | G29: ='M5 default'!Q18 -> 0.31840391 | H29: ='M5 default'!R18 -> 0.59283388 | I29: ='M5 default'!S18 -> 0.48859935 | J29: ='M5 default'!T18 -> 0.37459283 | K29: ='M5 default'!U18 -> 0.31840391 | L29: ='M5 default'!M18 -> -260.3112 | M29: ='M5 default'!V18 -> -0.044788274 | N29: ='M5 default'!W18 -> -0.2119798 | O29: ='M5 default'!N18 -> 7 | P29: ='M5 default'!O18 -> 13
A30: M5 | B30: Default settings | C30: 2022 | D30: ='M5 default'!C31 -> 1181 | E30: =D30/258 -> 4.5775194 | F30: ='M5 default'!P31 -> 0.33446232 | G30: ='M5 default'!Q31 -> 0.33446232 | H30: ='M5 default'!R31 -> 0.6257409 | I30: ='M5 default'!S31 -> 0.51143099 | J30: ='M5 default'!T31 -> 0.41066892 | K30: ='M5 default'!U31 -> 0.33446232 | L30: ='M5 default'!M31 -> -178.1159 | M30: ='M5 default'!V31 -> 0.0033869602 | N30: ='M5 default'!W31 -> -0.15081787 | O30: ='M5 default'!N31 -> 5 | P30: ='M5 default'!O31 -> 18
A31: M5 | B31: Default settings | C31: 2023 | D31: ='M5 default'!C44 -> 1199 | E31: =D31/257 -> 4.6653696 | F31: ='M5 default'!P44 -> 0.32276897 | G31: ='M5 default'!Q44 -> 0.32276897 | H31: ='M5 default'!R44 -> 0.58048374 | I31: ='M5 default'!S44 -> 0.47539616 | J31: ='M5 default'!T44 -> 0.38698916 | K31: ='M5 default'!U44 -> 0.32276897 | L31: ='M5 default'!M44 -> -249.41 | M31: ='M5 default'!V44 -> -0.031693078 | N31: ='M5 default'!W44 -> -0.20801501 | O31: ='M5 default'!N44 -> 5 | P31: ='M5 default'!O44 -> 19
A32: M5 | B32: Default settings | C32: 2024 | D32: ='M5 default'!C57 -> 1212 | E32: =D32/259 -> 4.6795367 | F32: ='M5 default'!P57 -> 0.33745875 | G32: ='M5 default'!Q57 -> 0.33745875 | H32: ='M5 default'!R57 -> 0.62211221 | I32: ='M5 default'!S57 -> 0.49834983 | J32: ='M5 default'!T57 -> 0.40759076 | K32: ='M5 default'!U57 -> 0.33745875 | L32: ='M5 default'!M57 -> -69.0067 | M32: ='M5 default'!V57 -> 0.012376238 | N32: ='M5 default'!W57 -> -0.056936221 | O32: ='M5 default'!N57 -> 5 | P32: ='M5 default'!O57 -> 13
A33: M5 | B33: Default settings | C33: 2025 | D33: ='M5 default'!C70 -> 1221 | E33: =D33/258 -> 4.7325581 | F33: ='M5 default'!P70 -> 0.34643735 | G33: ='M5 default'!Q70 -> 0.34643735 | H33: ='M5 default'!R70 -> 0.62080262 | I33: ='M5 default'!S70 -> 0.51105651 | J33: ='M5 default'!T70 -> 0.41195741 | K33: ='M5 default'!U70 -> 0.34643735 | L33: ='M5 default'!M70 -> 2.5287 | M33: ='M5 default'!V70 -> 0.039312039 | N33: ='M5 default'!W70 -> 0.0020710074 | O33: ='M5 default'!N70 -> 5 | P33: ='M5 default'!O70 -> 14
A34: M5 | B34: Default settings | C34: 2026 | D34: ='M5 default'!C81 -> 917 | E34: =D34/195 -> 4.7025641 | F34: ='M5 default'!P81 -> 0.33696838 | G34: ='M5 default'!Q81 -> 0.33696838 | H34: ='M5 default'!R81 -> 0.61068702 | I34: ='M5 default'!S81 -> 0.50054526 | J34: ='M5 default'!T81 -> 0.39585605 | K34: ='M5 default'!U81 -> 0.33696838 | L34: ='M5 default'!M81 -> -9.823 | M34: ='M5 default'!V81 -> 0.010905125 | N34: ='M5 default'!W81 -> -0.010712105 | O34: ='M5 default'!N81 -> 5 | P34: ='M5 default'!O81 -> 16
A35: M5 | B35: Default settings | C35: 2021-2026 | D35: ='M5 default'!C82 -> 6958 | E35: =D35/1485 -> 4.6855219 | F35: ='M5 default'!P82 -> 0.33256683 | G35: ='M5 default'!Q82 -> 0.33256683 | H35: ='M5 default'!R82 -> 0.60865191 | I35: ='M5 default'!S82 -> 0.49741305 | J35: ='M5 default'!T82 -> 0.39795918 | K35: ='M5 default'!U82 -> 0.33256683 | L35: ='M5 default'!M82 -> -764.1381 | M35: ='M5 default'!V82 -> -0.0022995114 | N35: ='M5 default'!W82 -> -0.10982151 | O35: ='M5 default'!N82 -> 7 | P35: ='M5 default'!O82 -> 19
A37: M5 | B37: Best settings (profit) | C37: 2021 | D37: ='M5 best'!C18 -> 230 | E37: =D37/258 -> 0.89147287 | F37: ='M5 best'!P18 -> 0.26956522 | G37: ='M5 best'!Q18 -> 0.26956522 | H37: ='M5 best'!R18 -> 0.62608696 | I37: ='M5 best'!S18 -> 0.52608696 | J37: ='M5 best'!T18 -> 0.41304348 | K37: ='M5 best'!U18 -> 0.26956522 | L37: ='M5 best'!M18 -> -25.4143 | M37: ='M5 best'!V18 -> -0.056521739 | N37: ='M5 best'!W18 -> -0.11049696 | O37: ='M5 best'!N18 -> 3 | P37: ='M5 best'!O18 -> 21
A38: M5 | B38: Best settings (profit) | C38: 2022 | D38: ='M5 best'!C31 -> 252 | E38: =D38/258 -> 0.97674419 | F38: ='M5 best'!P31 -> 0.3452381 | G38: ='M5 best'!Q31 -> 0.3452381 | H38: ='M5 best'!R31 -> 0.62301587 | I38: ='M5 best'!S31 -> 0.52380952 | J38: ='M5 best'!T31 -> 0.44047619 | K38: ='M5 best'!U31 -> 0.3452381 | L38: ='M5 best'!M31 -> 37.9106 | M38: ='M5 best'!V31 -> 0.20833333 | N38: ='M5 best'!W31 -> 0.15043889 | O38: ='M5 best'!N31 -> 5 | P38: ='M5 best'!O31 -> 10
A39: M5 | B39: Best settings (profit) | C39: 2023 | D39: ='M5 best'!C44 -> 250 | E39: =D39/257 -> 0.97276265 | F39: ='M5 best'!P44 -> 0.368 | G39: ='M5 best'!Q44 -> 0.368 | H39: ='M5 best'!R44 -> 0.604 | I39: ='M5 best'!S44 -> 0.524 | J39: ='M5 best'!T44 -> 0.456 | K39: ='M5 best'!U44 -> 0.368 | L39: ='M5 best'!M44 -> 58.4617 | M39: ='M5 best'!V44 -> 0.288 | N39: ='M5 best'!W44 -> 0.2338468 | O39: ='M5 best'!N44 -> 3 | P39: ='M5 best'!O44 -> 8
A40: M5 | B40: Best settings (profit) | C40: 2024 | D40: ='M5 best'!C57 -> 283 | E40: =D40/259 -> 1.0926641 | F40: ='M5 best'!P57 -> 0.30035336 | G40: ='M5 best'!Q57 -> 0.30035336 | H40: ='M5 best'!R57 -> 0.63957597 | I40: ='M5 best'!S57 -> 0.50530035 | J40: ='M5 best'!T57 -> 0.40989399 | K40: ='M5 best'!U57 -> 0.30035336 | L40: ='M5 best'!M57 -> 8.6974 | M40: ='M5 best'!V57 -> 0.051236749 | N40: ='M5 best'!W57 -> 0.030732862 | O40: ='M5 best'!N57 -> 5 | P40: ='M5 best'!O57 -> 16
A41: M5 | B41: Best settings (profit) | C41: 2025 | D41: ='M5 best'!C70 -> 262 | E41: =D41/258 -> 1.0155039 | F41: ='M5 best'!P70 -> 0.35877863 | G41: ='M5 best'!Q70 -> 0.35877863 | H41: ='M5 best'!R70 -> 0.63740458 | I41: ='M5 best'!S70 -> 0.54198473 | J41: ='M5 best'!T70 -> 0.45419847 | K41: ='M5 best'!U70 -> 0.35877863 | L41: ='M5 best'!M70 -> 63.5504 | M41: ='M5 best'!V70 -> 0.25572519 | N41: ='M5 best'!W70 -> 0.24255878 | O41: ='M5 best'!N70 -> 7 | P41: ='M5 best'!O70 -> 9
A42: M5 | B42: Best settings (profit) | C42: 2026 | D42: ='M5 best'!C81 -> 195 | E42: =D42/195 -> 1 | F42: ='M5 best'!P81 -> 0.26666667 | G42: ='M5 best'!Q81 -> 0.26666667 | H42: ='M5 best'!R81 -> 0.64615385 | I42: ='M5 best'!S81 -> 0.51282051 | J42: ='M5 best'!T81 -> 0.38461538 | K42: ='M5 best'!U81 -> 0.26666667 | L42: ='M5 best'!M81 -> -14.8276 | M42: ='M5 best'!V81 -> -0.066666667 | N42: ='M5 best'!W81 -> -0.076038974 | O42: ='M5 best'!N81 -> 4 | P42: ='M5 best'!O81 -> 13
A43: M5 | B43: Best settings (profit) | C43: 2021-2026 | D43: ='M5 best'!C82 -> 1472 | E43: =D43/1485 -> 0.99124579 | F43: ='M5 best'!P82 -> 0.32065217 | G43: ='M5 best'!Q82 -> 0.32065217 | H43: ='M5 best'!R82 -> 0.62907609 | I43: ='M5 best'!S82 -> 0.52241848 | J43: ='M5 best'!T82 -> 0.42798913 | K43: ='M5 best'!U82 -> 0.32065217 | L43: ='M5 best'!M82 -> 128.3782 | M43: ='M5 best'!V82 -> 0.12228261 | N43: ='M5 best'!W82 -> 0.087213451 | O43: ='M5 best'!N82 -> 7 | P43: ='M5 best'!O82 -> 21
A45: M5 | B45: Best settings with short losing streaks | C45: 2021 | D45: ='M5 low-streak'!C18 -> 264 | E45: =D45/258 -> 1.0232558 | F45: ='M5 low-streak'!P18 -> 0.1780303 | G45: ='M5 low-streak'!Q18 -> 0.53030303 | H45: ='M5 low-streak'!R18 -> 0.625 | I45: ='M5 low-streak'!S18 -> 0.53030303 | J45: ='M5 low-streak'!T18 -> 0.24242424 | K45: ='M5 low-streak'!U18 -> 0.1780303 | L45: ='M5 low-streak'!M18 -> 11.7172 | M45: ='M5 low-streak'!V18 -> 0.097727273 | N45: ='M5 low-streak'!W18 -> 0.044383333 | O45: ='M5 low-streak'!N18 -> 7 | P45: ='M5 low-streak'!O18 -> 6
A46: M5 | B46: Best settings with short losing streaks | C46: 2022 | D46: ='M5 low-streak'!C31 -> 288 | E46: =D46/258 -> 1.1162791 | F46: ='M5 low-streak'!P31 -> 0.17013889 | G46: ='M5 low-streak'!Q31 -> 0.54166667 | H46: ='M5 low-streak'!R31 -> 0.64236111 | I46: ='M5 low-streak'!S31 -> 0.54166667 | J46: ='M5 low-streak'!T31 -> 0.28125 | K46: ='M5 low-streak'!U31 -> 0.17013889 | L46: ='M5 low-streak'!M31 -> 13.4914 | M46: ='M5 low-streak'!V31 -> 0.10486111 | N46: ='M5 low-streak'!W31 -> 0.046845139 | O46: ='M5 low-streak'!N31 -> 8 | P46: ='M5 low-streak'!O31 -> 7
A47: M5 | B47: Best settings with short losing streaks | C47: 2023 | D47: ='M5 low-streak'!C44 -> 297 | E47: =D47/257 -> 1.155642 | F47: ='M5 low-streak'!P44 -> 0.1952862 | G47: ='M5 low-streak'!Q44 -> 0.51851852 | H47: ='M5 low-streak'!R44 -> 0.6026936 | I47: ='M5 low-streak'!S44 -> 0.51851852 | J47: ='M5 low-streak'!T44 -> 0.27272727 | K47: ='M5 low-streak'!U44 -> 0.1952862 | L47: ='M5 low-streak'!M44 -> 14.3111 | M47: ='M5 low-streak'!V44 -> 0.1030303 | N47: ='M5 low-streak'!W44 -> 0.048185522 | O47: ='M5 low-streak'!N44 -> 7 | P47: ='M5 low-streak'!O44 -> 7
A48: M5 | B48: Best settings with short losing streaks | C48: 2024 | D48: ='M5 low-streak'!C57 -> 320 | E48: =D48/259 -> 1.2355212 | F48: ='M5 low-streak'!P57 -> 0.171875 | G48: ='M5 low-streak'!Q57 -> 0.509375 | H48: ='M5 low-streak'!R57 -> 0.63125 | I48: ='M5 low-streak'!S57 -> 0.509375 | J48: ='M5 low-streak'!T57 -> 0.278125 | K48: ='M5 low-streak'!U57 -> 0.171875 | L48: ='M5 low-streak'!M57 -> 11.1997 | M48: ='M5 low-streak'!V57 -> 0.055625 | N48: ='M5 low-streak'!W57 -> 0.034999062 | O48: ='M5 low-streak'!N57 -> 7 | P48: ='M5 low-streak'!O57 -> 7
